Workbook
Name A_Limit: Inputs!$C$19
Name B_Limit: Inputs!$C$20
Name BestClass: Backtest!$H$5:$H$13
Name BestFlat: Backtest!$W$5:$W$13
Name BestMethod: Backtest!$V$5:$V$13
Name BtAbsErr: Backtest!$D$5:$D$604
Name BtActual: Backtest!$C$5:$C$604
Name BtClass: Backtest!$F$5:$F$604
Name BtCode: Backtest!$A$5:$A$604
Name BtErr: Backtest!$E$5:$E$604
Name BtMethod: Backtest!$B$5:$B$604
Name ClassList: Inputs!$B$29:$B$31
Name ClassSL: Inputs!$C$29:$C$31
Name ClsABC: ABC_XYZ!$F$5:$F$154
Name ClsClass: ABC_XYZ!$K$5:$K$154
Name ClsCode: ABC_XYZ!$A$5:$A$154
Name ClsSeasonal: ABC_XYZ!$M$5:$M$154
Name ClsValue: ABC_XYZ!$C$5:$C$154
Name ClsXYZ: ABC_XYZ!$J$5:$J$154
Name CostRatio: Inputs!$C$15
Name CurrentCover: Inputs!$C$16
Name DemandAll: Demand!$C$5:$DA$154
Name DemandCodes: Demand!$A$5:$A$154
Name DemandLast52: Demand!$BB$5:$DA$154
Name DemandPeak2010: Demand!$AP$5:$BB$154
Name DemandTrain: Demand!$C$5:$CO$154
Name FutCode: Forecast_Future!$A$5:$A$7204
Name FutHorizon: Forecast_Future!$C$5:$C$7204
Name FutMethod: Forecast_Future!$B$5:$B$7204
Name FutUnits: Forecast_Future!$E$5:$E$7204
Name HoldingRate: Inputs!$C$13
Name LeadTime: Inputs!$C$12
Name OrderCost: Inputs!$C$14
Name ParamCodes: Model_Params!$A$5:$A$154
Name PolClass: Policy!$C$5:$C$154
Name PolCode: Policy!$A$5:$A$154
Name PolCost: Policy!$G$5:$G$154
Name PolCur: Policy!$T$5:$T$154
Name PolFreed: Policy!$V$5:$V$154
Name PolHold: Policy!$Z$5:$Z$154
Name PolMethod: Policy!$D$5:$D$154
Name PolOrdCost: Policy!$AA$5:$AA$154
Name PolOrder: Policy!$Y$5:$Y$154
Name PolRank: Policy!$AC$5:$AC$154
Name PolRec: Policy!$U$5:$U$154
Name PolRisk: Policy!$X$5:$X$154
Name PolSD: Policy!$F$5:$F$154
Name PolShort: Policy!$AB$5:$AB$154
Name PolSS: Policy!$K$5:$K$154
Name PolStatus: Policy!$W$5:$W$154
Name SeasonalLimit: Inputs!$C$25
Name ServiceLevel: Inputs!$C$5
Name SKUList: SKU_Data!$A$5:$A$154
Name SL_A: Inputs!$C$8
Name SL_B: Inputs!$C$9
Name SL_C: Inputs!$C$10
Name WeeksPerYear: Inputs!$C$17
Name X_Limit: Inputs!$C$22
Name Y_Limit: Inputs!$C$23
Name Z: Inputs!$C$6

Sheet Start
A1: Inventory Planning & Demand Forecasting Model
A2: UK online gift retailer (UCI Online Retail II, real data) · 150 top SKUs · 103 weeks Dec-2009 to Nov-2011 · built for learning
B4: What it answers | C4: How much stock should we hold for each product, and when should we reorder, so we don't run out or overstock?
B5: How to use it | C5: 1) Change the yellow cells on the Inputs sheet (service level, lead time, costs). Every sheet recalculates. 2) Pick a product in the drop-down on the Forecast sheet to see its four forecasts and their accuracy. 3) Read the results on Summary and Charts; the full SKU list with reorder points is on Policy.
B6: Colour code | C6: Yellow cell, blue text = an input you can change. Grey cells = data from the CSVs (don't type over). Everything else = a formula. Click any cell and read the formula bar.
B8: SHEETS
B9: Inputs | C9: All assumptions in one place: service level (and z), lead time, holding and ordering cost, unit cost, current stock, class limits.
B10: ABC_XYZ | C10: ABC by value (cumulative share, SUMIFS), XYZ by demand variability (CV = STDEV.S / AVERAGE), the 9-box matrix (COUNTIFS).
B11: Forecast | C11: One SKU at a time (drop-down): naive, moving average, simple exponential smoothing and Holt-Winters written out week by week, plus Excel's own FORECAST.ETS. 12-week backtest with WAPE, MAPE and bias.
B12: Backtest | C12: Errors of all four methods for all 150 SKUs (from notebook 02), summed by ABC-XYZ class with SUMIFS. Picks the best method per class.
B13: Policy | C13: Every SKU: safety stock, reorder point, EOQ, min/max, weeks of cover, current vs recommended stock, stock-out risk, order suggestion.
B14: Summary | C14: Headline numbers, results by class, the service level vs cost trade-off and the top-10 reorder list.
B15: Charts | C15: Forecast vs actual for the selected SKU, stock by class, the trade-off curve, the 9-box and the Pareto curve.
B16: Demand, SKU_Data, Model_Params, Forecast_Future | C16: Data sheets (grey): weekly demand, SKU facts, fitted smoothing parameters, future forecasts.
B18: KEY FORMULAS
B19: Safety stock | C19: Safety stock = z × σ(weekly demand) × √(lead time in weeks), z = NORM.S.INV(service level)
B20: Reorder point (Min) | C20: ROP = forecast demand during the lead time + safety stock
B21: EOQ | C21: EOQ = √(2 × annual demand × ordering cost ÷ (holding cost % × unit cost))
B22: Max | C22: Max = reorder point + EOQ. Average stock = safety stock + EOQ ÷ 2. Weeks of cover = stock ÷ average weekly demand
B24: ASSUMPTIONS | C24: The data has no lead times, costs or stock levels, so these are assumptions (see Inputs and the README): lead time 3 weeks, holding cost 25% a year, £50 per order, unit cost 60% of selling price, current stock = 8 weeks of average demand.

Sheet Inputs
A1: Inputs (change the yellow cells)
A2: Everything in the model reads from this sheet. Named ranges in column E make the formulas readable.
B4: Assumption | C4: Value | D4: What it means / why this value | E4: Name in formulas
B5: Target service level | C5: 0.95 | D5: Chance of NOT running out during a lead time. 95% is the brief's default. | E5: ServiceLevel
B6: z (safety factor) | C6: =_xlfn.NORM.S.INV(C5) -> 1.6448536 | D6: z = NORM.S.INV(service level). 95% gives 1.645. | E6: Z
B8: Service level for A items (optional) | D8: Leave blank to use the target above. Try 98% for A, 90% for C. | E8: SL_A
B9: Service level for B items (optional) | E9: SL_B
B10: Service level for C items (optional) | E10: SL_C
B12: Lead time (weeks) | C12: 3 | D12: Order to delivery. Brief range 2-4 weeks; most stock is imported. | E12: LeadTime
B13: Holding cost (% of unit cost per year) | C13: 0.25 | D13: Storage, capital, insurance, damage, obsolescence. Brief range 20-25%. | E13: HoldingRate
B14: Ordering cost (£ per order) | C14: 50 | D14: Admin, freight booking and receiving for one purchase order line. | E14: OrderCost
B15: Unit cost (% of selling price) | C15: 0.6 | D15: The data only has selling prices; 60% = a 40% gross margin. | E15: CostRatio
B16: Current stock (weeks of average demand) | C16: 8 | D16: No stock data, so assume today's blanket rule: 8 weeks of cover for every SKU. | E16: CurrentCover
B17: Weeks per year | C17: 52 | E17: WeeksPerYear
B19: ABC: A = first ...% of value | C19: 0.8 | D19: Cumulative share of sales value. Classic split 80 / 15 / 5. | E19: A_Limit
B20: ABC: B = up to ...% of value | C20: 0.95 | D20: The rest is C. | E20: B_Limit
B22: XYZ: X = CV up to | C22: 0.75 | D22: CV = std dev / average of weekly demand. Weekly data is noisy, so the limits are higher than the monthly 0.5 / 1.0. | E22: X_Limit
B23: XYZ: Y = CV up to | C23: 1.25 | D23: Above this = Z (erratic). | E23: Y_Limit
B25: Seasonal if Christmas uplift at least | C25: 1.3 | D25: Uplift = avg demand Sep-Nov 2010 / avg over the training weeks. Seasonal SKUs may use Holt-Winters. | E25: SeasonalLimit
B27: Class service levels (used by the Policy sheet: blank override = target service level)
B28: Class | C28: Service level used | D28: z used
B29: A | C29: =IF(SL_A="",ServiceLevel,SL_A) -> 0.95 | D29: =_xlfn.NORM.S.INV(C29) -> 1.6448536
B30: B | C30: =IF(SL_B="",ServiceLevel,SL_B) -> 0.95 | D30: =_xlfn.NORM.S.INV(C30) -> 1.6448536
B31: C | C31: =IF(SL_C="",ServiceLevel,SL_C) -> 0.95 | D31: =_xlfn.NORM.S.INV(C31) -> 1.6448536

Sheet Summary
A1: Summary: current vs recommended stock
A2: All numbers update when you change Inputs. £ values are at cost (unit cost = selling price × unit cost %).
B4: Current stock value | C4: Recommended avg stock | D4: Working capital freed | E4: Stock reduction | F4: SKUs to reorder now | G4: SKUs overstocked
B5: =SUM(PolCur) -> 294811.67 | C5: =SUM(PolRec) -> 270948.37 | D5: =SUM(PolFreed) -> 23863.307 | E5: =1-SUM(PolRec)/SUM(PolCur) -> 0.080944242 | F5: =COUNTIF(PolStatus,"Reorder now") -> 29 | G5: =COUNTIF(PolStatus,"Overstock") -> 1
B6: ="Service level "&TEXT(ServiceLevel,"0.0%")&" · lead time "&LeadTime&" wks · holding "&TEXT(HoldingRate,"0%")&" · £"&OrderCost&" per order · current stock = "&CurrentCover&" weeks of cover" -> Service level 95.0% · lead time 3 wks · holding 25% · £50 per order · current stock = 8 weeks of cover
B8: By ABC class | I8: Service level vs cost trade-off (all SKUs at the same service level)
B9: Class | C9: SKUs | D9: Current stock (£) | E9: Recommended (£) | F9: Freed (£) | G9: Reorder now | I9: Service level | J9: z | K9: Safety stock (£) | L9: Holding cost / yr (£) | M9: Extra £ vs row above
B10: A | C10: =COUNTIF(PolClass,"A*") -> 95 | D10: =SUMIFS(PolCur,PolClass,"A*") -> 235312.33 | E10: =SUMIFS(PolRec,PolClass,"A*") -> 200217.84 | F10: =D10-E10 -> 35094.491 | G10: =COUNTIFS(PolClass,"A*",PolStatus,"Reorder now") -> 19 | I10: 0.8 | J10: =_xlfn.NORM.S.INV(I10) -> 0.84162123 | K10: =J10*SUMPRODUCT(PolSD,PolCost)*SQRT(LeadTime) -> 55552.178 | L10: =K10*HoldingRate -> 13888.044
B11: B | C11: =COUNTIF(PolClass,"B*") -> 39 | D11: =SUMIFS(PolCur,PolClass,"B*") -> 44000.566 | E11: =SUMIFS(PolRec,PolClass,"B*") -> 52183.196 | F11: =D11-E11 -> -8182.6295 | G11: =COUNTIFS(PolClass,"B*",PolStatus,"Reorder now") -> 6 | I11: 0.85 | J11: =_xlfn.NORM.S.INV(I11) -> 1.0364334 | K11: =J11*SUMPRODUCT(PolSD,PolCost)*SQRT(LeadTime) -> 68410.978 | L11: =K11*HoldingRate -> 17102.745 | M11: =K11-K10 -> 12858.801
B12: C | C12: =COUNTIF(PolClass,"C*") -> 16 | D12: =SUMIFS(PolCur,PolClass,"C*") -> 15498.772 | E12: =SUMIFS(PolRec,PolClass,"C*") -> 18547.326 | F12: =D12-E12 -> -3048.5543 | G12: =COUNTIFS(PolClass,"C*",PolStatus,"Reorder now") -> 4 | I12: 0.9 | J12: =_xlfn.NORM.S.INV(I12) -> 1.2815516 | K12: =J12*SUMPRODUCT(PolSD,PolCost)*SQRT(LeadTime) -> 84590.286 | L12: =K12*HoldingRate -> 21147.571 | M12: =K12-K11 -> 16179.307
B13: Total | C13: =SUM(C10:C12) -> 150 | D13: =SUM(D10:D12) -> 294811.67 | E13: =SUM(E10:E12) -> 270948.37 | F13: =SUM(F10:F12) -> 23863.307 | G13: =SUM(G10:G12) -> 29 | I13: 0.925 | J13: =_xlfn.NORM.S.INV(I13) -> 1.4395315 | K13: =J13*SUMPRODUCT(PolSD,PolCost)*SQRT(LeadTime) -> 95017.931 | L13: =K13*HoldingRate -> 23754.483 | M13: =K13-K12 -> 10427.645
I14: 0.95 | J14: =_xlfn.NORM.S.INV(I14) -> 1.6448536 | K14: =J14*SUMPRODUCT(PolSD,PolCost)*SQRT(LeadTime) -> 108570.46 | L14: =K14*HoldingRate -> 27142.614 | M14: =K14-K13 -> 13552.525
B15: By XYZ class (the blanket rule over-stocks steady items and under-stocks erratic ones) | I15: 0.97 | J15: =_xlfn.NORM.S.INV(I15) -> 1.8807936 | K15: =J15*SUMPRODUCT(PolSD,PolCost)*SQRT(LeadTime) -> 124143.95 | L15: =K15*HoldingRate -> 31035.987 | M15: =K15-K14 -> 15573.49
B16: Class | C16: SKUs | D16: Current stock (£) | E16: Recommended (£) | F16: Freed (£) | G16: Reorder now | I16: 0.98 | J16: =_xlfn.NORM.S.INV(I16) -> 2.0537489 | K16: =J16*SUMPRODUCT(PolSD,PolCost)*SQRT(LeadTime) -> 135560.06 | L16: =K16*HoldingRate -> 33890.015 | M16: =K16-K15 -> 11416.114
B17: X | C17: =COUNTIF(PolClass,"?X") -> 51 | D17: =SUMIFS(PolCur,PolClass,"?X") -> 115835.34 | E17: =SUMIFS(PolRec,PolClass,"?X") -> 83627.462 | F17: =D17-E17 -> 32207.882 | G17: =COUNTIFS(PolClass,"?X",PolStatus,"Reorder now") -> 0 | I17: 0.99 | J17: =_xlfn.NORM.S.INV(I17) -> 2.3263479 | K17: =J17*SUMPRODUCT(PolSD,PolCost)*SQRT(LeadTime) -> 153553.27 | L17: =K17*HoldingRate -> 38388.317 | M17: =K17-K16 -> 17993.208
B18: Y | C18: =COUNTIF(PolClass,"?Y") -> 55 | D18: =SUMIFS(PolCur,PolClass,"?Y") -> 100151.81 | E18: =SUMIFS(PolRec,PolClass,"?Y") -> 92204.566 | F18: =D18-E18 -> 7947.2443 | G18: =COUNTIFS(PolClass,"?Y",PolStatus,"Reorder now") -> 3 | I18: 0.995 | J18: =_xlfn.NORM.S.INV(I18) -> 2.5758293 | K18: =J18*SUMPRODUCT(PolSD,PolCost)*SQRT(LeadTime) -> 170020.58 | L18: =K18*HoldingRate -> 42505.144 | M18: =K18-K17 -> 16467.309
B19: Z | C19: =COUNTIF(PolClass,"?Z") -> 44 | D19: =SUMIFS(PolCur,PolClass,"?Z") -> 78824.519 | E19: =SUMIFS(PolRec,PolClass,"?Z") -> 95116.338 | F19: =D19-E19 -> -16291.819 | G19: =COUNTIFS(PolClass,"?Z",PolStatus,"Reorder now") -> 26 | I19: Going from 95% to 99% needs about 40% more safety stock: each extra point of service costs more than the last.
B22: Yearly running cost of the recommended policy | I22: Top 10 SKUs to reorder now (biggest shortfall below the reorder point, LARGE + INDEX/MATCH)
B23: Holding cost / year | C23: =SUM(PolHold) -> 67737.091 | D23: EOQ is where these two are equal: order more often → less stock but more orders. | I23: Stock code | J23: Class | K23: Shortfall (£) | L23: Order qty | M23: Stock-out risk
B24: Ordering cost / year | C24: =SUM(PolOrdCost) -> 40501.295 | I24: =IF(INDEX(PolShort,MATCH(LARGE(PolRank,1),PolRank,0))=0,"",INDEX(PolCode,MATCH(LARGE(PolRank,1),PolRank,0))) -> 22086 | J24: =IF(I24="","",INDEX(PolClass,MATCH(LARGE(PolRank,1),PolRank,0))) -> AZ | K24: =IF(I24="","",INDEX(PolShort,MATCH(LARGE(PolRank,1),PolRank,0))) -> 1761.7022 | L24: =IF(I24="","",INDEX(PolOrder,MATCH(LARGE(PolRank,1),PolRank,0))) -> 2654 | M24: =IF(I24="","",INDEX(PolRisk,MATCH(LARGE(PolRank,1),PolRank,0))) -> 0.24469079
B25: Total | C25: =C23+C24 -> 108238.39 | I25: =IF(INDEX(PolShort,MATCH(LARGE(PolRank,2),PolRank,0))=0,"",INDEX(PolCode,MATCH(LARGE(PolRank,2),PolRank,0))) -> 22114 | J25: =IF(I25="","",INDEX(PolClass,MATCH(LARGE(PolRank,2),PolRank,0))) -> AZ | K25: =IF(I25="","",INDEX(PolShort,MATCH(LARGE(PolRank,2),PolRank,0))) -> 1700.6145 | L25: =IF(I25="","",INDEX(PolOrder,MATCH(LARGE(PolRank,2),PolRank,0))) -> 1254 | M25: =IF(I25="","",INDEX(PolRisk,MATCH(LARGE(PolRank,2),PolRank,0))) -> 0.54923587
B26: Safety stock value | C26: =SUMPRODUCT(PolSS,PolCost) -> 108772.68 | I26: =IF(INDEX(PolShort,MATCH(LARGE(PolRank,3),PolRank,0))=0,"",INDEX(PolCode,MATCH(LARGE(PolRank,3),PolRank,0))) -> 15056BL | J26: =IF(I26="","",INDEX(PolClass,MATCH(LARGE(PolRank,3),PolRank,0))) -> AY | K26: =IF(I26="","",INDEX(PolShort,MATCH(LARGE(PolRank,3),PolRank,0))) -> 1429.5387 | L26: =IF(I26="","",INDEX(PolOrder,MATCH(LARGE(PolRank,3),PolRank,0))) -> 992 | M26: =IF(I26="","",INDEX(PolRisk,MATCH(LARGE(PolRank,3),PolRank,0))) -> 0.99894985
I27: =IF(INDEX(PolShort,MATCH(LARGE(PolRank,4),PolRank,0))=0,"",INDEX(PolCode,MATCH(LARGE(PolRank,4),PolRank,0))) -> 22111 | J27: =IF(I27="","",INDEX(PolClass,MATCH(LARGE(PolRank,4),PolRank,0))) -> AZ | K27: =IF(I27="","",INDEX(PolShort,MATCH(LARGE(PolRank,4),PolRank,0))) -> 1342.3407 | L27: =IF(I27="","",INDEX(PolOrder,MATCH(LARGE(PolRank,4),PolRank,0))) -> 1170 | M27: =IF(I27="","",INDEX(PolRisk,MATCH(LARGE(PolRank,4),PolRank,0))) -> 0.58023227
I28: =IF(INDEX(PolShort,MATCH(LARGE(PolRank,5),PolRank,0))=0,"",INDEX(PolCode,MATCH(LARGE(PolRank,5),PolRank,0))) -> 84029E | J28: =IF(I28="","",INDEX(PolClass,MATCH(LARGE(PolRank,5),PolRank,0))) -> AZ | K28: =IF(I28="","",INDEX(PolShort,MATCH(LARGE(PolRank,5),PolRank,0))) -> 933.91955 | L28: =IF(I28="","",INDEX(PolOrder,MATCH(LARGE(PolRank,5),PolRank,0))) -> 1144 | M28: =IF(I28="","",INDEX(PolRisk,MATCH(LARGE(PolRank,5),PolRank,0))) -> 0.25244502
I29: =IF(INDEX(PolShort,MATCH(LARGE(PolRank,6),PolRank,0))=0,"",INDEX(PolCode,MATCH(LARGE(PolRank,6),PolRank,0))) -> 21623 | J29: =IF(I29="","",INDEX(PolClass,MATCH(LARGE(PolRank,6),PolRank,0))) -> AZ | K29: =IF(I29="","",INDEX(PolShort,MATCH(LARGE(PolRank,6),PolRank,0))) -> 915.87684 | L29: =IF(I29="","",INDEX(PolOrder,MATCH(LARGE(PolRank,6),PolRank,0))) -> 772 | M29: =IF(I29="","",INDEX(PolRisk,MATCH(LARGE(PolRank,6),PolRank,0))) -> 0.15438969
I30: =IF(INDEX(PolShort,MATCH(LARGE(PolRank,7),PolRank,0))=0,"",INDEX(PolCode,MATCH(LARGE(PolRank,7),PolRank,0))) -> 84029G | J30: =IF(I30="","",INDEX(PolClass,MATCH(LARGE(PolRank,7),PolRank,0))) -> AZ | K30: =IF(I30="","",INDEX(PolShort,MATCH(LARGE(PolRank,7),PolRank,0))) -> 899.32348 | L30: =IF(I30="","",INDEX(PolOrder,MATCH(LARGE(PolRank,7),PolRank,0))) -> 995 | M30: =IF(I30="","",INDEX(PolRisk,MATCH(LARGE(PolRank,7),PolRank,0))) -> 0.49711742
I31: =IF(INDEX(PolShort,MATCH(LARGE(PolRank,8),PolRank,0))=0,"",INDEX(PolCode,MATCH(LARGE(PolRank,8),PolRank,0))) -> 21108 | J31: =IF(I31="","",INDEX(PolClass,MATCH(LARGE(PolRank,8),PolRank,0))) -> BZ | K31: =IF(I31="","",INDEX(PolShort,MATCH(LARGE(PolRank,8),PolRank,0))) -> 794.0542 | L31: =IF(I31="","",INDEX(PolOrder,MATCH(LARGE(PolRank,8),PolRank,0))) -> 2321 | M31: =IF(I31="","",INDEX(PolRisk,MATCH(LARGE(PolRank,8),PolRank,0))) -> 0.23724157
I32: =IF(INDEX(PolShort,MATCH(LARGE(PolRank,9),PolRank,0))=0,"",INDEX(PolCode,MATCH(LARGE(PolRank,9),PolRank,0))) -> 22087 | J32: =IF(I32="","",INDEX(PolClass,MATCH(LARGE(PolRank,9),PolRank,0))) -> BZ | K32: =IF(I32="","",INDEX(PolShort,MATCH(LARGE(PolRank,9),PolRank,0))) -> 750.99486 | L32: =IF(I32="","",INDEX(PolOrder,MATCH(LARGE(PolRank,9),PolRank,0))) -> 1396 | M32: =IF(I32="","",INDEX(PolRisk,MATCH(LARGE(PolRank,9),PolRank,0))) -> 0.66880863
I33: =IF(INDEX(PolShort,MATCH(LARGE(PolRank,10),PolRank,0))=0,"",INDEX(PolCode,MATCH(LARGE(PolRank,10),PolRank,0))) -> 21485 | J33: =IF(I33="","",INDEX(PolClass,MATCH(LARGE(PolRank,10),PolRank,0))) -> AZ | K33: =IF(I33="","",INDEX(PolShort,MATCH(LARGE(PolRank,10),PolRank,0))) -> 750.20475 | L33: =IF(I33="","",INDEX(PolOrder,MATCH(LARGE(PolRank,10),PolRank,0))) -> 921 | M33: =IF(I33="","",INDEX(PolRisk,MATCH(LARGE(PolRank,10),PolRank,0))) -> 0.43060572

Sheet Charts
A1: Charts
A2: All charts read live from the model sheets. The first one follows the SKU picked on the Forecast sheet.

Sheet ABC_XYZ
A1: ABC-XYZ classification
A2: ABC = value (cumulative share of net sales, last 52 weeks). XYZ = predictability (CV of weekly demand, last 52 weeks). Limits come from Inputs.
A4: Stock code | B4: Description | C4: Net sales 52w (£) | D4: Value rank | E4: Cumulative value share | F4: ABC | G4: Avg weekly demand | H4: Std dev weekly | I4: CV | J4: XYZ | K4: Class | L4: Christmas uplift | M4: Seasonal? | N4: Avg selling price (£) | O4: Same as SQL/ Python? | P4: 9-box matrix: number of SKUs (COUNTIFS)
A5: =SKU_Data!A5 -> 22423 | B5: =_xlfn.XLOOKUP(A5,SKUList,SKU_Data!$B$5:$B$154) -> REGENCY CAKESTAND 3 TIER | C5: =_xlfn.XLOOKUP(A5,SKUList,SKU_Data!$E$5:$E$154) -> 160270.37 | D5: =_xlfn.RANK.EQ(C5,$C$5:$C$154) -> 1 | E5: =SUMIFS($C$5:$C$154,$C$5:$C$154,">="&C5)/SUM($C$5:$C$154) -> 0.050076703 | F5: =IF(E5<=A_Limit,"A",IF(E5<=B_Limit,"B","C")) -> A | G5: =AVERAGE(_xlfn.XLOOKUP(A5,DemandCodes,DemandLast52)) -> 244.40385 | H5: =_xlfn.STDEV.S(_xlfn.XLOOKUP(A5,DemandCodes,DemandLast52)) -> 157.82943 | I5: =H5/G5 -> 0.64577309 | J5: =IF(I5<=X_Limit,"X",IF(I5<=Y_Limit,"Y","Z")) -> X | K5: =F5&J5 -> AX | L5: =AVERAGE(_xlfn.XLOOKUP(A5,DemandCodes,DemandPeak2010))/AVERAGE(_xlfn.XLOOKUP(A5,DemandCodes,DemandTrain)) -> 1.9313203 | M5: =IF(L5>=SeasonalLimit,"Yes","No") -> Yes | N5: =_xlfn.XLOOKUP(A5,SKUList,SKU_Data!$C$5:$C$154)/_xlfn.XLOOKUP(A5,SKUList,SKU_Data!$D$5:$D$154) -> 12.531381 | O5: =IF(K5=_xlfn.XLOOKUP(A5,SKUList,SKU_Data!$F$5:$F$154),"✓","≠") -> ✓ | Q5: X (steady) | R5: Y (variable) | S5: Z (erratic) | T5: Total
A6: =SKU_Data!A6 -> 85123A | B6: =_xlfn.XLOOKUP(A6,SKUList,SKU_Data!$B$5:$B$154) -> WHITE HANGING HEART T-LIGHT HOLDER | C6: =_xlfn.XLOOKUP(A6,SKUList,SKU_Data!$E$5:$E$154) -> 97727.17 | D6: =_xlfn.RANK.EQ(C6,$C$5:$C$154) -> 2 | E6: =SUMIFS($C$5:$C$154,$C$5:$C$154,">="&C6)/SUM($C$5:$C$154) -> 0.080611695 | F6: =IF(E6<=A_Limit,"A",IF(E6<=B_Limit,"B","C")) -> A | G6: =AVERAGE(_xlfn.XLOOKUP(A6,DemandCodes,DemandLast52)) -> 665.01923 | H6: =_xlfn.STDEV.S(_xlfn.XLOOKUP(A6,DemandCodes,DemandLast52)) -> 519.54797 | I6: =H6/G6 -> 0.78125256 | J6: =IF(I6<=X_Limit,"X",IF(I6<=Y_Limit,"Y","Z")) -> Y | K6: =F6&J6 -> AY | L6: =AVERAGE(_xlfn.XLOOKUP(A6,DemandCodes,DemandPeak2010))/AVERAGE(_xlfn.XLOOKUP(A6,DemandCodes,DemandTrain)) -> 1.3546089 | M6: =IF(L6>=SeasonalLimit,"Yes","No") -> Yes | N6: =_xlfn.XLOOKUP(A6,SKUList,SKU_Data!$C$5:$C$154)/_xlfn.XLOOKUP(A6,SKUList,SKU_Data!$D$5:$D$154) -> 2.8082491 | O6: =IF(K6=_xlfn.XLOOKUP(A6,SKUList,SKU_Data!$F$5:$F$154),"✓","≠") -> ✓ | P6: A | Q6: =COUNTIFS(ClsABC,$P6,ClsXYZ,"X") -> 36 | R6: =COUNTIFS(ClsABC,$P6,ClsXYZ,"Y") -> 31 | S6: =COUNTIFS(ClsABC,$P6,ClsXYZ,"Z") -> 28 | T6: =SUM(Q6:S6) -> 95
A7: =SKU_Data!A7 -> 47566 | B7: =_xlfn.XLOOKUP(A7,SKUList,SKU_Data!$B$5:$B$154) -> PARTY BUNTING | C7: =_xlfn.XLOOKUP(A7,SKUList,SKU_Data!$E$5:$E$154) -> 97325.28 | D7: =_xlfn.RANK.EQ(C7,$C$5:$C$154) -> 3 | E7: =SUMIFS($C$5:$C$154,$C$5:$C$154,">="&C7)/SUM($C$5:$C$154) -> 0.11102112 | F7: =IF(E7<=A_Limit,"A",IF(E7<=B_Limit,"B","C")) -> A | G7: =AVERAGE(_xlfn.XLOOKUP(A7,DemandCodes,DemandLast52)) -> 343.88462 | H7: =_xlfn.STDEV.S(_xlfn.XLOOKUP(A7,DemandCodes,DemandLast52)) -> 253.99326 | I7: =H7/G7 -> 0.73860023 | J7: =IF(I7<=X_Limit,"X",IF(I7<=Y_Limit,"Y","Z")) -> X | K7: =F7&J7 -> AX | L7: =AVERAGE(_xlfn.XLOOKUP(A7,DemandCodes,DemandPeak2010))/AVERAGE(_xlfn.XLOOKUP(A7,DemandCodes,DemandTrain)) -> 0.6947788 | M7: =IF(L7>=SeasonalLimit,"Yes","No") -> No | N7: =_xlfn.XLOOKUP(A7,SKUList,SKU_Data!$C$5:$C$154)/_xlfn.XLOOKUP(A7,SKUList,SKU_Data!$D$5:$D$154) -> 5.425774 | O7: =IF(K7=_xlfn.XLOOKUP(A7,SKUList,SKU_Data!$F$5:$F$154),"✓","≠") -> ✓ | P7: B | Q7: =COUNTIFS(ClsABC,$P7,ClsXYZ,"X") -> 10 | R7: =COUNTIFS(ClsABC,$P7,ClsXYZ,"Y") -> 17 | S7: =COUNTIFS(ClsABC,$P7,ClsXYZ,"Z") -> 12 | T7: =SUM(Q7:S7) -> 39
A8: =SKU_Data!A8 -> 85099B | B8: =_xlfn.XLOOKUP(A8,SKUList,SKU_Data!$B$5:$B$154) -> JUMBO BAG RED RETROSPOT | C8: =_xlfn.XLOOKUP(A8,SKUList,SKU_Data!$E$5:$E$154) -> 90869.71 | D8: =_xlfn.RANK.EQ(C8,$C$5:$C$154) -> 4 | E8: =SUMIFS($C$5:$C$154,$C$5:$C$154,">="&C8)/SUM($C$5:$C$154) -> 0.13941349 | F8: =IF(E8<=A_Limit,"A",IF(E8<=B_Limit,"B","C")) -> A | G8: =AVERAGE(_xlfn.XLOOKUP(A8,DemandCodes,DemandLast52)) -> 900.42308 | H8: =_xlfn.STDEV.S(_xlfn.XLOOKUP(A8,DemandCodes,DemandLast52)) -> 493.56249 | I8: =H8/G8 -> 0.5481451 | J8: =IF(I8<=X_Limit,"X",IF(I8<=Y_Limit,"Y","Z")) -> X | K8: =F8&J8 -> AX | L8: =AVERAGE(_xlfn.XLOOKUP(A8,DemandCodes,DemandPeak2010))/AVERAGE(_xlfn.XLOOKUP(A8,DemandCodes,DemandTrain)) -> 1.4922836 | M8: =IF(L8>=SeasonalLimit,"Yes","No") -> Yes | N8: =_xlfn.XLOOKUP(A8,SKUList,SKU_Data!$C$5:$C$154)/_xlfn.XLOOKUP(A8,SKUList,SKU_Data!$D$5:$D$154) -> 1.9369511 | O8: =IF(K8=_xlfn.XLOOKUP(A8,SKUList,SKU_Data!$F$5:$F$154),"✓","≠") -> ✓ | P8: C | Q8: =COUNTIFS(ClsABC,$P8,ClsXYZ,"X") -> 5 | R8: =COUNTIFS(ClsABC,$P8,ClsXYZ,"Y") -> 7 | S8: =COUNTIFS(ClsABC,$P8,ClsXYZ,"Z") -> 4 | T8: =SUM(Q8:S8) -> 16
A9: =SKU_Data!A9 -> 84879 | B9: =_xlfn.XLOOKUP(A9,SKUList,SKU_Data!$B$5:$B$154) -> ASSORTED COLOUR BIRD ORNAMENT | C9: =_xlfn.XLOOKUP(A9,SKUList,SKU_Data!$E$5:$E$154) -> 56285.16 | D9: =_xlfn.RANK.EQ(C9,$C$5:$C$154) -> 5 | E9: =SUMIFS($C$5:$C$154,$C$5:$C$154,">="&C9)/SUM($C$5:$C$154) -> 0.15699986 | F9: =IF(E9<=A_Limit,"A",IF(E9<=B_Limit,"B","C")) -> A | G9: =AVERAGE(_xlfn.XLOOKUP(A9,DemandCodes,DemandLast52)) -> 667.76923 | H9: =_xlfn.STDEV.S(_xlfn.XLOOKUP(A9,DemandCodes,DemandLast52)) -> 560.66958 | I9: =H9/G9 -> 0.83961577 | J9: =IF(I9<=X_Limit,"X",IF(I9<=Y_Limit,"Y","Z")) -> Y | K9: =F9&J9 -> AY | L9: =AVERAGE(_xlfn.XLOOKUP(A9,DemandCodes,DemandPeak2010))/AVERAGE(_xlfn.XLOOKUP(A9,DemandCodes,DemandTrain)) -> 2.0484386 | M9: =IF(L9>=SeasonalLimit,"Yes","No") -> Yes | N9: =_xlfn.XLOOKUP(A9,SKUList,SKU_Data!$C$5:$C$154)/_xlfn.XLOOKUP(A9,SKUList,SKU_Data!$D$5:$D$154) -> 1.6200477 | O9: =IF(K9=_xlfn.XLOOKUP(A9,SKUList,SKU_Data!$F$5:$F$154),"✓","≠") -> ✓ | P9: Total | Q9: =SUM(Q6:Q8) -> 51 | R9: =SUM(R6:R8) -> 55 | S9: =SUM(S6:S8) -> 44 | T9: =SUM(T6:T8) -> 150
A10: =SKU_Data!A10 -> 22086 | B10: =_xlfn.XLOOKUP(A10,SKUList,SKU_Data!$B$5:$B$154) -> PAPER CHAIN KIT 50'S CHRISTMAS | C10: =_xlfn.XLOOKUP(A10,SKUList,SKU_Data!$E$5:$E$154) -> 55727.95 | D10: =_xlfn.RANK.EQ(C10,$C$5:$C$154) -> 6 | E10: =SUMIFS($C$5:$C$154,$C$5:$C$154,">="&C10)/SUM($C$5:$C$154) -> 0.17441214 | F10: =IF(E10<=A_Limit,"A",IF(E10<=B_Limit,"B","C")) -> A | G10: =AVERAGE(_xlfn.XLOOKUP(A10,DemandCodes,DemandLast52)) -> 313.82692 | H10: =_xlfn.STDEV.S(_xlfn.XLOOKUP(A10,DemandCodes,DemandLast52)) -> 522.61637 | I10: =H10/G10 -> 1.6653013 | J10: =IF(I10<=X_Limit,"X",IF(I10<=Y_Limit,"Y","Z")) -> Z | K10: =F10&J10 -> AZ | L10: =AVERAGE(_xlfn.XLOOKUP(A10,DemandCodes,DemandPeak2010))/AVERAGE(_xlfn.XLOOKUP(A10,DemandCodes,DemandTrain)) -> 4.8464339 | M10: =IF(L10>=SeasonalLimit,"Yes","No") -> Yes | N10: =_xlfn.XLOOKUP(A10,SKUList,SKU_Data!$C$5:$C$154)/_xlfn.XLOOKUP(A10,SKUList,SKU_Data!$D$5:$D$154) -> 3.3983453 | O10: =IF(K10=_xlfn.XLOOKUP(A10,SKUList,SKU_Data!$F$5:$F$154),"✓","≠") -> ✓
A11: =SKU_Data!A11 -> 79321 | B11: =_xlfn.XLOOKUP(A11,SKUList,SKU_Data!$B$5:$B$154) -> CHILLI LIGHTS | C11: =_xlfn.XLOOKUP(A11,SKUList,SKU_Data!$E$5:$E$154) -> 51524.91 | D11: =_xlfn.RANK.EQ(C11,$C$5:$C$154) -> 7 | E11: =SUMIFS($C$5:$C$154,$C$5:$C$154,">="&C11)/SUM($C$5:$C$154) -> 0.19051117 | F11: =IF(E11<=A_Limit,"A",IF(E11<=B_Limit,"B","C")) -> A | G11: =AVERAGE(_xlfn.XLOOKUP(A11,DemandCodes,DemandLast52)) -> 189.92308 | H11: =_xlfn.STDEV.S(_xlfn.XLOOKUP(A11,DemandCodes,DemandLast52)) -> 226.97049 | I11: =H11/G11 -> 1.1950653 | J11: =IF(I11<=X_Limit,"X",IF(I11<=Y_Limit,"Y","Z")) -> Y | K11: =F11&J11 -> AY | L11: =AVERAGE(_xlfn.XLOOKUP(A11,DemandCodes,DemandPeak2010))/AVERAGE(_xlfn.XLOOKUP(A11,DemandCodes,DemandTrain)) -> 2.1948041 | M11: =IF(L11>=SeasonalLimit,"Yes","No") -> Yes | N11: =_xlfn.XLOOKUP(A11,SKUList,SKU_Data!$C$5:$C$154)/_xlfn.XLOOKUP(A11,SKUList,SKU_Data!$D$5:$D$154) -> 5.2103325 | O11: =IF(K11=_xlfn.XLOOKUP(A11,SKUList,SKU_Data!$F$5:$F$154),"✓","≠") -> ✓ | P11: 9-box matrix: share of sales value (SUMIFS)
A12: =SKU_Data!A12 -> 22502 | B12: =_xlfn.XLOOKUP(A12,SKUList,SKU_Data!$B$5:$B$154) -> PICNIC BASKET WICKER SMALL | C12: =_xlfn.XLOOKUP(A12,SKUList,SKU_Data!$E$5:$E$154) -> 51315.59 | D12: =_xlfn.RANK.EQ(C12,$C$5:$C$154) -> 8 | E12: =SUMIFS($C$5:$C$154,$C$5:$C$154,">="&C12)/SUM($C$5:$C$154) -> 0.2065448 | F12: =IF(E12<=A_Limit,"A",IF(E12<=B_Limit,"B","C")) -> A | G12: =AVERAGE(_xlfn.XLOOKUP(A12,DemandCodes,DemandLast52)) -> 36.673077 | H12: =_xlfn.STDEV.S(_xlfn.XLOOKUP(A12,DemandCodes,DemandLast52)) -> 48.335316 | I12: =H12/G12 -> 1.3180055 | J12: =IF(I12<=X_Limit,"X",IF(I12<=Y_Limit,"Y","Z")) -> Z | K12: =F12&J12 -> AZ | L12: =AVERAGE(_xlfn.XLOOKUP(A12,DemandCodes,DemandPeak2010))/AVERAGE(_xlfn.XLOOKUP(A12,DemandCodes,DemandTrain)) -> 1.5039434 | M12: =IF(L12>=SeasonalLimit,"Yes","No") -> Yes | N12: =_xlfn.XLOOKUP(A12,SKUList,SKU_Data!$C$5:$C$154)/_xlfn.XLOOKUP(A12,SKUList,SKU_Data!$D$5:$D$154) -> 26.085187 | O12: =IF(K12=_xlfn.XLOOKUP(A12,SKUList,SKU_Data!$F$5:$F$154),"✓","≠") -> ✓ | Q12: X (steady) | R12: Y (variable) | S12: Z (erratic) | T12: Total
A13: =SKU_Data!A13 -> 22197 | B13: =_xlfn.XLOOKUP(A13,SKUList,SKU_Data!$B$5:$B$154) -> SMALL POPCORN HOLDER | C13: =_xlfn.XLOOKUP(A13,SKUList,SKU_Data!$E$5:$E$154) -> 44426.46 | D13: =_xlfn.RANK.EQ(C13,$C$5:$C$154) -> 9 | E13: =SUMIFS($C$5:$C$154,$C$5:$C$154,">="&C13)/SUM($C$5:$C$154) -> 0.22042591 | F13: =IF(E13<=A_Limit,"A",IF(E13<=B_Limit,"B","C")) -> A | G13: =AVERAGE(_xlfn.XLOOKUP(A13,DemandCodes,DemandLast52)) -> 940.19231 | H13: =_xlfn.STDEV.S(_xlfn.XLOOKUP(A13,DemandCodes,DemandLast52)) -> 942.673 | I13: =H13/G13 -> 1.0026385 | J13: =IF(I13<=X_Limit,"X",IF(I13<=Y_Limit,"Y","Z")) -> Y | K13: =F13&J13 -> AY | L13: =AVERAGE(_xlfn.XLOOKUP(A13,DemandCodes,DemandPeak2010))/AVERAGE(_xlfn.XLOOKUP(A13,DemandCodes,DemandTrain)) -> 2.0594331 | M13: =IF(L13>=SeasonalLimit,"Yes","No") -> Yes | N13: =_xlfn.XLOOKUP(A13,SKUList,SKU_Data!$C$5:$C$154)/_xlfn.XLOOKUP(A13,SKUList,SKU_Data!$D$5:$D$154) -> 0.90749438 | O13: =IF(K13=_xlfn.XLOOKUP(A13,SKUList,SKU_Data!$F$5:$F$154),"✓","≠") -> ✓ | P13: A | Q13: =SUMIFS(ClsValue,ClsABC,$P13,ClsXYZ,"X")/SUM(ClsValue) -> 0.33818547 | R13: =SUMIFS(ClsValue,ClsABC,$P13,ClsXYZ,"Y")/SUM(ClsValue) -> 0.2514302 | S13: =SUMIFS(ClsValue,ClsABC,$P13,ClsXYZ,"Z")/SUM(ClsValue) -> 0.20931421 | T13: =SUM(Q13:S13) -> 0.79892989
A14: =SKU_Data!A14 -> 22386 | B14: =_xlfn.XLOOKUP(A14,SKUList,SKU_Data!$B$5:$B$154) -> JUMBO BAG PINK POLKADOT | C14: =_xlfn.XLOOKUP(A14,SKUList,SKU_Data!$E$5:$E$154) -> 40758.71 | D14: =_xlfn.RANK.EQ(C14,$C$5:$C$154) -> 10 | E14: =SUMIFS($C$5:$C$154,$C$5:$C$154,">="&C14)/SUM($C$5:$C$154) -> 0.23316103 | F14: =IF(E14<=A_Limit,"A",IF(E14<=B_Limit,"B","C")) -> A | G14: =AVERAGE(_xlfn.XLOOKUP(A14,DemandCodes,DemandLast52)) -> 396.30769 | H14: =_xlfn.STDEV.S(_xlfn.XLOOKUP(A14,DemandCodes,DemandLast52)) -> 278.83515 | I14: =H14/G14 -> 0.70358248 | J14: =IF(I14<=X_Limit,"X",IF(I14<=Y_Limit,"Y","Z")) -> X | K14: =F14&J14 -> AX | L14: =AVERAGE(_xlfn.XLOOKUP(A14,DemandCodes,DemandPeak2010))/AVERAGE(_xlfn.XLOOKUP(A14,DemandCodes,DemandTrain)) -> 1.2199262 | M14: =IF(L14>=SeasonalLimit,"Yes","No") -> No | N14: =_xlfn.XLOOKUP(A14,SKUList,SKU_Data!$C$5:$C$154)/_xlfn.XLOOKUP(A14,SKUList,SKU_Data!$D$5:$D$154) -> 1.9737604 | O14: =IF(K14=_xlfn.XLOOKUP(A14,SKUList,SKU_Data!$F$5:$F$154),"✓","≠") -> ✓ | P14: B | Q14: =SUMIFS(ClsValue,ClsABC,$P14,ClsXYZ,"X")/SUM(ClsValue) -> 0.038295451 | R14: =SUMIFS(ClsValue,ClsABC,$P14,ClsXYZ,"Y")/SUM(ClsValue) -> 0.064960964 | S14: =SUMIFS(ClsValue,ClsABC,$P14,ClsXYZ,"Z")/SUM(ClsValue) -> 0.045274381 | T14: =SUM(Q14:S14) -> 0.1485308
A15: =SKU_Data!A15 -> 21137 | B15: =_xlfn.XLOOKUP(A15,SKUList,SKU_Data!$B$5:$B$154) -> BLACK RECORD COVER FRAME | C15: =_xlfn.XLOOKUP(A15,SKUList,SKU_Data!$E$5:$E$154) -> 34577.75 | D15: =_xlfn.RANK.EQ(C15,$C$5:$C$154) -> 11 | E15: =SUMIFS($C$5:$C$154,$C$5:$C$154,">="&C15)/SUM($C$5:$C$154) -> 0.24396489 | F15: =IF(E15<=A_Limit,"A",IF(E15<=B_Limit,"B","C")) -> A | G15: =AVERAGE(_xlfn.XLOOKUP(A15,DemandCodes,DemandLast52)) -> 191.69231 | H15: =_xlfn.STDEV.S(_xlfn.XLOOKUP(A15,DemandCodes,DemandLast52)) -> 227.12004 | I15: =H15/G15 -> 1.1848156 | J15: =IF(I15<=X_Limit,"X",IF(I15<=Y_Limit,"Y","Z")) -> Y | K15: =F15&J15 -> AY | L15: =AVERAGE(_xlfn.XLOOKUP(A15,DemandCodes,DemandPeak2010))/AVERAGE(_xlfn.XLOOKUP(A15,DemandCodes,DemandTrain)) -> 1.9922247 | M15: =IF(L15>=SeasonalLimit,"Yes","No") -> Yes | N15: =_xlfn.XLOOKUP(A15,SKUList,SKU_Data!$C$5:$C$154)/_xlfn.XLOOKUP(A15,SKUList,SKU_Data!$D$5:$D$154) -> 3.4691341 | O15: =IF(K15=_xlfn.XLOOKUP(A15,SKUList,SKU_Data!$F$5:$F$154),"✓","≠") -> ✓ | P15: C | Q15: =SUMIFS(ClsValue,ClsABC,$P15,ClsXYZ,"X")/SUM(ClsValue) -> 0.016630695 | R15: =SUMIFS(ClsValue,ClsABC,$P15,ClsXYZ,"Y")/SUM(ClsValue) -> 0.023013106 | S15: =SUMIFS(ClsValue,ClsABC,$P15,ClsXYZ,"Z")/SUM(ClsValue) -> 0.012895517 | T15: =SUM(Q15:S15) -> 0.052539317
A16: =SKU_Data!A16 -> 20725 | B16: =_xlfn.XLOOKUP(A16,SKUList,SKU_Data!$B$5:$B$154) -> LUNCH BAG RED RETROSPOT | C16: =_xlfn.XLOOKUP(A16,SKUList,SKU_Data!$E$5:$E$154) -> 33896.01 | D16: =_xlfn.RANK.EQ(C16,$C$5:$C$154) -> 12 | E16: =SUMIFS($C$5:$C$154,$C$5:$C$154,">="&C16)/SUM($C$5:$C$154) -> 0.25455575 | F16: =IF(E16<=A_Limit,"A",IF(E16<=B_Limit,"B","C")) -> A | G16: =AVERAGE(_xlfn.XLOOKUP(A16,DemandCodes,DemandLast52)) -> 352.61538 | H16: =_xlfn.STDEV.S(_xlfn.XLOOKUP(A16,DemandCodes,DemandLast52)) -> 174.64969 | I16: =H16/G16 -> 0.495298 | J16: =IF(I16<=X_Limit,"X",IF(I16<=Y_Limit,"Y","Z")) -> X | K16: =F16&J16 -> AX | L16: =AVERAGE(_xlfn.XLOOKUP(A16,DemandCodes,DemandPeak2010))/AVERAGE(_xlfn.XLOOKUP(A16,DemandCodes,DemandTrain)) -> 1.0244654 | M16: =IF(L16>=SeasonalLimit,"Yes","No") -> No | N16: =_xlfn.XLOOKUP(A16,SKUList,SKU_Data!$C$5:$C$154)/_xlfn.XLOOKUP(A16,SKUList,SKU_Data!$D$5:$D$154) -> 1.8376697 | O16: =IF(K16=_xlfn.XLOOKUP(A16,SKUList,SKU_Data!$F$5:$F$154),"✓","≠") -> ✓ | P16: Total | Q16: =SUM(Q13:Q15) -> 0.39311162 | R16: =SUM(R13:R15) -> 0.33940427 | S16: =SUM(S13:S15) -> 0.26748411 | T16: =SUM(T13:T15) -> 1
A17: =SKU_Data!A17 -> 82484 | B17: =_xlfn.XLOOKUP(A17,SKUList,SKU_Data!$B$5:$B$154) -> WOOD BLACK BOARD ANT WHITE FINISH | C17: =_xlfn.XLOOKUP(A17,SKUList,SKU_Data!$E$5:$E$154) -> 33229.4 | D17: =_xlfn.RANK.EQ(C17,$C$5:$C$154) -> 13 | E17: =SUMIFS($C$5:$C$154,$C$5:$C$154,">="&C17)/SUM($C$5:$C$154) -> 0.26493832 | F17: =IF(E17<=A_Limit,"A",IF(E17<=B_Limit,"B","C")) -> A | G17: =AVERAGE(_xlfn.XLOOKUP(A17,DemandCodes,DemandLast52)) -> 107.09615 | H17: =_xlfn.STDEV.S(_xlfn.XLOOKUP(A17,DemandCodes,DemandLast52)) -> 171.62422 | I17: =H17/G17 -> 1.6025246 | J17: =IF(I17<=X_Limit,"X",IF(I17<=Y_Limit,"Y","Z")) -> Z | K17: =F17&J17 -> AZ | L17: =AVERAGE(_xlfn.XLOOKUP(A17,DemandCodes,DemandPeak2010))/AVERAGE(_xlfn.XLOOKUP(A17,DemandCodes,DemandTrain)) -> 1.37031 | M17: =IF(L17>=SeasonalLimit,"Yes","No") -> Yes | N17: =_xlfn.XLOOKUP(A17,SKUList,SKU_Data!$C$5:$C$154)/_xlfn.XLOOKUP(A17,SKUList,SKU_Data!$D$5:$D$154) -> 5.9711053 | O17: =IF(K17=_xlfn.XLOOKUP(A17,SKUList,SKU_Data!$F$5:$F$154),"✓","≠") -> ✓
A18: =SKU_Data!A18 -> 85099F | B18: =_xlfn.XLOOKUP(A18,SKUList,SKU_Data!$B$5:$B$154) -> JUMBO BAG STRAWBERRY | C18: =_xlfn.XLOOKUP(A18,SKUList,SKU_Data!$E$5:$E$154) -> 31496.69 | D18: =_xlfn.RANK.EQ(C18,$C$5:$C$154) -> 14 | E18: =SUMIFS($C$5:$C$154,$C$5:$C$154,">="&C18)/SUM($C$5:$C$154) -> 0.27477951 | F18: =IF(E18<=A_Limit,"A",IF(E18<=B_Limit,"B","C")) -> A | G18: =AVERAGE(_xlfn.XLOOKUP(A18,DemandCodes,DemandLast52)) -> 319.53846 | H18: =_xlfn.STDEV.S(_xlfn.XLOOKUP(A18,DemandCodes,DemandLast52)) -> 250.01909 | I18: =H18/G18 -> 0.78243819 | J18: =IF(I18<=X_Limit,"X",IF(I18<=Y_Limit,"Y","Z")) -> Y | K18: =F18&J18 -> AY | L18: =AVERAGE(_xlfn.XLOOKUP(A18,DemandCodes,DemandPeak2010))/AVERAGE(_xlfn.XLOOKUP(A18,DemandCodes,DemandTrain)) -> 1.0156457 | M18: =IF(L18>=SeasonalLimit,"Yes","No") -> No | N18: =_xlfn.XLOOKUP(A18,SKUList,SKU_Data!$C$5:$C$154)/_xlfn.XLOOKUP(A18,SKUList,SKU_Data!$D$5:$D$154) -> 1.8940468 | O18: =IF(K18=_xlfn.XLOOKUP(A18,SKUList,SKU_Data!$F$5:$F$154),"✓","≠") -> ✓ | P18: How to read it
A19: =SKU_Data!A19 -> 22469 | B19: =_xlfn.XLOOKUP(A19,SKUList,SKU_Data!$B$5:$B$154) -> HEART OF WICKER SMALL | C19: =_xlfn.XLOOKUP(A19,SKUList,SKU_Data!$E$5:$E$154) -> 30715.45 | D19: =_xlfn.RANK.EQ(C19,$C$5:$C$154) -> 15 | E19: =SUMIFS($C$5:$C$154,$C$5:$C$154,">="&C19)/SUM($C$5:$C$154) -> 0.28437659 | F19: =IF(E19<=A_Limit,"A",IF(E19<=B_Limit,"B","C")) -> A | G19: =AVERAGE(_xlfn.XLOOKUP(A19,DemandCodes,DemandLast52)) -> 331.48077 | H19: =_xlfn.STDEV.S(_xlfn.XLOOKUP(A19,DemandCodes,DemandLast52)) -> 332.30712 | I19: =H19/G19 -> 1.0024929 | J19: =IF(I19<=X_Limit,"X",IF(I19<=Y_Limit,"Y","Z")) -> Y | K19: =F19&J19 -> AY | L19: =AVERAGE(_xlfn.XLOOKUP(A19,DemandCodes,DemandPeak2010))/AVERAGE(_xlfn.XLOOKUP(A19,DemandCodes,DemandTrain)) -> 1.4407266 | M19: =IF(L19>=SeasonalLimit,"Yes","No") -> Yes | N19: =_xlfn.XLOOKUP(A19,SKUList,SKU_Data!$C$5:$C$154)/_xlfn.XLOOKUP(A19,SKUList,SKU_Data!$D$5:$D$154) -> 1.7802038 | O19: =IF(K19=_xlfn.XLOOKUP(A19,SKUList,SKU_Data!$F$5:$F$154),"✓","≠") -> ✓ | P19: AX = valuable and steady: easy to forecast, keep lean stock.
A20: =SKU_Data!A20 -> 22178 | B20: =_xlfn.XLOOKUP(A20,SKUList,SKU_Data!$B$5:$B$154) -> VICTORIAN GLASS HANGING T-LIGHT | C20: =_xlfn.XLOOKUP(A20,SKUList,SKU_Data!$E$5:$E$154) -> 30004.53 | D20: =_xlfn.RANK.EQ(C20,$C$5:$C$154) -> 16 | E20: =SUMIFS($C$5:$C$154,$C$5:$C$154,">="&C20)/SUM($C$5:$C$154) -> 0.29375155 | F20: =IF(E20<=A_Limit,"A",IF(E20<=B_Limit,"B","C")) -> A | G20: =AVERAGE(_xlfn.XLOOKUP(A20,DemandCodes,DemandLast52)) -> 433.98077 | H20: =_xlfn.STDEV.S(_xlfn.XLOOKUP(A20,DemandCodes,DemandLast52)) -> 278.41819 | I20: =H20/G20 -> 0.64154498 | J20: =IF(I20<=X_Limit,"X",IF(I20<=Y_Limit,"Y","Z")) -> X | K20: =F20&J20 -> AX | L20: =AVERAGE(_xlfn.XLOOKUP(A20,DemandCodes,DemandPeak2010))/AVERAGE(_xlfn.XLOOKUP(A20,DemandCodes,DemandTrain)) -> 1.6354751 | M20: =IF(L20>=SeasonalLimit,"Yes","No") -> Yes | N20: =_xlfn.XLOOKUP(A20,SKUList,SKU_Data!$C$5:$C$154)/_xlfn.XLOOKUP(A20,SKUList,SKU_Data!$D$5:$D$154) -> 1.3309946 | O20: =IF(K20=_xlfn.XLOOKUP(A20,SKUList,SKU_Data!$F$5:$F$154),"✓","≠") -> ✓ | P20: AZ = valuable but erratic: the risky box; needs the most safety stock and attention.
A21: =SKU_Data!A21 -> 21931 | B21: =_xlfn.XLOOKUP(A21,SKUList,SKU_Data!$B$5:$B$154) -> JUMBO STORAGE BAG SUKI | C21: =_xlfn.XLOOKUP(A21,SKUList,SKU_Data!$E$5:$E$154) -> 29521.44 | D21: =_xlfn.RANK.EQ(C21,$C$5:$C$154) -> 17 | E21: =SUMIFS($C$5:$C$154,$C$5:$C$154,">="&C21)/SUM($C$5:$C$154) -> 0.30297557 | F21: =IF(E21<=A_Limit,"A",IF(E21<=B_Limit,"B","C")) -> A | G21: =AVERAGE(_xlfn.XLOOKUP(A21,DemandCodes,DemandLast52)) -> 250.63462 | H21: =_xlfn.STDEV.S(_xlfn.XLOOKUP(A21,DemandCodes,DemandLast52)) -> 113.00391 | I21: =H21/G21 -> 0.45087112 | J21: =IF(I21<=X_Limit,"X",IF(I21<=Y_Limit,"Y","Z")) -> X | K21: =F21&J21 -> AX | L21: =AVERAGE(_xlfn.XLOOKUP(A21,DemandCodes,DemandPeak2010))/AVERAGE(_xlfn.XLOOKUP(A21,DemandCodes,DemandTrain)) -> 1.2146196 | M21: =IF(L21>=SeasonalLimit,"Yes","No") -> No | N21: =_xlfn.XLOOKUP(A21,SKUList,SKU_Data!$C$5:$C$154)/_xlfn.XLOOKUP(A21,SKUList,SKU_Data!$D$5:$D$154) -> 2.2536054 | O21: =IF(K21=_xlfn.XLOOKUP(A21,SKUList,SKU_Data!$F$5:$F$154),"✓","≠") -> ✓ | P21: CZ = low value and erratic: candidates for make-to-order or delisting.
A22: =SKU_Data!A22 -> 22112 | B22: =_xlfn.XLOOKUP(A22,SKUList,SKU_Data!$B$5:$B$154) -> CHOCOLATE HOT WATER BOTTLE | C22: =_xlfn.XLOOKUP(A22,SKUList,SKU_Data!$E$5:$E$154) -> 28625.99 | D22: =_xlfn.RANK.EQ(C22,$C$5:$C$154) -> 18 | E22: =SUMIFS($C$5:$C$154,$C$5:$C$154,">="&C22)/SUM($C$5:$C$154) -> 0.3119198 | F22: =IF(E22<=A_Limit,"A",IF(E22<=B_Limit,"B","C")) -> A | G22: =AVERAGE(_xlfn.XLOOKUP(A22,DemandCodes,DemandLast52)) -> 101.36538 | H22: =_xlfn.STDEV.S(_xlfn.XLOOKUP(A22,DemandCodes,DemandLast52)) -> 133.41576 | I22: =H22/G22 -> 1.3161866 | J22: =IF(I22<=X_Limit,"X",IF(I22<=Y_Limit,"Y","Z")) -> Z | K22: =F22&J22 -> AZ | L22: =AVERAGE(_xlfn.XLOOKUP(A22,DemandCodes,DemandPeak2010))/AVERAGE(_xlfn.XLOOKUP(A22,DemandCodes,DemandTrain)) -> 3.1597499 | M22: =IF(L22>=SeasonalLimit,"Yes","No") -> Yes | N22: =_xlfn.XLOOKUP(A22,SKUList,SKU_Data!$C$5:$C$154)/_xlfn.XLOOKUP(A22,SKUList,SKU_Data!$D$5:$D$154) -> 5.4037544 | O22: =IF(K22=_xlfn.XLOOKUP(A22,SKUList,SKU_Data!$F$5:$F$154),"✓","≠") -> ✓ | P22: Check vs SQL/Python (default limits only): | T22: =COUNTIF($O$5:$O$154,"✓")&" / 150 match" -> 150 / 150 match
A23: =SKU_Data!A23 -> 22114 | B23: =_xlfn.XLOOKUP(A23,SKUList,SKU_Data!$B$5:$B$154) -> HOT WATER BOTTLE TEA AND SYMPATHY | C23: =_xlfn.XLOOKUP(A23,SKUList,SKU_Data!$E$5:$E$154) -> 28284.91 | D23: =_xlfn.RANK.EQ(C23,$C$5:$C$154) -> 19 | E23: =SUMIFS($C$5:$C$154,$C$5:$C$154,">="&C23)/SUM($C$5:$C$154) -> 0.32075746 | F23: =IF(E23<=A_Limit,"A",IF(E23<=B_Limit,"B","C")) -> A | G23: =AVERAGE(_xlfn.XLOOKUP(A23,DemandCodes,DemandLast52)) -> 94.653846 | H23: =_xlfn.STDEV.S(_xlfn.XLOOKUP(A23,DemandCodes,DemandLast52)) -> 161.55129 | I23: =H23/G23 -> 1.7067588 | J23: =IF(I23<=X_Limit,"X",IF(I23<=Y_Limit,"Y","Z")) -> Z | K23: =F23&J23 -> AZ | L23: =AVERAGE(_xlfn.XLOOKUP(A23,DemandCodes,DemandPeak2010))/AVERAGE(_xlfn.XLOOKUP(A23,DemandCodes,DemandTrain)) -> 3.3254182 | M23: =IF(L23>=SeasonalLimit,"Yes","No") -> Yes | N23: =_xlfn.XLOOKUP(A23,SKUList,SKU_Data!$C$5:$C$154)/_xlfn.XLOOKUP(A23,SKUList,SKU_Data!$D$5:$D$154) -> 5.7144305 | O23: =IF(K23=_xlfn.XLOOKUP(A23,SKUList,SKU_Data!$F$5:$F$154),"✓","≠") -> ✓
A24: =SKU_Data!A24 -> 22470 | B24: =_xlfn.XLOOKUP(A24,SKUList,SKU_Data!$B$5:$B$154) -> HEART OF WICKER LARGE | C24: =_xlfn.XLOOKUP(A24,SKUList,SKU_Data!$E$5:$E$154) -> 27315.13 | D24: =_xlfn.RANK.EQ(C24,$C$5:$C$154) -> 20 | E24: =SUMIFS($C$5:$C$154,$C$5:$C$154,">="&C24)/SUM($C$5:$C$154) -> 0.32929211 | F24: =IF(E24<=A_Limit,"A",IF(E24<=B_Limit,"B","C")) -> A | G24: =AVERAGE(_xlfn.XLOOKUP(A24,DemandCodes,DemandLast52)) -> 173.32692 | H24: =_xlfn.STDEV.S(_xlfn.XLOOKUP(A24,DemandCodes,DemandLast52)) -> 249.91424 | I24: =H24/G24 -> 1.4418662 | J24: =IF(I24<=X_Limit,"X",IF(I24<=Y_Limit,"Y","Z")) -> Z | K24: =F24&J24 -> AZ | L24: =AVERAGE(_xlfn.XLOOKUP(A24,DemandCodes,DemandPeak2010))/AVERAGE(_xlfn.XLOOKUP(A24,DemandCodes,DemandTrain)) -> 2.1773857 | M24: =IF(L24>=SeasonalLimit,"Yes","No") -> Yes | N24: =_xlfn.XLOOKUP(A24,SKUList,SKU_Data!$C$5:$C$154)/_xlfn.XLOOKUP(A24,SKUList,SKU_Data!$D$5:$D$154) -> 3.0286393 | O24: =IF(K24=_xlfn.XLOOKUP(A24,SKUList,SKU_Data!$F$5:$F$154),"✓","≠") -> ✓
A25: =SKU_Data!A25 -> 22411 | B25: =_xlfn.XLOOKUP(A25,SKUList,SKU_Data!$B$5:$B$154) -> JUMBO SHOPPER VINTAGE RED PAISLEY | C25: =_xlfn.XLOOKUP(A25,SKUList,SKU_Data!$E$5:$E$154) -> 26756.59 | D25: =_xlfn.RANK.EQ(C25,$C$5:$C$154) -> 21 | E25: =SUMIFS($C$5:$C$154,$C$5:$C$154,">="&C25)/SUM($C$5:$C$154) -> 0.33765224 | F25: =IF(E25<=A_Limit,"A",IF(E25<=B_Limit,"B","C")) -> A | G25: =AVERAGE(_xlfn.XLOOKUP(A25,DemandCodes,DemandLast52)) -> 224.19231 | H25: =_xlfn.STDEV.S(_xlfn.XLOOKUP(A25,DemandCodes,DemandLast52)) -> 129.38892 | I25: =H25/G25 -> 0.57713361 | J25: =IF(I25<=X_Limit,"X",IF(I25<=Y_Limit,"Y","Z")) -> X | K25: =F25&J25 -> AX | L25: =AVERAGE(_xlfn.XLOOKUP(A25,DemandCodes,DemandPeak2010))/AVERAGE(_xlfn.XLOOKUP(A25,DemandCodes,DemandTrain)) -> 1.574114 | M25: =IF(L25>=SeasonalLimit,"Yes","No") -> Yes | N25: =_xlfn.XLOOKUP(A25,SKUList,SKU_Data!$C$5:$C$154)/_xlfn.XLOOKUP(A25,SKUList,SKU_Data!$D$5:$D$154) -> 2.279309 | O25: =IF(K25=_xlfn.XLOOKUP(A25,SKUList,SKU_Data!$F$5:$F$154),"✓","≠") -> ✓
A26: =SKU_Data!A26 -> 22355 | B26: =_xlfn.XLOOKUP(A26,SKUList,SKU_Data!$B$5:$B$154) -> CHARLOTTE BAG SUKI DESIGN | C26: =_xlfn.XLOOKUP(A26,SKUList,SKU_Data!$E$5:$E$154) -> 26739.4 | D26: =_xlfn.RANK.EQ(C26,$C$5:$C$154) -> 22 | E26: =SUMIFS($C$5:$C$154,$C$5:$C$154,">="&C26)/SUM($C$5:$C$154) -> 0.34600701 | F26: =IF(E26<=A_Limit,"A",IF(E26<=B_Limit,"B","C")) -> A | G26: =AVERAGE(_xlfn.XLOOKUP(A26,DemandCodes,DemandLast52)) -> 323.69231 | H26: =_xlfn.STDEV.S(_xlfn.XLOOKUP(A26,DemandCodes,DemandLast52)) -> 152.94348 | I26: =H26/G26 -> 0.47249649 | J26: =IF(I26<=X_Limit,"X",IF(I26<=Y_Limit,"Y","Z")) -> X | K26: =F26&J26 -> AX | L26: =AVERAGE(_xlfn.XLOOKUP(A26,DemandCodes,DemandPeak2010))/AVERAGE(_xlfn.XLOOKUP(A26,DemandCodes,DemandTrain)) -> 1.4400386 | M26: =IF(L26>=SeasonalLimit,"Yes","No") -> Yes | N26: =_xlfn.XLOOKUP(A26,SKUList,SKU_Data!$C$5:$C$154)/_xlfn.XLOOKUP(A26,SKUList,SKU_Data!$D$5:$D$154) -> 1.5813126 | O26: =IF(K26=_xlfn.XLOOKUP(A26,SKUList,SKU_Data!$F$5:$F$154),"✓","≠") -> ✓
A27: =SKU_Data!A27 -> 20685 | B27: =_xlfn.XLOOKUP(A27,SKUList,SKU_Data!$B$5:$B$154) -> DOORMAT RED RETROSPOT | C27: =_xlfn.XLOOKUP(A27,SKUList,SKU_Data!$E$5:$E$154) -> 26531.03 | D27: =_xlfn.RANK.EQ(C27,$C$5:$C$154) -> 23 | E27: =SUMIFS($C$5:$C$154,$C$5:$C$154,">="&C27)/SUM($C$5:$C$154) -> 0.35429666 | F27: =IF(E27<=A_Limit,"A",IF(E27<=B_Limit,"B","C")) -> A | G27: =AVERAGE(_xlfn.XLOOKUP(A27,DemandCodes,DemandLast52)) -> 74.615385 | H27: =_xlfn.STDEV.S(_xlfn.XLOOKUP(A27,DemandCodes,DemandLast52)) -> 96.675555 | I27: =H27/G27 -> 1.2956518 | J27: =IF(I27<=X_Limit,"X",IF(I27<=Y_Limit,"Y","Z")) -> Z | K27: =F27&J27 -> AZ | L27: =AVERAGE(_xlfn.XLOOKUP(A27,DemandCodes,DemandPeak2010))/AVERAGE(_xlfn.XLOOKUP(A27,DemandCodes,DemandTrain)) -> 1.0686052 | M27: =IF(L27>=SeasonalLimit,"Yes","No") -> No | N27: =_xlfn.XLOOKUP(A27,SKUList,SKU_Data!$C$5:$C$154)/_xlfn.XLOOKUP(A27,SKUList,SKU_Data!$D$5:$D$154) -> 6.840408 | O27: =IF(K27=_xlfn.XLOOKUP(A27,SKUList,SKU_Data!$F$5:$F$154),"✓","≠") -> ✓
A28: =SKU_Data!A28 -> 85099C | B28: =_xlfn.XLOOKUP(A28,SKUList,SKU_Data!$B$5:$B$154) -> JUMBO BAG BAROQUE BLACK WHITE | C28: =_xlfn.XLOOKUP(A28,SKUList,SKU_Data!$E$5:$E$154) -> 26437.73 | D28: =_xlfn.RANK.EQ(C28,$C$5:$C$154) -> 24 | E28: =SUMIFS($C$5:$C$154,$C$5:$C$154,">="&C28)/SUM($C$5:$C$154) -> 0.36255717 | F28: =IF(E28<=A_Limit,"A",IF(E28<=B_Limit,"B","C")) -> A | G28: =AVERAGE(_xlfn.XLOOKUP(A28,DemandCodes,DemandLast52)) -> 252.19231 | H28: =_xlfn.STDEV.S(_xlfn.XLOOKUP(A28,DemandCodes,DemandLast52)) -> 147.08008 | I28: =H28/G28 -> 0.58320606 | J28: =IF(I28<=X_Limit,"X",IF(I28<=Y_Limit,"Y","Z")) -> X | K28: =F28&J28 -> AX | L28: =AVERAGE(_xlfn.XLOOKUP(A28,DemandCodes,DemandPeak2010))/AVERAGE(_xlfn.XLOOKUP(A28,DemandCodes,DemandTrain)) -> 1.4668478 | M28: =IF(L28>=SeasonalLimit,"Yes","No") -> Yes | N28: =_xlfn.XLOOKUP(A28,SKUList,SKU_Data!$C$5:$C$154)/_xlfn.XLOOKUP(A28,SKUList,SKU_Data!$D$5:$D$154) -> 2.0118308 | O28: =IF(K28=_xlfn.XLOOKUP(A28,SKUList,SKU_Data!$F$5:$F$154),"✓","≠") -> ✓
A29: =SKU_Data!A29 -> 22629 | B29: =_xlfn.XLOOKUP(A29,SKUList,SKU_Data!$B$5:$B$154) -> SPACEBOY LUNCH BOX | C29: =_xlfn.XLOOKUP(A29,SKUList,SKU_Data!$E$5:$E$154) -> 25292.45 | D29: =_xlfn.RANK.EQ(C29,$C$5:$C$154) -> 25 | E29: =SUMIFS($C$5:$C$154,$C$5:$C$154,">="&C29)/SUM($C$5:$C$154) -> 0.37045983 | F29: =IF(E29<=A_Limit,"A",IF(E29<=B_Limit,"B","C")) -> A | G29: =AVERAGE(_xlfn.XLOOKUP(A29,DemandCodes,DemandLast52)) -> 270.01923 | H29: =_xlfn.STDEV.S(_xlfn.XLOOKUP(A29,DemandCodes,DemandLast52)) -> 180.60079 | I29: =H29/G29 -> 0.66884419 | J29: =IF(I29<=X_Limit,"X",IF(I29<=Y_Limit,"Y","Z")) -> X | K29: =F29&J29 -> AX | L29: =AVERAGE(_xlfn.XLOOKUP(A29,DemandCodes,DemandPeak2010))/AVERAGE(_xlfn.XLOOKUP(A29,DemandCodes,DemandTrain)) -> 1.7959148 | M29: =IF(L29>=SeasonalLimit,"Yes","No") -> Yes | N29: =_xlfn.XLOOKUP(A29,SKUList,SKU_Data!$C$5:$C$154)/_xlfn.XLOOKUP(A29,SKUList,SKU_Data!$D$5:$D$154) -> 1.8010039 | O29: =IF(K29=_xlfn.XLOOKUP(A29,SKUList,SKU_Data!$F$5:$F$154),"✓","≠") -> ✓
A30: =SKU_Data!A30 -> 22457 | B30: =_xlfn.XLOOKUP(A30,SKUList,SKU_Data!$B$5:$B$154) -> NATURAL SLATE HEART CHALKBOARD | C30: =_xlfn.XLOOKUP(A30,SKUList,SKU_Data!$E$5:$E$154) -> 25172.56 | D30: =_xlfn.RANK.EQ(C30,$C$5:$C$154) -> 26 | E30: =SUMIFS($C$5:$C$154,$C$5:$C$154,">="&C30)/SUM($C$5:$C$154) -> 0.37832503 | F30: =IF(E30<=A_Limit,"A",IF(E30<=B_Limit,"B","C")) -> A | G30: =AVERAGE(_xlfn.XLOOKUP(A30,DemandCodes,DemandLast52)) -> 156.69231 | H30: =_xlfn.STDEV.S(_xlfn.XLOOKUP(A30,DemandCodes,DemandLast52)) -> 69.601819 | I30: =H30/G30 -> 0.44419423 | J30: =IF(I30<=X_Limit,"X",IF(I30<=Y_Limit,"Y","Z")) -> X | K30: =F30&J30 -> AX | L30: =AVERAGE(_xlfn.XLOOKUP(A30,DemandCodes,DemandPeak2010))/AVERAGE(_xlfn.XLOOKUP(A30,DemandCodes,DemandTrain)) -> 1.6347442 | M30: =IF(L30>=SeasonalLimit,"Yes","No") -> Yes | N30: =_xlfn.XLOOKUP(A30,SKUList,SKU_Data!$C$5:$C$154)/_xlfn.XLOOKUP(A30,SKUList,SKU_Data!$D$5:$D$154) -> 3.088451 | O30: =IF(K30=_xlfn.XLOOKUP(A30,SKUList,SKU_Data!$F$5:$F$154),"✓","≠") -> ✓
A31: =SKU_Data!A31 -> 21915 | B31: =_xlfn.XLOOKUP(A31,SKUList,SKU_Data!$B$5:$B$154) -> RED HARMONICA IN BOX | C31: =_xlfn.XLOOKUP(A31,SKUList,SKU_Data!$E$5:$E$154) -> 25165.67 | D31: =_xlfn.RANK.EQ(C31,$C$5:$C$154) -> 27 | E31: =SUMIFS($C$5:$C$154,$C$5:$C$154,">="&C31)/SUM($C$5:$C$154) -> 0.38618808 | F31: =IF(E31<=A_Limit,"A",IF(E31<=B_Limit,"B","C")) -> A | G31: =AVERAGE(_xlfn.XLOOKUP(A31,DemandCodes,DemandLast52)) -> 400.5 | H31: =_xlfn.STDEV.S(_xlfn.XLOOKUP(A31,DemandCodes,DemandLast52)) -> 512.11807 | I31: =H31/G31 -> 1.2786968 | J31: =IF(I31<=X_Limit,"X",IF(I31<=Y_Limit,"Y","Z")) -> Z | K31: =F31&J31 -> AZ | L31: =AVERAGE(_xlfn.XLOOKUP(A31,DemandCodes,DemandPeak2010))/AVERAGE(_xlfn.XLOOKUP(A31,DemandCodes,DemandTrain)) -> 2.1347613 | M31: =IF(L31>=SeasonalLimit,"Yes","No") -> Yes | N31: =_xlfn.XLOOKUP(A31,SKUList,SKU_Data!$C$5:$C$154)/_xlfn.XLOOKUP(A31,SKUList,SKU_Data!$D$5:$D$154) -> 1.208511 | O31: =IF(K31=_xlfn.XLOOKUP(A31,SKUList,SKU_Data!$F$5:$F$154),"✓","≠") -> ✓
A32: =SKU_Data!A32 -> 48138 | B32: =_xlfn.XLOOKUP(A32,SKUList,SKU_Data!$B$5:$B$154) -> DOORMAT UNION FLAG | C32: =_xlfn.XLOOKUP(A32,SKUList,SKU_Data!$E$5:$E$154) -> 24942.07 | D32: =_xlfn.RANK.EQ(C32,$C$5:$C$154) -> 28 | E32: =SUMIFS($C$5:$C$154,$C$5:$C$154,">="&C32)/SUM($C$5:$C$154) -> 0.39398127 | F32: =IF(E32<=A_Limit,"A",IF(E32<=B_Limit,"B","C")) -> A | G32: =AVERAGE(_xlfn.XLOOKUP(A32,DemandCodes,DemandLast52)) -> 70.942308 | H32: =_xlfn.STDEV.S(_xlfn.XLOOKUP(A32,DemandCodes,DemandLast52)) -> 100.92191 | I32: =H32/G32 -> 1.4225913 | J32: =IF(I32<=X_Limit,"X",IF(I32<=Y_Limit,"Y","Z")) -> Z | K32: =F32&J32 -> AZ | L32: =AVERAGE(_xlfn.XLOOKUP(A32,DemandCodes,DemandPeak2010))/AVERAGE(_xlfn.XLOOKUP(A32,DemandCodes,DemandTrain)) -> 0.95941503 | M32: =IF(L32>=SeasonalLimit,"Yes","No") -> No | N32: =_xlfn.XLOOKUP(A32,SKUList,SKU_Data!$C$5:$C$154)/_xlfn.XLOOKUP(A32,SKUList,SKU_Data!$D$5:$D$154) -> 6.7638337 | O32: =IF(K32=_xlfn.XLOOKUP(A32,SKUList,SKU_Data!$F$5:$F$154),"✓","≠") -> ✓
A33: =SKU_Data!A33 -> 84946 | B33: =_xlfn.XLOOKUP(A33,SKUList,SKU_Data!$B$5:$B$154) -> ANTIQUE SILVER TEA GLASS ETCHED | C33: =_xlfn.XLOOKUP(A33,SKUList,SKU_Data!$E$5:$E$154) -> 24434.12 | D33: =_xlfn.RANK.EQ(C33,$C$5:$C$154) -> 29 | E33: =SUMIFS($C$5:$C$154,$C$5:$C$154,">="&C33)/SUM($C$5:$C$154) -> 0.40161574 | F33: =IF(E33<=A_Limit,"A",IF(E33<=B_Limit,"B","C")) -> A | G33: =AVERAGE(_xlfn.XLOOKUP(A33,DemandCodes,DemandLast52)) -> 348.84615 | H33: =_xlfn.STDEV.S(_xlfn.XLOOKUP(A33,DemandCodes,DemandLast52)) -> 224.27612 | I33: =H33/G33 -> 0.6429084 | J33: =IF(I33<=X_Limit,"X",IF(I33<=Y_Limit,"Y","Z")) -> X | K33: =F33&J33 -> AX | L33: =AVERAGE(_xlfn.XLOOKUP(A33,DemandCodes,DemandPeak2010))/AVERAGE(_xlfn.XLOOKUP(A33,DemandCodes,DemandTrain)) -> 1.8302841 | M33: =IF(L33>=SeasonalLimit,"Yes","No") -> Yes | N33: =_xlfn.XLOOKUP(A33,SKUList,SKU_Data!$C$5:$C$154)/_xlfn.XLOOKUP(A33,SKUList,SKU_Data!$D$5:$D$154) -> 1.3428289 | O33: =IF(K33=_xlfn.XLOOKUP(A33,SKUList,SKU_Data!$F$5:$F$154),"✓","≠") -> ✓
A34: =SKU_Data!A34 -> 22326 | B34: =_xlfn.XLOOKUP(A34,SKUList,SKU_Data!$B$5:$B$154) -> ROUND SNACK BOXES SET OF4 WOODLAND | C34: =_xlfn.XLOOKUP(A34,SKUList,SKU_Data!$E$5:$E$154) -> 24126.93 | D34: =_xlfn.RANK.EQ(C34,$C$5:$C$154) -> 30 | E34: =SUMIFS($C$5:$C$154,$C$5:$C$154,">="&C34)/SUM($C$5:$C$154) -> 0.40915424 | F34: =IF(E34<=A_Limit,"A",IF(E34<=B_Limit,"B","C")) -> A | G34: =AVERAGE(_xlfn.XLOOKUP(A34,DemandCodes,DemandLast52)) -> 163.40385 | H34: =_xlfn.STDEV.S(_xlfn.XLOOKUP(A34,DemandCodes,DemandLast52)) -> 118.87747 | I34: =H34/G34 -> 0.72750718 | J34: =IF(I34<=X_Limit,"X",IF(I34<=Y_Limit,"Y","Z")) -> X | K34: =F34&J34 -> AX | L34: =AVERAGE(_xlfn.XLOOKUP(A34,DemandCodes,DemandPeak2010))/AVERAGE(_xlfn.XLOOKUP(A34,DemandCodes,DemandTrain)) -> 1.1692199 | M34: =IF(L34>=SeasonalLimit,"Yes","No") -> No | N34: =_xlfn.XLOOKUP(A34,SKUList,SKU_Data!$C$5:$C$154)/_xlfn.XLOOKUP(A34,SKUList,SKU_Data!$D$5:$D$154) -> 2.8399566 | O34: =IF(K34=_xlfn.XLOOKUP(A34,SKUList,SKU_Data!$F$5:$F$154),"✓","≠") -> ✓
... A154: =SKU_Data!A154 -> 21791 | B154: =_xlfn.XLOOKUP(A154,SKUList,SKU_Data!$B$5:$B$154) -> VINTAGE HEADS AND TAILS CARD GAME | C154: =_xlfn.XLOOKUP(A154,SKUList,SKU_Data!$E$5:$E$154) -> 9984.99 | D154: =_xlfn.RANK.EQ(C154,$C$5:$C$154) -> 150 | E154: =SUMIFS($C$5:$C$154,$C$5:$C$154,">="&C154)/SUM($C$5:$C$154) -> 1 | F154: =IF(E154<=A_Limit,"A",IF(E154<=B_Limit,"B","C")) -> C | G154: =AVERAGE(_xlfn.XLOOKUP(A154,DemandCodes,DemandLast52)) -> 143.75 | H154: =_xlfn.STDEV.S(_xlfn.XLOOKUP(A154,DemandCodes,DemandLast52)) -> 160.7869 | I154: =H154/G154 -> 1.1185175 | J154: =IF(I154<=X_Limit,"X",IF(I154<=Y_Limit,"Y","Z")) -> Y | K154: =F154&J154 -> CY | L154: =AVERAGE(_xlfn.XLOOKUP(A154,DemandCodes,DemandPeak2010))/AVERAGE(_xlfn.XLOOKUP(A154,DemandCodes,DemandTrain)) -> 2.3637194 | M154: =IF(L154>=SeasonalLimit,"Yes","No") -> Yes | N154: =_xlfn.XLOOKUP(A154,SKUList,SKU_Data!$C$5:$C$154)/_xlfn.XLOOKUP(A154,SKUList,SKU_Data!$D$5:$D$154) -> 1.3353735 | O154: =IF(K154=_xlfn.XLOOKUP(A154,SKUList,SKU_Data!$F$5:$F$154),"✓","≠") -> ✓

Sheet Forecast
A1: Forecast one SKU: four methods, backtest and accuracy
A2: Pick a stock code in C4. Train = weeks 1-91 (fit), Test = weeks 92-103 (Sep-Nov 2011, the backtest), Future = weeks 104-115.
B4: Stock code (pick one) | C4: 85123A | D4: =C4&"" -> 85123A | E4: Moving-average window (weeks) | G4: 8 | K4: Backtest accuracy (test weeks 92-103) | S4: How the columns work
B5: Description | C5: =_xlfn.XLOOKUP($D$4,SKUList,SKU_Data!$B$5:$B$154) -> WHITE HANGING HEART T-LIGHT HOLDER | E5: SES α (fitted) | G5: =_xlfn.XLOOKUP($D$4,ParamCodes,Model_Params!$B$5:$B$154) -> 0.5 | K5: Method | L5: WAPE | M5: MAPE | N5: Bias | O5: Score | Q5: Check | S5: SES level: level = α × actual + (1 − α) × last level. The forecast is the last level, flat for every future week.
B6: ABC-XYZ class | C6: =_xlfn.XLOOKUP($D$4,ClsCode,ClsClass) -> AY | E6: SES α override (optional) | K6: Naive | L6: =SUM(Q106:Q117)/SUM($D$106:$D$117) -> 0.52857143 | M6: =IFERROR(AVERAGE(W106:W117),"n/a") -> 0.50439448 | N6: =(SUM(G106:G117)-SUM($D$106:$D$117))/SUM($D$106:$D$117) -> -0.43631961 | O6: =L6+ABS(N6) -> 0.96489104 | Q6: =IF(ABS(SUM(Q106:Q117)-SUMIFS(BtAbsErr,BtCode,$D$4,BtMethod,"Naive"))<0.01,"✓ same","differs") -> ✓ same | S6: Naive: the last actual (week 91 for the backtest, week 103 for the future). Moving average: average of the last N weeks.
B7: Seasonal? (Christmas uplift) | C7: =_xlfn.XLOOKUP($D$4,ClsCode,ClsSeasonal)&" ("&TEXT(_xlfn.XLOOKUP($D$4,ClsCode,ABC_XYZ!$L$5:$L$154),"0.00")&")" -> Yes (1.35) | E7: SES α used | G7: =IF(G6="",G5,G6) -> 0.5 | K7: Moving average | L7: =SUM(R106:R117)/SUM($D$106:$D$117) -> 0.44576271 | M7: =IFERROR(AVERAGE(X106:X117),"n/a") -> 0.64512202 | N7: =(SUM(H106:H117)-SUM($D$106:$D$117))/SUM($D$106:$D$117) -> -0.080205811 | O7: =L7+ABS(N7) -> 0.52596852 | Q7: =IF(ABS(SUM(R106:R117)-SUMIFS(BtAbsErr,BtCode,$D$4,BtMethod,"Moving average"))<0.01,"✓ same","differs") -> ✓ same | S7: Holt-Winters start: level = average of weeks 1-52, trend = 0, season = 9-week centred average − level (smooths out noise).
B8: Method chosen for its class | C8: =IF(AND(_xlfn.XLOOKUP(C6,BestClass,BestMethod)="Holt-Winters",_xlfn.XLOOKUP($D$4,ClsCode,ClsSeasonal)="No"),_xlfn.XLOOKUP(C6,BestClass,BestFlat),_xlfn.XLOOKUP(C6,BestClass,BestMethod)) -> Holt-Winters | E8: Holt-Winters α / β / γ | G8: =_xlfn.XLOOKUP($D$4,ParamCodes,Model_Params!$C$5:$C$154) -> 0.05 | H8: =_xlfn.XLOOKUP($D$4,ParamCodes,Model_Params!$D$5:$D$154) -> 0.05 | I8: =_xlfn.XLOOKUP($D$4,ParamCodes,Model_Params!$E$5:$E$154) -> 0 | K8: SES | L8: =SUM(S106:S117)/SUM($D$106:$D$117) -> 0.47060034 | M8: =IFERROR(AVERAGE(Y106:Y117),"n/a") -> 0.52951457 | N8: =(SUM(F106:F117)-SUM($D$106:$D$117))/SUM($D$106:$D$117) -> -0.28607178 | O8: =L8+ABS(N8) -> 0.75667212 | Q8: =IF(ABS(SUM(S106:S117)-SUMIFS(BtAbsErr,BtCode,$D$4,BtMethod,"SES"))<0.01,"✓ same","differs") -> ✓ same | S8: Then each week: level = α(actual − season a year ago) + (1−α)(last level + last trend); trend = β(level change) + (1−β)last trend;
K9: Holt-Winters | L9: =SUM(T106:T117)/SUM($D$106:$D$117) -> 0.42734709 | M9: =IFERROR(AVERAGE(Z106:Z117),"n/a") -> 0.53092891 | N9: =(SUM(M106:M117)-SUM($D$106:$D$117))/SUM($D$106:$D$117) -> -0.17466733 | O9: =L9+ABS(N9) -> 0.60201442 | Q9: =IF(ABS(SUM(T106:T117)-SUMIFS(BtAbsErr,BtCode,$D$4,BtMethod,"Holt-Winters"))<0.01,"✓ same","differs") -> ✓ same | S9: season = γ(actual − level) + (1−γ)(season a year ago). Forecast = level + trend × weeks ahead + season a year ago (never below 0).
K10: Excel FORECAST.ETS | L10: =SUM(U106:U117)/SUM($D$106:$D$117) -> 0.48165305 | M10: =IFERROR(AVERAGE(AA106:AA117),"n/a") -> 0.54911294 | N10: =(SUM(N106:N117)-SUM($D$106:$D$117))/SUM($D$106:$D$117) -> -0.024594272 | O10: =L10+ABS(N10) -> 0.50624733 | Q10: (Excel's own) | S10: Excel FORECAST.ETS: Excel's built-in Holt-Winters (AAA) with seasonality 52; it picks its own parameters, so it differs a little.
B11: The window and α override only change this sheet (the Backtest and Policy sheets use the fitted values and an 8-week window). | S11: #N/A cells are on purpose (no forecast in training weeks / no actuals in future weeks): charts skip #N/A instead of drawing zeros.
K12: Matches the Python batch run? (needs window 8 and fitted α)
A14: Wk | B14: Week starting | C14: Period | D14: Actual demand | E14: SES level | F14: SES forecast | G14: Naive forecast | H14: Moving avg forecast | I14: HW smoothed (yr 1) | J14: HW level | K14: HW trend | L14: HW season | M14: Holt-Winters forecast | N14: Excel FORECAST.ETS | Q14: |err| Naive | R14: |err| MA | S14: |err| SES | T14: |err| HW | U14: |err| ETS | V14: APE Naive | W14: APE MA | X14: APE SES | Y14: APE HW | Z14: APE ETS
A15: 1 | B15: =Demand!C$4 -> 40154 | C15: Train | D15: =INDEX(DemandAll,MATCH($D$4,DemandCodes,0),A15) -> 3138 | E15: =D15 -> 3138 | F15: =NA() -> #N/A | G15: =NA() -> #N/A | H15: =NA() -> #N/A | I15: =AVERAGE(INDEX($D$15:$D$105,MAX(1,A15-4)):INDEX($D$15:$D$105,MIN(91,A15+4))) -> 1263.2 | L15: =I15-$J$66 -> 206.79615 | M15: =NA() -> #N/A | N15: =NA() -> #N/A
A16: 2 | B16: =Demand!D$4 -> 40161 | C16: Train | D16: =INDEX(DemandAll,MATCH($D$4,DemandCodes,0),A16) -> 1286 | E16: =$G$7*D16+(1-$G$7)*E15 -> 2212 | F16: =NA() -> #N/A | G16: =NA() -> #N/A | H16: =NA() -> #N/A | I16: =AVERAGE(INDEX($D$15:$D$105,MAX(1,A16-4)):INDEX($D$15:$D$105,MIN(91,A16+4))) -> 1205.5 | L16: =I16-$J$66 -> 149.09615 | M16: =NA() -> #N/A | N16: =NA() -> #N/A
A17: 3 | B17: =Demand!E$4 -> 40168 | C17: Train | D17: =INDEX(DemandAll,MATCH($D$4,DemandCodes,0),A17) -> 125 | E17: =$G$7*D17+(1-$G$7)*E16 -> 1168.5 | F17: =NA() -> #N/A | G17: =NA() -> #N/A | H17: =NA() -> #N/A | I17: =AVERAGE(INDEX($D$15:$D$105,MAX(1,A17-4)):INDEX($D$15:$D$105,MIN(91,A17+4))) -> 1234 | L17: =I17-$J$66 -> 177.59615 | M17: =NA() -> #N/A | N17: =NA() -> #N/A
A18: 4 | B18: =Demand!F$4 -> 40175 | C18: Train | D18: =INDEX(DemandAll,MATCH($D$4,DemandCodes,0),A18) -> 0 | E18: =$G$7*D18+(1-$G$7)*E17 -> 584.25 | F18: =NA() -> #N/A | G18: =NA() -> #N/A | H18: =NA() -> #N/A | I18: =AVERAGE(INDEX($D$15:$D$105,MAX(1,A18-4)):INDEX($D$15:$D$105,MIN(91,A18+4))) -> 1251.375 | L18: =I18-$J$66 -> 194.97115 | M18: =NA() -> #N/A | N18: =NA() -> #N/A
A19: 5 | B19: =Demand!G$4 -> 40182 | C19: Train | D19: =INDEX(DemandAll,MATCH($D$4,DemandCodes,0),A19) -> 1767 | E19: =$G$7*D19+(1-$G$7)*E18 -> 1175.625 | F19: =NA() -> #N/A | G19: =NA() -> #N/A | H19: =NA() -> #N/A | I19: =AVERAGE(INDEX($D$15:$D$105,MAX(1,A19-4)):INDEX($D$15:$D$105,MIN(91,A19+4))) -> 1193 | L19: =I19-$J$66 -> 136.59615 | M19: =NA() -> #N/A | N19: =NA() -> #N/A
A20: 6 | B20: =Demand!H$4 -> 40189 | C20: Train | D20: =INDEX(DemandAll,MATCH($D$4,DemandCodes,0),A20) -> 917 | E20: =$G$7*D20+(1-$G$7)*E19 -> 1046.3125 | F20: =NA() -> #N/A | G20: =NA() -> #N/A | H20: =NA() -> #N/A | I20: =AVERAGE(INDEX($D$15:$D$105,MAX(1,A20-4)):INDEX($D$15:$D$105,MIN(91,A20+4))) -> 908.33333 | L20: =I20-$J$66 -> -148.07051 | M20: =NA() -> #N/A | N20: =NA() -> #N/A
A21: 7 | B21: =Demand!I$4 -> 40196 | C21: Train | D21: =INDEX(DemandAll,MATCH($D$4,DemandCodes,0),A21) -> 1405 | E21: =$G$7*D21+(1-$G$7)*E20 -> 1225.6562 | F21: =NA() -> #N/A | G21: =NA() -> #N/A | H21: =NA() -> #N/A | I21: =AVERAGE(INDEX($D$15:$D$105,MAX(1,A21-4)):INDEX($D$15:$D$105,MIN(91,A21+4))) -> 839.55556 | L21: =I21-$J$66 -> -216.84829 | M21: =NA() -> #N/A | N21: =NA() -> #N/A
A22: 8 | B22: =Demand!J$4 -> 40203 | C22: Train | D22: =INDEX(DemandAll,MATCH($D$4,DemandCodes,0),A22) -> 1373 | E22: =$G$7*D22+(1-$G$7)*E21 -> 1299.3281 | F22: =NA() -> #N/A | G22: =NA() -> #N/A | H22: =NA() -> #N/A | I22: =AVERAGE(INDEX($D$15:$D$105,MAX(1,A22-4)):INDEX($D$15:$D$105,MIN(91,A22+4))) -> 928.11111 | L22: =I22-$J$66 -> -128.29274 | M22: =NA() -> #N/A | N22: =NA() -> #N/A
A23: 9 | B23: =Demand!K$4 -> 40210 | C23: Train | D23: =INDEX(DemandAll,MATCH($D$4,DemandCodes,0),A23) -> 726 | E23: =$G$7*D23+(1-$G$7)*E22 -> 1012.6641 | F23: =NA() -> #N/A | G23: =NA() -> #N/A | H23: =NA() -> #N/A | I23: =AVERAGE(INDEX($D$15:$D$105,MAX(1,A23-4)):INDEX($D$15:$D$105,MIN(91,A23+4))) -> 1021.1111 | L23: =I23-$J$66 -> -35.292735 | M23: =NA() -> #N/A | N23: =NA() -> #N/A
A24: 10 | B24: =Demand!L$4 -> 40217 | C24: Train | D24: =INDEX(DemandAll,MATCH($D$4,DemandCodes,0),A24) -> 576 | E24: =$G$7*D24+(1-$G$7)*E23 -> 794.33203 | F24: =NA() -> #N/A | G24: =NA() -> #N/A | H24: =NA() -> #N/A | I24: =AVERAGE(INDEX($D$15:$D$105,MAX(1,A24-4)):INDEX($D$15:$D$105,MIN(91,A24+4))) -> 917.33333 | L24: =I24-$J$66 -> -139.07051 | M24: =NA() -> #N/A | N24: =NA() -> #N/A
A25: 11 | B25: =Demand!M$4 -> 40224 | C25: Train | D25: =INDEX(DemandAll,MATCH($D$4,DemandCodes,0),A25) -> 667 | E25: =$G$7*D25+(1-$G$7)*E24 -> 730.66602 | F25: =NA() -> #N/A | G25: =NA() -> #N/A | H25: =NA() -> #N/A | I25: =AVERAGE(INDEX($D$15:$D$105,MAX(1,A25-4)):INDEX($D$15:$D$105,MIN(91,A25+4))) -> 980 | L25: =I25-$J$66 -> -76.403846 | M25: =NA() -> #N/A | N25: =NA() -> #N/A
A26: 12 | B26: =Demand!N$4 -> 40231 | C26: Train | D26: =INDEX(DemandAll,MATCH($D$4,DemandCodes,0),A26) -> 922 | E26: =$G$7*D26+(1-$G$7)*E25 -> 826.33301 | F26: =NA() -> #N/A | G26: =NA() -> #N/A | H26: =NA() -> #N/A | I26: =AVERAGE(INDEX($D$15:$D$105,MAX(1,A26-4)):INDEX($D$15:$D$105,MIN(91,A26+4))) -> 954.77778 | L26: =I26-$J$66 -> -101.62607 | M26: =NA() -> #N/A | N26: =NA() -> #N/A
A27: 13 | B27: =Demand!O$4 -> 40238 | C27: Train | D27: =INDEX(DemandAll,MATCH($D$4,DemandCodes,0),A27) -> 837 | E27: =$G$7*D27+(1-$G$7)*E26 -> 831.6665 | F27: =NA() -> #N/A | G27: =NA() -> #N/A | H27: =NA() -> #N/A | I27: =AVERAGE(INDEX($D$15:$D$105,MAX(1,A27-4)):INDEX($D$15:$D$105,MIN(91,A27+4))) -> 901.66667 | L27: =I27-$J$66 -> -154.73718 | M27: =NA() -> #N/A | N27: =NA() -> #N/A
A28: 14 | B28: =Demand!P$4 -> 40245 | C28: Train | D28: =INDEX(DemandAll,MATCH($D$4,DemandCodes,0),A28) -> 833 | E28: =$G$7*D28+(1-$G$7)*E27 -> 832.33325 | F28: =NA() -> #N/A | G28: =NA() -> #N/A | H28: =NA() -> #N/A | I28: =AVERAGE(INDEX($D$15:$D$105,MAX(1,A28-4)):INDEX($D$15:$D$105,MIN(91,A28+4))) -> 921.55556 | L28: =I28-$J$66 -> -134.84829 | M28: =NA() -> #N/A | N28: =NA() -> #N/A
A29: 15 | B29: =Demand!Q$4 -> 40252 | C29: Train | D29: =INDEX(DemandAll,MATCH($D$4,DemandCodes,0),A29) -> 1481 | E29: =$G$7*D29+(1-$G$7)*E28 -> 1156.6666 | F29: =NA() -> #N/A | G29: =NA() -> #N/A | H29: =NA() -> #N/A | I29: =AVERAGE(INDEX($D$15:$D$105,MAX(1,A29-4)):INDEX($D$15:$D$105,MIN(91,A29+4))) -> 951.11111 | L29: =I29-$J$66 -> -105.29274 | M29: =NA() -> #N/A | N29: =NA() -> #N/A
A30: 16 | B30: =Demand!R$4 -> 40259 | C30: Train | D30: =INDEX(DemandAll,MATCH($D$4,DemandCodes,0),A30) -> 1178 | E30: =$G$7*D30+(1-$G$7)*E29 -> 1167.3333 | F30: =NA() -> #N/A | G30: =NA() -> #N/A | H30: =NA() -> #N/A | I30: =AVERAGE(INDEX($D$15:$D$105,MAX(1,A30-4)):INDEX($D$15:$D$105,MIN(91,A30+4))) -> 953.44444 | L30: =I30-$J$66 -> -102.9594 | M30: =NA() -> #N/A | N30: =NA() -> #N/A
A31: 17 | B31: =Demand!S$4 -> 40266 | C31: Train | D31: =INDEX(DemandAll,MATCH($D$4,DemandCodes,0),A31) -> 895 | E31: =$G$7*D31+(1-$G$7)*E30 -> 1031.1667 | F31: =NA() -> #N/A | G31: =NA() -> #N/A | H31: =NA() -> #N/A | I31: =AVERAGE(INDEX($D$15:$D$105,MAX(1,A31-4)):INDEX($D$15:$D$105,MIN(91,A31+4))) -> 974 | L31: =I31-$J$66 -> -82.403846 | M31: =NA() -> #N/A | N31: =NA() -> #N/A
A32: 18 | B32: =Demand!T$4 -> 40273 | C32: Train | D32: =INDEX(DemandAll,MATCH($D$4,DemandCodes,0),A32) -> 905 | E32: =$G$7*D32+(1-$G$7)*E31 -> 968.08333 | F32: =NA() -> #N/A | G32: =NA() -> #N/A | H32: =NA() -> #N/A | I32: =AVERAGE(INDEX($D$15:$D$105,MAX(1,A32-4)):INDEX($D$15:$D$105,MIN(91,A32+4))) -> 997.33333 | L32: =I32-$J$66 -> -59.070513 | M32: =NA() -> #N/A | N32: =NA() -> #N/A
A33: 19 | B33: =Demand!U$4 -> 40280 | C33: Train | D33: =INDEX(DemandAll,MATCH($D$4,DemandCodes,0),A33) -> 842 | E33: =$G$7*D33+(1-$G$7)*E32 -> 905.04166 | F33: =NA() -> #N/A | G33: =NA() -> #N/A | H33: =NA() -> #N/A | I33: =AVERAGE(INDEX($D$15:$D$105,MAX(1,A33-4)):INDEX($D$15:$D$105,MIN(91,A33+4))) -> 1027.5556 | L33: =I33-$J$66 -> -28.848291 | M33: =NA() -> #N/A | N33: =NA() -> #N/A
A34: 20 | B34: =Demand!V$4 -> 40287 | C34: Train | D34: =INDEX(DemandAll,MATCH($D$4,DemandCodes,0),A34) -> 688 | E34: =$G$7*D34+(1-$G$7)*E33 -> 796.52083 | F34: =NA() -> #N/A | G34: =NA() -> #N/A | H34: =NA() -> #N/A | I34: =AVERAGE(INDEX($D$15:$D$105,MAX(1,A34-4)):INDEX($D$15:$D$105,MIN(91,A34+4))) -> 1001.6667 | L34: =I34-$J$66 -> -54.737179 | M34: =NA() -> #N/A | N34: =NA() -> #N/A
A35: 21 | B35: =Demand!W$4 -> 40294 | C35: Train | D35: =INDEX(DemandAll,MATCH($D$4,DemandCodes,0),A35) -> 1107 | E35: =$G$7*D35+(1-$G$7)*E34 -> 951.76042 | F35: =NA() -> #N/A | G35: =NA() -> #N/A | H35: =NA() -> #N/A | I35: =AVERAGE(INDEX($D$15:$D$105,MAX(1,A35-4)):INDEX($D$15:$D$105,MIN(91,A35+4))) -> 976.66667 | L35: =I35-$J$66 -> -79.737179 | M35: =NA() -> #N/A | N35: =NA() -> #N/A
A36: 22 | B36: =Demand!X$4 -> 40301 | C36: Train | D36: =INDEX(DemandAll,MATCH($D$4,DemandCodes,0),A36) -> 1047 | E36: =$G$7*D36+(1-$G$7)*E35 -> 999.38021 | F36: =NA() -> #N/A | G36: =NA() -> #N/A | H36: =NA() -> #N/A | I36: =AVERAGE(INDEX($D$15:$D$105,MAX(1,A36-4)):INDEX($D$15:$D$105,MIN(91,A36+4))) -> 937.77778 | L36: =I36-$J$66 -> -118.62607 | M36: =NA() -> #N/A | N36: =NA() -> #N/A
A37: 23 | B37: =Demand!Y$4 -> 40308 | C37: Train | D37: =INDEX(DemandAll,MATCH($D$4,DemandCodes,0),A37) -> 1105 | E37: =$G$7*D37+(1-$G$7)*E36 -> 1052.1901 | F37: =NA() -> #N/A | G37: =NA() -> #N/A | H37: =NA() -> #N/A | I37: =AVERAGE(INDEX($D$15:$D$105,MAX(1,A37-4)):INDEX($D$15:$D$105,MIN(91,A37+4))) -> 1013.8889 | L37: =I37-$J$66 -> -42.514957 | M37: =NA() -> #N/A | N37: =NA() -> #N/A
A38: 24 | B38: =Demand!Z$4 -> 40315 | C38: Train | D38: =INDEX(DemandAll,MATCH($D$4,DemandCodes,0),A38) -> 1248 | E38: =$G$7*D38+(1-$G$7)*E37 -> 1150.0951 | F38: =NA() -> #N/A | G38: =NA() -> #N/A | H38: =NA() -> #N/A | I38: =AVERAGE(INDEX($D$15:$D$105,MAX(1,A38-4)):INDEX($D$15:$D$105,MIN(91,A38+4))) -> 984.88889 | L38: =I38-$J$66 -> -71.514957 | M38: =NA() -> #N/A | N38: =NA() -> #N/A
A39: 25 | B39: =Demand!AA$4 -> 40322 | C39: Train | D39: =INDEX(DemandAll,MATCH($D$4,DemandCodes,0),A39) -> 953 | E39: =$G$7*D39+(1-$G$7)*E38 -> 1051.5475 | F39: =NA() -> #N/A | G39: =NA() -> #N/A | H39: =NA() -> #N/A | I39: =AVERAGE(INDEX($D$15:$D$105,MAX(1,A39-4)):INDEX($D$15:$D$105,MIN(91,A39+4))) -> 995.55556 | L39: =I39-$J$66 -> -60.848291 | M39: =NA() -> #N/A | N39: =NA() -> #N/A
A40: 26 | B40: =Demand!AB$4 -> 40329 | C40: Train | D40: =INDEX(DemandAll,MATCH($D$4,DemandCodes,0),A40) -> 545 | E40: =$G$7*D40+(1-$G$7)*E39 -> 798.27376 | F40: =NA() -> #N/A | G40: =NA() -> #N/A | H40: =NA() -> #N/A | I40: =AVERAGE(INDEX($D$15:$D$105,MAX(1,A40-4)):INDEX($D$15:$D$105,MIN(91,A40+4))) -> 1006.3333 | L40: =I40-$J$66 -> -50.070513 | M40: =NA() -> #N/A | N40: =NA() -> #N/A
A41: 27 | B41: =Demand!AC$4 -> 40336 | C41: Train | D41: =INDEX(DemandAll,MATCH($D$4,DemandCodes,0),A41) -> 1590 | E41: =$G$7*D41+(1-$G$7)*E40 -> 1194.1369 | F41: =NA() -> #N/A | G41: =NA() -> #N/A | H41: =NA() -> #N/A | I41: =AVERAGE(INDEX($D$15:$D$105,MAX(1,A41-4)):INDEX($D$15:$D$105,MIN(91,A41+4))) -> 969 | L41: =I41-$J$66 -> -87.403846 | M41: =NA() -> #N/A | N41: =NA() -> #N/A
A42: 28 | B42: =Demand!AD$4 -> 40343 | C42: Train | D42: =INDEX(DemandAll,MATCH($D$4,DemandCodes,0),A42) -> 581 | E42: =$G$7*D42+(1-$G$7)*E41 -> 887.56844 | F42: =NA() -> #N/A | G42: =NA() -> #N/A | H42: =NA() -> #N/A | I42: =AVERAGE(INDEX($D$15:$D$105,MAX(1,A42-4)):INDEX($D$15:$D$105,MIN(91,A42+4))) -> 986.33333 | L42: =I42-$J$66 -> -70.070513 | M42: =NA() -> #N/A | N42: =NA() -> #N/A
A43: 29 | B43: =Demand!AE$4 -> 40350 | C43: Train | D43: =INDEX(DemandAll,MATCH($D$4,DemandCodes,0),A43) -> 784 | E43: =$G$7*D43+(1-$G$7)*E42 -> 835.78422 | F43: =NA() -> #N/A | G43: =NA() -> #N/A | H43: =NA() -> #N/A | I43: =AVERAGE(INDEX($D$15:$D$105,MAX(1,A43-4)):INDEX($D$15:$D$105,MIN(91,A43+4))) -> 972.55556 | L43: =I43-$J$66 -> -83.848291 | M43: =NA() -> #N/A | N43: =NA() -> #N/A
A44: 30 | B44: =Demand!AF$4 -> 40357 | C44: Train | D44: =INDEX(DemandAll,MATCH($D$4,DemandCodes,0),A44) -> 1204 | E44: =$G$7*D44+(1-$G$7)*E43 -> 1019.8921 | F44: =NA() -> #N/A | G44: =NA() -> #N/A | H44: =NA() -> #N/A | I44: =AVERAGE(INDEX($D$15:$D$105,MAX(1,A44-4)):INDEX($D$15:$D$105,MIN(91,A44+4))) -> 931.88889 | L44: =I44-$J$66 -> -124.51496 | M44: =NA() -> #N/A | N44: =NA() -> #N/A
A45: 31 | B45: =Demand!AG$4 -> 40364 | C45: Train | D45: =INDEX(DemandAll,MATCH($D$4,DemandCodes,0),A45) -> 711 | E45: =$G$7*D45+(1-$G$7)*E44 -> 865.44606 | F45: =NA() -> #N/A | G45: =NA() -> #N/A | H45: =NA() -> #N/A | I45: =AVERAGE(INDEX($D$15:$D$105,MAX(1,A45-4)):INDEX($D$15:$D$105,MIN(91,A45+4))) -> 931.55556 | L45: =I45-$J$66 -> -124.84829 | M45: =NA() -> #N/A | N45: =NA() -> #N/A
A46: 32 | B46: =Demand!AH$4 -> 40371 | C46: Train | D46: =INDEX(DemandAll,MATCH($D$4,DemandCodes,0),A46) -> 1261 | E46: =$G$7*D46+(1-$G$7)*E45 -> 1063.223 | F46: =NA() -> #N/A | G46: =NA() -> #N/A | H46: =NA() -> #N/A | I46: =AVERAGE(INDEX($D$15:$D$105,MAX(1,A46-4)):INDEX($D$15:$D$105,MIN(91,A46+4))) -> 890.77778 | L46: =I46-$J$66 -> -165.62607 | M46: =NA() -> #N/A | N46: =NA() -> #N/A
A47: 33 | B47: =Demand!AI$4 -> 40378 | C47: Train | D47: =INDEX(DemandAll,MATCH($D$4,DemandCodes,0),A47) -> 1124 | E47: =$G$7*D47+(1-$G$7)*E46 -> 1093.6115 | F47: =NA() -> #N/A | G47: =NA() -> #N/A | H47: =NA() -> #N/A | I47: =AVERAGE(INDEX($D$15:$D$105,MAX(1,A47-4)):INDEX($D$15:$D$105,MIN(91,A47+4))) -> 1013.4444 | L47: =I47-$J$66 -> -42.959402 | M47: =NA() -> #N/A | N47: =NA() -> #N/A
A48: 34 | B48: =Demand!AJ$4 -> 40385 | C48: Train | D48: =INDEX(DemandAll,MATCH($D$4,DemandCodes,0),A48) -> 587 | E48: =$G$7*D48+(1-$G$7)*E47 -> 840.30576 | F48: =NA() -> #N/A | G48: =NA() -> #N/A | H48: =NA() -> #N/A | I48: =AVERAGE(INDEX($D$15:$D$105,MAX(1,A48-4)):INDEX($D$15:$D$105,MIN(91,A48+4))) -> 1014.4444 | L48: =I48-$J$66 -> -41.959402 | M48: =NA() -> #N/A | N48: =NA() -> #N/A
A49: 35 | B49: =Demand!AK$4 -> 40392 | C49: Train | D49: =INDEX(DemandAll,MATCH($D$4,DemandCodes,0),A49) -> 542 | E49: =$G$7*D49+(1-$G$7)*E48 -> 691.15288 | F49: =NA() -> #N/A | G49: =NA() -> #N/A | H49: =NA() -> #N/A | I49: =AVERAGE(INDEX($D$15:$D$105,MAX(1,A49-4)):INDEX($D$15:$D$105,MIN(91,A49+4))) -> 978.11111 | L49: =I49-$J$66 -> -78.292735 | M49: =NA() -> #N/A | N49: =NA() -> #N/A
A50: 36 | B50: =Demand!AL$4 -> 40399 | C50: Train | D50: =INDEX(DemandAll,MATCH($D$4,DemandCodes,0),A50) -> 1223 | E50: =$G$7*D50+(1-$G$7)*E49 -> 957.07644 | F50: =NA() -> #N/A | G50: =NA() -> #N/A | H50: =NA() -> #N/A | I50: =AVERAGE(INDEX($D$15:$D$105,MAX(1,A50-4)):INDEX($D$15:$D$105,MIN(91,A50+4))) -> 1000.4444 | L50: =I50-$J$66 -> -55.959402 | M50: =NA() -> #N/A | N50: =NA() -> #N/A
A51: 37 | B51: =Demand!AM$4 -> 40406 | C51: Train | D51: =INDEX(DemandAll,MATCH($D$4,DemandCodes,0),A51) -> 1685 | E51: =$G$7*D51+(1-$G$7)*E50 -> 1321.0382 | F51: =NA() -> #N/A | G51: =NA() -> #N/A | H51: =NA() -> #N/A | I51: =AVERAGE(INDEX($D$15:$D$105,MAX(1,A51-4)):INDEX($D$15:$D$105,MIN(91,A51+4))) -> 975.66667 | L51: =I51-$J$66 -> -80.737179 | M51: =NA() -> #N/A | N51: =NA() -> #N/A
A52: 38 | B52: =Demand!AN$4 -> 40413 | C52: Train | D52: =INDEX(DemandAll,MATCH($D$4,DemandCodes,0),A52) -> 793 | E52: =$G$7*D52+(1-$G$7)*E51 -> 1057.0191 | F52: =NA() -> #N/A | G52: =NA() -> #N/A | H52: =NA() -> #N/A | I52: =AVERAGE(INDEX($D$15:$D$105,MAX(1,A52-4)):INDEX($D$15:$D$105,MIN(91,A52+4))) -> 971.66667 | L52: =I52-$J$66 -> -84.737179 | M52: =NA() -> #N/A | N52: =NA() -> #N/A
A53: 39 | B53: =Demand!AO$4 -> 40420 | C53: Train | D53: =INDEX(DemandAll,MATCH($D$4,DemandCodes,0),A53) -> 877 | E53: =$G$7*D53+(1-$G$7)*E52 -> 967.00955 | F53: =NA() -> #N/A | G53: =NA() -> #N/A | H53: =NA() -> #N/A | I53: =AVERAGE(INDEX($D$15:$D$105,MAX(1,A53-4)):INDEX($D$15:$D$105,MIN(91,A53+4))) -> 1007.6667 | L53: =I53-$J$66 -> -48.737179 | M53: =NA() -> #N/A | N53: =NA() -> #N/A
A54: 40 | B54: =Demand!AP$4 -> 40427 | C54: Train | D54: =INDEX(DemandAll,MATCH($D$4,DemandCodes,0),A54) -> 912 | E54: =$G$7*D54+(1-$G$7)*E53 -> 939.50478 | F54: =NA() -> #N/A | G54: =NA() -> #N/A | H54: =NA() -> #N/A | I54: =AVERAGE(INDEX($D$15:$D$105,MAX(1,A54-4)):INDEX($D$15:$D$105,MIN(91,A54+4))) -> 1057.8889 | L54: =I54-$J$66 -> 1.4850427 | M54: =NA() -> #N/A | N54: =NA() -> #N/A
A55: 41 | B55: =Demand!AQ$4 -> 40434 | C55: Train | D55: =INDEX(DemandAll,MATCH($D$4,DemandCodes,0),A55) -> 1038 | E55: =$G$7*D55+(1-$G$7)*E54 -> 988.75239 | F55: =NA() -> #N/A | G55: =NA() -> #N/A | H55: =NA() -> #N/A | I55: =AVERAGE(INDEX($D$15:$D$105,MAX(1,A55-4)):INDEX($D$15:$D$105,MIN(91,A55+4))) -> 1032.8889 | L55: =I55-$J$66 -> -23.514957 | M55: =NA() -> #N/A | N55: =NA() -> #N/A
A56: 42 | B56: =Demand!AR$4 -> 40441 | C56: Train | D56: =INDEX(DemandAll,MATCH($D$4,DemandCodes,0),A56) -> 1088 | E56: =$G$7*D56+(1-$G$7)*E55 -> 1038.3762 | F56: =NA() -> #N/A | G56: =NA() -> #N/A | H56: =NA() -> #N/A | I56: =AVERAGE(INDEX($D$15:$D$105,MAX(1,A56-4)):INDEX($D$15:$D$105,MIN(91,A56+4))) -> 934.33333 | L56: =I56-$J$66 -> -122.07051 | M56: =NA() -> #N/A | N56: =NA() -> #N/A
A57: 43 | B57: =Demand!AS$4 -> 40448 | C57: Train | D57: =INDEX(DemandAll,MATCH($D$4,DemandCodes,0),A57) -> 911 | E57: =$G$7*D57+(1-$G$7)*E56 -> 974.6881 | F57: =NA() -> #N/A | G57: =NA() -> #N/A | H57: =NA() -> #N/A | I57: =AVERAGE(INDEX($D$15:$D$105,MAX(1,A57-4)):INDEX($D$15:$D$105,MIN(91,A57+4))) -> 973.33333 | L57: =I57-$J$66 -> -83.070513 | M57: =NA() -> #N/A | N57: =NA() -> #N/A
A58: 44 | B58: =Demand!AT$4 -> 40455 | C58: Train | D58: =INDEX(DemandAll,MATCH($D$4,DemandCodes,0),A58) -> 994 | E58: =$G$7*D58+(1-$G$7)*E57 -> 984.34405 | F58: =NA() -> #N/A | G58: =NA() -> #N/A | H58: =NA() -> #N/A | I58: =AVERAGE(INDEX($D$15:$D$105,MAX(1,A58-4)):INDEX($D$15:$D$105,MIN(91,A58+4))) -> 1027.2222 | L58: =I58-$J$66 -> -29.181624 | M58: =NA() -> #N/A | N58: =NA() -> #N/A
A59: 45 | B59: =Demand!AU$4 -> 40462 | C59: Train | D59: =INDEX(DemandAll,MATCH($D$4,DemandCodes,0),A59) -> 998 | E59: =$G$7*D59+(1-$G$7)*E58 -> 991.17202 | F59: =NA() -> #N/A | G59: =NA() -> #N/A | H59: =NA() -> #N/A | I59: =AVERAGE(INDEX($D$15:$D$105,MAX(1,A59-4)):INDEX($D$15:$D$105,MIN(91,A59+4))) -> 1106.3333 | L59: =I59-$J$66 -> 49.929487 | M59: =NA() -> #N/A | N59: =NA() -> #N/A
A60: 46 | B60: =Demand!AV$4 -> 40469 | C60: Train | D60: =INDEX(DemandAll,MATCH($D$4,DemandCodes,0),A60) -> 798 | E60: =$G$7*D60+(1-$G$7)*E59 -> 894.58601 | F60: =NA() -> #N/A | G60: =NA() -> #N/A | H60: =NA() -> #N/A | I60: =AVERAGE(INDEX($D$15:$D$105,MAX(1,A60-4)):INDEX($D$15:$D$105,MIN(91,A60+4))) -> 1089.4444 | L60: =I60-$J$66 -> 33.040598 | M60: =NA() -> #N/A | N60: =NA() -> #N/A
A61: 47 | B61: =Demand!AW$4 -> 40476 | C61: Train | D61: =INDEX(DemandAll,MATCH($D$4,DemandCodes,0),A61) -> 1144 | E61: =$G$7*D61+(1-$G$7)*E60 -> 1019.293 | F61: =NA() -> #N/A | G61: =NA() -> #N/A | H61: =NA() -> #N/A | I61: =AVERAGE(INDEX($D$15:$D$105,MAX(1,A61-4)):INDEX($D$15:$D$105,MIN(91,A61+4))) -> 1191 | L61: =I61-$J$66 -> 134.59615 | M61: =NA() -> #N/A | N61: =NA() -> #N/A
A62: 48 | B62: =Demand!AX$4 -> 40483 | C62: Train | D62: =INDEX(DemandAll,MATCH($D$4,DemandCodes,0),A62) -> 1362 | E62: =$G$7*D62+(1-$G$7)*E61 -> 1190.6465 | F62: =NA() -> #N/A | G62: =NA() -> #N/A | H62: =NA() -> #N/A | I62: =AVERAGE(INDEX($D$15:$D$105,MAX(1,A62-4)):INDEX($D$15:$D$105,MIN(91,A62+4))) -> 1272.8889 | L62: =I62-$J$66 -> 216.48504 | M62: =NA() -> #N/A | N62: =NA() -> #N/A
A63: 49 | B63: =Demand!AY$4 -> 40490 | C63: Train | D63: =INDEX(DemandAll,MATCH($D$4,DemandCodes,0),A63) -> 1624 | E63: =$G$7*D63+(1-$G$7)*E62 -> 1407.3233 | F63: =NA() -> #N/A | G63: =NA() -> #N/A | H63: =NA() -> #N/A | I63: =AVERAGE(INDEX($D$15:$D$105,MAX(1,A63-4)):INDEX($D$15:$D$105,MIN(91,A63+4))) -> 1286.8889 | L63: =I63-$J$66 -> 230.48504 | M63: =NA() -> #N/A | N63: =NA() -> #N/A
A64: 50 | B64: =Demand!AZ$4 -> 40497 | C64: Train | D64: =INDEX(DemandAll,MATCH($D$4,DemandCodes,0),A64) -> 886 | E64: =$G$7*D64+(1-$G$7)*E63 -> 1146.6616 | F64: =NA() -> #N/A | G64: =NA() -> #N/A | H64: =NA() -> #N/A | I64: =AVERAGE(INDEX($D$15:$D$105,MAX(1,A64-4)):INDEX($D$15:$D$105,MIN(91,A64+4))) -> 1290.2222 | L64: =I64-$J$66 -> 233.81838 | M64: =NA() -> #N/A | N64: =NA() -> #N/A
A65: 51 | B65: =Demand!BA$4 -> 40504 | C65: Train | D65: =INDEX(DemandAll,MATCH($D$4,DemandCodes,0),A65) -> 2002 | E65: =$G$7*D65+(1-$G$7)*E64 -> 1574.3308 | F65: =NA() -> #N/A | G65: =NA() -> #N/A | H65: =NA() -> #N/A | I65: =AVERAGE(INDEX($D$15:$D$105,MAX(1,A65-4)):INDEX($D$15:$D$105,MIN(91,A65+4))) -> 1220.7778 | L65: =I65-$J$66 -> 164.37393 | M65: =NA() -> #N/A | N65: =NA() -> #N/A
A66: 52 | B66: =Demand!BB$4 -> 40511 | C66: Train | D66: =INDEX(DemandAll,MATCH($D$4,DemandCodes,0),A66) -> 1648 | E66: =$G$7*D66+(1-$G$7)*E65 -> 1611.1654 | F66: =NA() -> #N/A | G66: =NA() -> #N/A | H66: =NA() -> #N/A | I66: =AVERAGE(INDEX($D$15:$D$105,MAX(1,A66-4)):INDEX($D$15:$D$105,MIN(91,A66+4))) -> 1093.6667 | J66: =AVERAGE($D$15:$D$66) -> 1056.4038 | K66: 0 | L66: =I66-$J$66 -> 37.262821 | M66: =NA() -> #N/A | N66: =NA() -> #N/A
A67: 53 | B67: =Demand!BC$4 -> 40518 | C67: Train | D67: =INDEX(DemandAll,MATCH($D$4,DemandCodes,0),A67) -> 1120 | E67: =$G$7*D67+(1-$G$7)*E66 -> 1365.5827 | F67: =NA() -> #N/A | G67: =NA() -> #N/A | H67: =NA() -> #N/A | J67: =$G$8*(D67-L15)+(1-$G$8)*(J66+K66) -> 1049.2438 | K67: =$H$8*(J67-J66)+(1-$H$8)*K66 -> -0.358 | L67: =$I$8*(D67-J67)+(1-$I$8)*L15 -> 206.79615 | M67: =NA() -> #N/A | N67: =NA() -> #N/A
A68: 54 | B68: =Demand!BD$4 -> 40525 | C68: Train | D68: =INDEX(DemandAll,MATCH($D$4,DemandCodes,0),A68) -> 1028 | E68: =$G$7*D68+(1-$G$7)*E67 -> 1196.7914 | F68: =NA() -> #N/A | G68: =NA() -> #N/A | H68: =NA() -> #N/A | J68: =$G$8*(D68-L16)+(1-$G$8)*(J67+K67) -> 1040.3867 | K68: =$H$8*(J68-J67)+(1-$H$8)*K67 -> -0.782955 | L68: =$I$8*(D68-J68)+(1-$I$8)*L16 -> 149.09615 | M68: =NA() -> #N/A | N68: =NA() -> #N/A
A69: 55 | B69: =Demand!BE$4 -> 40532 | C69: Train | D69: =INDEX(DemandAll,MATCH($D$4,DemandCodes,0),A69) -> 173 | E69: =$G$7*D69+(1-$G$7)*E68 -> 684.89568 | F69: =NA() -> #N/A | G69: =NA() -> #N/A | H69: =NA() -> #N/A | J69: =$G$8*(D69-L17)+(1-$G$8)*(J68+K68) -> 987.39379 | K69: =$H$8*(J69-J68)+(1-$H$8)*K68 -> -3.3934549 | L69: =$I$8*(D69-J69)+(1-$I$8)*L17 -> 177.59615 | M69: =NA() -> #N/A | N69: =NA() -> #N/A
A70: 56 | B70: =Demand!BF$4 -> 40539 | C70: Train | D70: =INDEX(DemandAll,MATCH($D$4,DemandCodes,0),A70) -> 0 | E70: =$G$7*D70+(1-$G$7)*E69 -> 342.44784 | F70: =NA() -> #N/A | G70: =NA() -> #N/A | H70: =NA() -> #N/A | J70: =$G$8*(D70-L18)+(1-$G$8)*(J69+K69) -> 925.05176 | K70: =$H$8*(J70-J69)+(1-$H$8)*K69 -> -6.3408836 | L70: =$I$8*(D70-J70)+(1-$I$8)*L18 -> 194.97115 | M70: =NA() -> #N/A | N70: =NA() -> #N/A
A71: 57 | B71: =Demand!BG$4 -> 40546 | C71: Train | D71: =INDEX(DemandAll,MATCH($D$4,DemandCodes,0),A71) -> 971 | E71: =$G$7*D71+(1-$G$7)*E70 -> 656.72392 | F71: =NA() -> #N/A | G71: =NA() -> #N/A | H71: =NA() -> #N/A | J71: =$G$8*(D71-L19)+(1-$G$8)*(J70+K70) -> 914.49553 | K71: =$H$8*(J71-J70)+(1-$H$8)*K70 -> -6.5516512 | L71: =$I$8*(D71-J71)+(1-$I$8)*L19 -> 136.59615 | M71: =NA() -> #N/A | N71: =NA() -> #N/A
A72: 58 | B72: =Demand!BH$4 -> 40553 | C72: Train | D72: =INDEX(DemandAll,MATCH($D$4,DemandCodes,0),A72) -> 3327 | E72: =$G$7*D72+(1-$G$7)*E71 -> 1991.862 | F72: =NA() -> #N/A | G72: =NA() -> #N/A | H72: =NA() -> #N/A | J72: =$G$8*(D72-L20)+(1-$G$8)*(J71+K71) -> 1036.3002 | K72: =$H$8*(J72-J71)+(1-$H$8)*K71 -> -0.13383459 | L72: =$I$8*(D72-J72)+(1-$I$8)*L20 -> -148.07051 | M72: =NA() -> #N/A | N72: =NA() -> #N/A
A73: 59 | B73: =Demand!BI$4 -> 40560 | C73: Train | D73: =INDEX(DemandAll,MATCH($D$4,DemandCodes,0),A73) -> 655 | E73: =$G$7*D73+(1-$G$7)*E72 -> 1323.431 | F73: =NA() -> #N/A | G73: =NA() -> #N/A | H73: =NA() -> #N/A | J73: =$G$8*(D73-L21)+(1-$G$8)*(J72+K72) -> 1027.9505 | K73: =$H$8*(J73-J72)+(1-$H$8)*K72 -> -0.54462981 | L73: =$I$8*(D73-J73)+(1-$I$8)*L21 -> -216.84829 | M73: =NA() -> #N/A | N73: =NA() -> #N/A
A74: 60 | B74: =Demand!BJ$4 -> 40567 | C74: Train | D74: =INDEX(DemandAll,MATCH($D$4,DemandCodes,0),A74) -> 540 | E74: =$G$7*D74+(1-$G$7)*E73 -> 931.71549 | F74: =NA() -> #N/A | G74: =NA() -> #N/A | H74: =NA() -> #N/A | J74: =$G$8*(D74-L22)+(1-$G$8)*(J73+K73) -> 1009.4502 | K74: =$H$8*(J74-J73)+(1-$H$8)*K73 -> -1.4424126 | L74: =$I$8*(D74-J74)+(1-$I$8)*L22 -> -128.29274 | M74: =NA() -> #N/A | N74: =NA() -> #N/A
A75: 61 | B75: =Demand!BK$4 -> 40574 | C75: Train | D75: =INDEX(DemandAll,MATCH($D$4,DemandCodes,0),A75) -> 586 | E75: =$G$7*D75+(1-$G$7)*E74 -> 758.85774 | F75: =NA() -> #N/A | G75: =NA() -> #N/A | H75: =NA() -> #N/A | J75: =$G$8*(D75-L23)+(1-$G$8)*(J74+K74) -> 988.67202 | K75: =$H$8*(J75-J74)+(1-$H$8)*K74 -> -2.4092002 | L75: =$I$8*(D75-J75)+(1-$I$8)*L23 -> -35.292735 | M75: =NA() -> #N/A | N75: =NA() -> #N/A
A76: 62 | B76: =Demand!BL$4 -> 40581 | C76: Train | D76: =INDEX(DemandAll,MATCH($D$4,DemandCodes,0),A76) -> 516 | E76: =$G$7*D76+(1-$G$7)*E75 -> 637.42887 | F76: =NA() -> #N/A | G76: =NA() -> #N/A | H76: =NA() -> #N/A | J76: =$G$8*(D76-L24)+(1-$G$8)*(J75+K75) -> 969.70321 | K76: =$H$8*(J76-J75)+(1-$H$8)*K75 -> -3.2371809 | L76: =$I$8*(D76-J76)+(1-$I$8)*L24 -> -139.07051 | M76: =NA() -> #N/A | N76: =NA() -> #N/A
A77: 63 | B77: =Demand!BM$4 -> 40588 | C77: Train | D77: =INDEX(DemandAll,MATCH($D$4,DemandCodes,0),A77) -> 365 | E77: =$G$7*D77+(1-$G$7)*E76 -> 501.21444 | F77: =NA() -> #N/A | G77: =NA() -> #N/A | H77: =NA() -> #N/A | J77: =$G$8*(D77-L25)+(1-$G$8)*(J76+K76) -> 940.21292 | K77: =$H$8*(J77-J76)+(1-$H$8)*K76 -> -4.5498364 | L77: =$I$8*(D77-J77)+(1-$I$8)*L25 -> -76.403846 | M77: =NA() -> #N/A | N77: =NA() -> #N/A
A78: 64 | B78: =Demand!BN$4 -> 40595 | C78: Train | D78: =INDEX(DemandAll,MATCH($D$4,DemandCodes,0),A78) -> 401 | E78: =$G$7*D78+(1-$G$7)*E77 -> 451.10722 | F78: =NA() -> #N/A | G78: =NA() -> #N/A | H78: =NA() -> #N/A | J78: =$G$8*(D78-L26)+(1-$G$8)*(J77+K77) -> 914.01123 | K78: =$H$8*(J78-J77)+(1-$H$8)*K77 -> -5.6324289 | L78: =$I$8*(D78-J78)+(1-$I$8)*L26 -> -101.62607 | M78: =NA() -> #N/A | N78: =NA() -> #N/A
A79: 65 | B79: =Demand!BO$4 -> 40602 | C79: Train | D79: =INDEX(DemandAll,MATCH($D$4,DemandCodes,0),A79) -> 380 | E79: =$G$7*D79+(1-$G$7)*E78 -> 415.55361 | F79: =NA() -> #N/A | G79: =NA() -> #N/A | H79: =NA() -> #N/A | J79: =$G$8*(D79-L27)+(1-$G$8)*(J78+K78) -> 889.69672 | K79: =$H$8*(J79-J78)+(1-$H$8)*K78 -> -6.566533 | L79: =$I$8*(D79-J79)+(1-$I$8)*L27 -> -154.73718 | M79: =NA() -> #N/A | N79: =NA() -> #N/A
A80: 66 | B80: =Demand!BP$4 -> 40609 | C80: Train | D80: =INDEX(DemandAll,MATCH($D$4,DemandCodes,0),A80) -> 446 | E80: =$G$7*D80+(1-$G$7)*E79 -> 430.7768 | F80: =NA() -> #N/A | G80: =NA() -> #N/A | H80: =NA() -> #N/A | J80: =$G$8*(D80-L28)+(1-$G$8)*(J79+K79) -> 868.01609 | K80: =$H$8*(J80-J79)+(1-$H$8)*K79 -> -7.3222377 | L80: =$I$8*(D80-J80)+(1-$I$8)*L28 -> -134.84829 | M80: =NA() -> #N/A | N80: =NA() -> #N/A
A81: 67 | B81: =Demand!BQ$4 -> 40616 | C81: Train | D81: =INDEX(DemandAll,MATCH($D$4,DemandCodes,0),A81) -> 463 | E81: =$G$7*D81+(1-$G$7)*E80 -> 446.8884 | F81: =NA() -> #N/A | G81: =NA() -> #N/A | H81: =NA() -> #N/A | J81: =$G$8*(D81-L29)+(1-$G$8)*(J80+K80) -> 846.0738 | K81: =$H$8*(J81-J80)+(1-$H$8)*K80 -> -8.0532405 | L81: =$I$8*(D81-J81)+(1-$I$8)*L29 -> -105.29274 | M81: =NA() -> #N/A | N81: =NA() -> #N/A
A82: 68 | B82: =Demand!BR$4 -> 40623 | C82: Train | D82: =INDEX(DemandAll,MATCH($D$4,DemandCodes,0),A82) -> 365 | E82: =$G$7*D82+(1-$G$7)*E81 -> 405.9442 | F82: =NA() -> #N/A | G82: =NA() -> #N/A | H82: =NA() -> #N/A | J82: =$G$8*(D82-L30)+(1-$G$8)*(J81+K81) -> 819.5175 | K82: =$H$8*(J82-J81)+(1-$H$8)*K81 -> -8.9783934 | L82: =$I$8*(D82-J82)+(1-$I$8)*L30 -> -102.9594 | M82: =NA() -> #N/A | N82: =NA() -> #N/A
A83: 69 | B83: =Demand!BS$4 -> 40630 | C83: Train | D83: =INDEX(DemandAll,MATCH($D$4,DemandCodes,0),A83) -> 574 | E83: =$G$7*D83+(1-$G$7)*E82 -> 489.9721 | F83: =NA() -> #N/A | G83: =NA() -> #N/A | H83: =NA() -> #N/A | J83: =$G$8*(D83-L31)+(1-$G$8)*(J82+K82) -> 802.83234 | K83: =$H$8*(J83-J82)+(1-$H$8)*K82 -> -9.3637315 | L83: =$I$8*(D83-J83)+(1-$I$8)*L31 -> -82.403846 | M83: =NA() -> #N/A | N83: =NA() -> #N/A
A84: 70 | B84: =Demand!BT$4 -> 40637 | C84: Train | D84: =INDEX(DemandAll,MATCH($D$4,DemandCodes,0),A84) -> 368 | E84: =$G$7*D84+(1-$G$7)*E83 -> 428.98605 | F84: =NA() -> #N/A | G84: =NA() -> #N/A | H84: =NA() -> #N/A | J84: =$G$8*(D84-L32)+(1-$G$8)*(J83+K83) -> 775.14871 | K84: =$H$8*(J84-J83)+(1-$H$8)*K83 -> -10.279727 | L84: =$I$8*(D84-J84)+(1-$I$8)*L32 -> -59.070513 | M84: =NA() -> #N/A | N84: =NA() -> #N/A
A85: 71 | B85: =Demand!BU$4 -> 40644 | C85: Train | D85: =INDEX(DemandAll,MATCH($D$4,DemandCodes,0),A85) -> 474 | E85: =$G$7*D85+(1-$G$7)*E84 -> 451.49303 | F85: =NA() -> #N/A | G85: =NA() -> #N/A | H85: =NA() -> #N/A | J85: =$G$8*(D85-L33)+(1-$G$8)*(J84+K84) -> 751.76795 | K85: =$H$8*(J85-J84)+(1-$H$8)*K84 -> -10.934779 | L85: =$I$8*(D85-J85)+(1-$I$8)*L33 -> -28.848291 | M85: =NA() -> #N/A | N85: =NA() -> #N/A
A86: 72 | B86: =Demand!BV$4 -> 40651 | C86: Train | D86: =INDEX(DemandAll,MATCH($D$4,DemandCodes,0),A86) -> 492 | E86: =$G$7*D86+(1-$G$7)*E85 -> 471.74651 | F86: =NA() -> #N/A | G86: =NA() -> #N/A | H86: =NA() -> #N/A | J86: =$G$8*(D86-L34)+(1-$G$8)*(J85+K85) -> 731.12837 | K86: =$H$8*(J86-J85)+(1-$H$8)*K85 -> -11.420018 | L86: =$I$8*(D86-J86)+(1-$I$8)*L34 -> -54.737179 | M86: =NA() -> #N/A | N86: =NA() -> #N/A
A87: 73 | B87: =Demand!BW$4 -> 40658 | C87: Train | D87: =INDEX(DemandAll,MATCH($D$4,DemandCodes,0),A87) -> 375 | E87: =$G$7*D87+(1-$G$7)*E86 -> 423.37326 | F87: =NA() -> #N/A | G87: =NA() -> #N/A | H87: =NA() -> #N/A | J87: =$G$8*(D87-L35)+(1-$G$8)*(J86+K86) -> 706.45979 | K87: =$H$8*(J87-J86)+(1-$H$8)*K86 -> -12.082446 | L87: =$I$8*(D87-J87)+(1-$I$8)*L35 -> -79.737179 | M87: =NA() -> #N/A | N87: =NA() -> #N/A
A88: 74 | B88: =Demand!BX$4 -> 40665 | C88: Train | D88: =INDEX(DemandAll,MATCH($D$4,DemandCodes,0),A88) -> 1144 | E88: =$G$7*D88+(1-$G$7)*E87 -> 783.68663 | F88: =NA() -> #N/A | G88: =NA() -> #N/A | H88: =NA() -> #N/A | J88: =$G$8*(D88-L36)+(1-$G$8)*(J87+K87) -> 722.78978 | K88: =$H$8*(J88-J87)+(1-$H$8)*K87 -> -10.661825 | L88: =$I$8*(D88-J88)+(1-$I$8)*L36 -> -118.62607 | M88: =NA() -> #N/A | N88: =NA() -> #N/A
A89: 75 | B89: =Demand!BY$4 -> 40672 | C89: Train | D89: =INDEX(DemandAll,MATCH($D$4,DemandCodes,0),A89) -> 880 | E89: =$G$7*D89+(1-$G$7)*E88 -> 831.84331 | F89: =NA() -> #N/A | G89: =NA() -> #N/A | H89: =NA() -> #N/A | J89: =$G$8*(D89-L37)+(1-$G$8)*(J88+K88) -> 722.64731 | K89: =$H$8*(J89-J88)+(1-$H$8)*K88 -> -10.135857 | L89: =$I$8*(D89-J89)+(1-$I$8)*L37 -> -42.514957 | M89: =NA() -> #N/A | N89: =NA() -> #N/A
A90: 76 | B90: =Demand!BZ$4 -> 40679 | C90: Train | D90: =INDEX(DemandAll,MATCH($D$4,DemandCodes,0),A90) -> 794 | E90: =$G$7*D90+(1-$G$7)*E89 -> 812.92166 | F90: =NA() -> #N/A | G90: =NA() -> #N/A | H90: =NA() -> #N/A | J90: =$G$8*(D90-L38)+(1-$G$8)*(J89+K89) -> 720.16162 | K90: =$H$8*(J90-J89)+(1-$H$8)*K89 -> -9.7533483 | L90: =$I$8*(D90-J90)+(1-$I$8)*L38 -> -71.514957 | M90: =NA() -> #N/A | N90: =NA() -> #N/A
A91: 77 | B91: =Demand!CA$4 -> 40686 | C91: Train | D91: =INDEX(DemandAll,MATCH($D$4,DemandCodes,0),A91) -> 1023 | E91: =$G$7*D91+(1-$G$7)*E90 -> 917.96083 | F91: =NA() -> #N/A | G91: =NA() -> #N/A | H91: =NA() -> #N/A | J91: =$G$8*(D91-L39)+(1-$G$8)*(J90+K90) -> 729.08028 | K91: =$H$8*(J91-J90)+(1-$H$8)*K90 -> -8.8197483 | L91: =$I$8*(D91-J91)+(1-$I$8)*L39 -> -60.848291 | M91: =NA() -> #N/A | N91: =NA() -> #N/A
A92: 78 | B92: =Demand!CB$4 -> 40693 | C92: Train | D92: =INDEX(DemandAll,MATCH($D$4,DemandCodes,0),A92) -> 629 | E92: =$G$7*D92+(1-$G$7)*E91 -> 773.48041 | F92: =NA() -> #N/A | G92: =NA() -> #N/A | H92: =NA() -> #N/A | J92: =$G$8*(D92-L40)+(1-$G$8)*(J91+K91) -> 718.20103 | K92: =$H$8*(J92-J91)+(1-$H$8)*K91 -> -8.9227233 | L92: =$I$8*(D92-J92)+(1-$I$8)*L40 -> -50.070513 | M92: =NA() -> #N/A | N92: =NA() -> #N/A
A93: 79 | B93: =Demand!CC$4 -> 40700 | C93: Train | D93: =INDEX(DemandAll,MATCH($D$4,DemandCodes,0),A93) -> 372 | E93: =$G$7*D93+(1-$G$7)*E92 -> 572.74021 | F93: =NA() -> #N/A | G93: =NA() -> #N/A | H93: =NA() -> #N/A | J93: =$G$8*(D93-L41)+(1-$G$8)*(J92+K92) -> 696.78458 | K93: =$H$8*(J93-J92)+(1-$H$8)*K92 -> -9.5474095 | L93: =$I$8*(D93-J93)+(1-$I$8)*L41 -> -87.403846 | M93: =NA() -> #N/A | N93: =NA() -> #N/A
A94: 80 | B94: =Demand!CD$4 -> 40707 | C94: Train | D94: =INDEX(DemandAll,MATCH($D$4,DemandCodes,0),A94) -> 390 | E94: =$G$7*D94+(1-$G$7)*E93 -> 481.3701 | F94: =NA() -> #N/A | G94: =NA() -> #N/A | H94: =NA() -> #N/A | J94: =$G$8*(D94-L42)+(1-$G$8)*(J93+K93) -> 675.87884 | K94: =$H$8*(J94-J93)+(1-$H$8)*K93 -> -10.115326 | L94: =$I$8*(D94-J94)+(1-$I$8)*L42 -> -70.070513 | M94: =NA() -> #N/A | N94: =NA() -> #N/A
A95: 81 | B95: =Demand!CE$4 -> 40714 | C95: Train | D95: =INDEX(DemandAll,MATCH($D$4,DemandCodes,0),A95) -> 236 | E95: =$G$7*D95+(1-$G$7)*E94 -> 358.68505 | F95: =NA() -> #N/A | G95: =NA() -> #N/A | H95: =NA() -> #N/A | J95: =$G$8*(D95-L43)+(1-$G$8)*(J94+K94) -> 648.46775 | K95: =$H$8*(J95-J94)+(1-$H$8)*K94 -> -10.980114 | L95: =$I$8*(D95-J95)+(1-$I$8)*L43 -> -83.848291 | M95: =NA() -> #N/A | N95: =NA() -> #N/A
A96: 82 | B96: =Demand!CF$4 -> 40721 | C96: Train | D96: =INDEX(DemandAll,MATCH($D$4,DemandCodes,0),A96) -> 258 | E96: =$G$7*D96+(1-$G$7)*E95 -> 308.34253 | F96: =NA() -> #N/A | G96: =NA() -> #N/A | H96: =NA() -> #N/A | J96: =$G$8*(D96-L44)+(1-$G$8)*(J95+K95) -> 624.739 | K96: =$H$8*(J96-J95)+(1-$H$8)*K95 -> -11.617546 | L96: =$I$8*(D96-J96)+(1-$I$8)*L44 -> -124.51496 | M96: =NA() -> #N/A | N96: =NA() -> #N/A
A97: 83 | B97: =Demand!CG$4 -> 40728 | C97: Train | D97: =INDEX(DemandAll,MATCH($D$4,DemandCodes,0),A97) -> 263 | E97: =$G$7*D97+(1-$G$7)*E96 -> 285.67126 | F97: =NA() -> #N/A | G97: =NA() -> #N/A | H97: =NA() -> #N/A | J97: =$G$8*(D97-L45)+(1-$G$8)*(J96+K96) -> 601.8578 | K97: =$H$8*(J97-J96)+(1-$H$8)*K96 -> -12.180729 | L97: =$I$8*(D97-J97)+(1-$I$8)*L45 -> -124.84829 | M97: =NA() -> #N/A | N97: =NA() -> #N/A
A98: 84 | B98: =Demand!CH$4 -> 40735 | C98: Train | D98: =INDEX(DemandAll,MATCH($D$4,DemandCodes,0),A98) -> 1198 | E98: =$G$7*D98+(1-$G$7)*E97 -> 741.83563 | F98: =NA() -> #N/A | G98: =NA() -> #N/A | H98: =NA() -> #N/A | J98: =$G$8*(D98-L46)+(1-$G$8)*(J97+K97) -> 628.37452 | K98: =$H$8*(J98-J97)+(1-$H$8)*K97 -> -10.245856 | L98: =$I$8*(D98-J98)+(1-$I$8)*L46 -> -165.62607 | M98: =NA() -> #N/A | N98: =NA() -> #N/A
A99: 85 | B99: =Demand!CI$4 -> 40742 | C99: Train | D99: =INDEX(DemandAll,MATCH($D$4,DemandCodes,0),A99) -> 720 | E99: =$G$7*D99+(1-$G$7)*E98 -> 730.91782 | F99: =NA() -> #N/A | G99: =NA() -> #N/A | H99: =NA() -> #N/A | J99: =$G$8*(D99-L47)+(1-$G$8)*(J98+K98) -> 625.3702 | K99: =$H$8*(J99-J98)+(1-$H$8)*K98 -> -9.8837794 | L99: =$I$8*(D99-J99)+(1-$I$8)*L47 -> -42.959402 | M99: =NA() -> #N/A | N99: =NA() -> #N/A
A100: 86 | B100: =Demand!CJ$4 -> 40749 | C100: Train | D100: =INDEX(DemandAll,MATCH($D$4,DemandCodes,0),A100) -> 780 | E100: =$G$7*D100+(1-$G$7)*E99 -> 755.45891 | F100: =NA() -> #N/A | G100: =NA() -> #N/A | H100: =NA() -> #N/A | J100: =$G$8*(D100-L48)+(1-$G$8)*(J99+K99) -> 625.81007 | K100: =$H$8*(J100-J99)+(1-$H$8)*K99 -> -9.367597 | L100: =$I$8*(D100-J100)+(1-$I$8)*L48 -> -41.959402 | M100: =NA() -> #N/A | N100: =NA() -> #N/A
A101: 87 | B101: =Demand!CK$4 -> 40756 | C101: Train | D101: =INDEX(DemandAll,MATCH($D$4,DemandCodes,0),A101) -> 438 | E101: =$G$7*D101+(1-$G$7)*E100 -> 596.72945 | F101: =NA() -> #N/A | G101: =NA() -> #N/A | H101: =NA() -> #N/A | J101: =$G$8*(D101-L49)+(1-$G$8)*(J100+K100) -> 611.43499 | K101: =$H$8*(J101-J100)+(1-$H$8)*K100 -> -9.6179713 | L101: =$I$8*(D101-J101)+(1-$I$8)*L49 -> -78.292735 | M101: =NA() -> #N/A | N101: =NA() -> #N/A
A102: 88 | B102: =Demand!CL$4 -> 40763 | C102: Train | D102: =INDEX(DemandAll,MATCH($D$4,DemandCodes,0),A102) -> 470 | E102: =$G$7*D102+(1-$G$7)*E101 -> 533.36473 | F102: =NA() -> #N/A | G102: =NA() -> #N/A | H102: =NA() -> #N/A | J102: =$G$8*(D102-L50)+(1-$G$8)*(J101+K101) -> 598.02413 | K102: =$H$8*(J102-J101)+(1-$H$8)*K101 -> -9.8076154 | L102: =$I$8*(D102-J102)+(1-$I$8)*L50 -> -55.959402 | M102: =NA() -> #N/A | N102: =NA() -> #N/A
...

Sheet Backtest
A1: Backtest: which forecast method works best for each class?
A2: Columns A-F: errors of each method per SKU over the 12 test weeks (from notebook 02). Columns I onward: SUMIFS by class, score = WAPE + |bias|, lowest wins.
H3: WAPE = Σ|error| / Σactual Bias = Σerror / Σactual (negative = forecast too low) Score = WAPE + |bias|
A4: Stock code | B4: Method | C4: Actual units (12 wks) | D4: Sum |error| | E4: Sum error | F4: Class | H4: Class | I4: SKUs | J4: WAPE Naive | K4: WAPE Moving average | L4: WAPE SES | M4: WAPE Holt-Winters | N4: Bias Naive | O4: Bias Moving average | P4: Bias SES | Q4: Bias Holt-Winters | R4: Score Naive | S4: Score Moving average | T4: Score SES | U4: Score Holt-Winters | V4: Best method | W4: Best non-seasonal method
A5: 22423 | B5: Naive | C5: 2481 | D5: 859 | E5: -825 | F5: =_xlfn.XLOOKUP(A5,ClsCode,ClsClass) -> AX | H5: AX | I5: =COUNTIFS(ClsClass,H5) -> 36 | J5: =IFERROR(SUMIFS(BtAbsErr,BtClass,$H5,BtMethod,"Naive")/SUMIFS(BtActual,BtClass,$H5,BtMethod,"Naive"),"") -> 0.49754178 | K5: =IFERROR(SUMIFS(BtAbsErr,BtClass,$H5,BtMethod,"Moving average")/SUMIFS(BtActual,BtClass,$H5,BtMethod,"Moving average"),"") -> 0.45871182 | L5: =IFERROR(SUMIFS(BtAbsErr,BtClass,$H5,BtMethod,"SES")/SUMIFS(BtActual,BtClass,$H5,BtMethod,"SES"),"") -> 0.45932501 | M5: =IFERROR(SUMIFS(BtAbsErr,BtClass,$H5,BtMethod,"Holt-Winters")/SUMIFS(BtActual,BtClass,$H5,BtMethod,"Holt-Winters"),"") -> 0.48445942 | N5: =IFERROR(SUMIFS(BtErr,BtClass,$H5,BtMethod,"Naive")/SUMIFS(BtActual,BtClass,$H5,BtMethod,"Naive"),"") -> -0.26713219 | O5: =IFERROR(SUMIFS(BtErr,BtClass,$H5,BtMethod,"Moving average")/SUMIFS(BtActual,BtClass,$H5,BtMethod,"Moving average"),"") -> 0.012562316 | P5: =IFERROR(SUMIFS(BtErr,BtClass,$H5,BtMethod,"SES")/SUMIFS(BtActual,BtClass,$H5,BtMethod,"SES"),"") -> -0.014556892 | Q5: =IFERROR(SUMIFS(BtErr,BtClass,$H5,BtMethod,"Holt-Winters")/SUMIFS(BtActual,BtClass,$H5,BtMethod,"Holt-Winters"),"") -> 0.12996244 | R5: =IFERROR(J5+ABS(N5),"") -> 0.76467397 | S5: =IFERROR(K5+ABS(O5),"") -> 0.47127414 | T5: =IFERROR(L5+ABS(P5),"") -> 0.4738819 | U5: =IFERROR(M5+ABS(Q5),"") -> 0.61442186 | V5: =IF(I5=0,"",SUBSTITUTE(INDEX($R$4:$U$4,MATCH(MIN(R5:U5),R5:U5,0)),"Score ","")) -> Moving average | W5: =IF(I5=0,"",SUBSTITUTE(INDEX($R$4:$T$4,MATCH(MIN(R5:T5),R5:T5,0)),"Score ","")) -> Moving average
A6: 22423 | B6: Moving average | C6: 2481 | D6: 649 | E6: 90 | F6: =_xlfn.XLOOKUP(A6,ClsCode,ClsClass) -> AX | H6: AY | I6: =COUNTIFS(ClsClass,H6) -> 31 | J6: =IFERROR(SUMIFS(BtAbsErr,BtClass,$H6,BtMethod,"Naive")/SUMIFS(BtActual,BtClass,$H6,BtMethod,"Naive"),"") -> 0.73967575 | K6: =IFERROR(SUMIFS(BtAbsErr,BtClass,$H6,BtMethod,"Moving average")/SUMIFS(BtActual,BtClass,$H6,BtMethod,"Moving average"),"") -> 0.60536535 | L6: =IFERROR(SUMIFS(BtAbsErr,BtClass,$H6,BtMethod,"SES")/SUMIFS(BtActual,BtClass,$H6,BtMethod,"SES"),"") -> 0.59849615 | M6: =IFERROR(SUMIFS(BtAbsErr,BtClass,$H6,BtMethod,"Holt-Winters")/SUMIFS(BtActual,BtClass,$H6,BtMethod,"Holt-Winters"),"") -> 0.64247972 | N6: =IFERROR(SUMIFS(BtErr,BtClass,$H6,BtMethod,"Naive")/SUMIFS(BtActual,BtClass,$H6,BtMethod,"Naive"),"") -> -0.39971182 | O6: =IFERROR(SUMIFS(BtErr,BtClass,$H6,BtMethod,"Moving average")/SUMIFS(BtActual,BtClass,$H6,BtMethod,"Moving average"),"") -> -0.25492764 | P6: =IFERROR(SUMIFS(BtErr,BtClass,$H6,BtMethod,"SES")/SUMIFS(BtActual,BtClass,$H6,BtMethod,"SES"),"") -> -0.29816271 | Q6: =IFERROR(SUMIFS(BtErr,BtClass,$H6,BtMethod,"Holt-Winters")/SUMIFS(BtActual,BtClass,$H6,BtMethod,"Holt-Winters"),"") -> 0.068553895 | R6: =IFERROR(J6+ABS(N6),"") -> 1.1393876 | S6: =IFERROR(K6+ABS(O6),"") -> 0.86029298 | T6: =IFERROR(L6+ABS(P6),"") -> 0.89665886 | U6: =IFERROR(M6+ABS(Q6),"") -> 0.71103361 | V6: =IF(I6=0,"",SUBSTITUTE(INDEX($R$4:$U$4,MATCH(MIN(R6:U6),R6:U6,0)),"Score ","")) -> Holt-Winters | W6: =IF(I6=0,"",SUBSTITUTE(INDEX($R$4:$T$4,MATCH(MIN(R6:T6),R6:T6,0)),"Score ","")) -> Moving average
A7: 22423 | B7: SES | C7: 2481 | D7: 751.1932 | E7: -591.5796 | F7: =_xlfn.XLOOKUP(A7,ClsCode,ClsClass) -> AX | H7: AZ | I7: =COUNTIFS(ClsClass,H7) -> 28 | J7: =IFERROR(SUMIFS(BtAbsErr,BtClass,$H7,BtMethod,"Naive")/SUMIFS(BtActual,BtClass,$H7,BtMethod,"Naive"),"") -> 1.0387239 | K7: =IFERROR(SUMIFS(BtAbsErr,BtClass,$H7,BtMethod,"Moving average")/SUMIFS(BtActual,BtClass,$H7,BtMethod,"Moving average"),"") -> 0.80109351 | L7: =IFERROR(SUMIFS(BtAbsErr,BtClass,$H7,BtMethod,"SES")/SUMIFS(BtActual,BtClass,$H7,BtMethod,"SES"),"") -> 0.79159603 | M7: =IFERROR(SUMIFS(BtAbsErr,BtClass,$H7,BtMethod,"Holt-Winters")/SUMIFS(BtActual,BtClass,$H7,BtMethod,"Holt-Winters"),"") -> 0.76705251 | N7: =IFERROR(SUMIFS(BtErr,BtClass,$H7,BtMethod,"Naive")/SUMIFS(BtActual,BtClass,$H7,BtMethod,"Naive"),"") -> -0.23390657 | O7: =IFERROR(SUMIFS(BtErr,BtClass,$H7,BtMethod,"Moving average")/SUMIFS(BtActual,BtClass,$H7,BtMethod,"Moving average"),"") -> -0.62190115 | P7: =IFERROR(SUMIFS(BtErr,BtClass,$H7,BtMethod,"SES")/SUMIFS(BtActual,BtClass,$H7,BtMethod,"SES"),"") -> -0.51089672 | Q7: =IFERROR(SUMIFS(BtErr,BtClass,$H7,BtMethod,"Holt-Winters")/SUMIFS(BtActual,BtClass,$H7,BtMethod,"Holt-Winters"),"") -> 0.14717217 | R7: =IFERROR(J7+ABS(N7),"") -> 1.2726304 | S7: =IFERROR(K7+ABS(O7),"") -> 1.4229947 | T7: =IFERROR(L7+ABS(P7),"") -> 1.3024928 | U7: =IFERROR(M7+ABS(Q7),"") -> 0.91422468 | V7: =IF(I7=0,"",SUBSTITUTE(INDEX($R$4:$U$4,MATCH(MIN(R7:U7),R7:U7,0)),"Score ","")) -> Holt-Winters | W7: =IF(I7=0,"",SUBSTITUTE(INDEX($R$4:$T$4,MATCH(MIN(R7:T7),R7:T7,0)),"Score ","")) -> Naive
A8: 22423 | B8: Holt-Winters | C8: 2481 | D8: 1258.1304 | E8: 904.029 | F8: =_xlfn.XLOOKUP(A8,ClsCode,ClsClass) -> AX | H8: BX | I8: =COUNTIFS(ClsClass,H8) -> 10 | J8: =IFERROR(SUMIFS(BtAbsErr,BtClass,$H8,BtMethod,"Naive")/SUMIFS(BtActual,BtClass,$H8,BtMethod,"Naive"),"") -> 0.43072585 | K8: =IFERROR(SUMIFS(BtAbsErr,BtClass,$H8,BtMethod,"Moving average")/SUMIFS(BtActual,BtClass,$H8,BtMethod,"Moving average"),"") -> 0.4546751 | L8: =IFERROR(SUMIFS(BtAbsErr,BtClass,$H8,BtMethod,"SES")/SUMIFS(BtActual,BtClass,$H8,BtMethod,"SES"),"") -> 0.4345453 | M8: =IFERROR(SUMIFS(BtAbsErr,BtClass,$H8,BtMethod,"Holt-Winters")/SUMIFS(BtActual,BtClass,$H8,BtMethod,"Holt-Winters"),"") -> 0.43499425 | N8: =IFERROR(SUMIFS(BtErr,BtClass,$H8,BtMethod,"Naive")/SUMIFS(BtActual,BtClass,$H8,BtMethod,"Naive"),"") -> -0.15494066 | O8: =IFERROR(SUMIFS(BtErr,BtClass,$H8,BtMethod,"Moving average")/SUMIFS(BtActual,BtClass,$H8,BtMethod,"Moving average"),"") -> -0.15189168 | P8: =IFERROR(SUMIFS(BtErr,BtClass,$H8,BtMethod,"SES")/SUMIFS(BtActual,BtClass,$H8,BtMethod,"SES"),"") -> -0.13703823 | Q8: =IFERROR(SUMIFS(BtErr,BtClass,$H8,BtMethod,"Holt-Winters")/SUMIFS(BtActual,BtClass,$H8,BtMethod,"Holt-Winters"),"") -> -0.18099286 | R8: =IFERROR(J8+ABS(N8),"") -> 0.58566651 | S8: =IFERROR(K8+ABS(O8),"") -> 0.60656678 | T8: =IFERROR(L8+ABS(P8),"") -> 0.57158353 | U8: =IFERROR(M8+ABS(Q8),"") -> 0.61598711 | V8: =IF(I8=0,"",SUBSTITUTE(INDEX($R$4:$U$4,MATCH(MIN(R8:U8),R8:U8,0)),"Score ","")) -> SES | W8: =IF(I8=0,"",SUBSTITUTE(INDEX($R$4:$T$4,MATCH(MIN(R8:T8),R8:T8,0)),"Score ","")) -> SES
A9: 85123A | B9: Naive | C9: 8260 | D9: 4366 | E9: -3604 | F9: =_xlfn.XLOOKUP(A9,ClsCode,ClsClass) -> AY | H9: BY | I9: =COUNTIFS(ClsClass,H9) -> 17 | J9: =IFERROR(SUMIFS(BtAbsErr,BtClass,$H9,BtMethod,"Naive")/SUMIFS(BtActual,BtClass,$H9,BtMethod,"Naive"),"") -> 0.68577483 | K9: =IFERROR(SUMIFS(BtAbsErr,BtClass,$H9,BtMethod,"Moving average")/SUMIFS(BtActual,BtClass,$H9,BtMethod,"Moving average"),"") -> 0.59964238 | L9: =IFERROR(SUMIFS(BtAbsErr,BtClass,$H9,BtMethod,"SES")/SUMIFS(BtActual,BtClass,$H9,BtMethod,"SES"),"") -> 0.54538219 | M9: =IFERROR(SUMIFS(BtAbsErr,BtClass,$H9,BtMethod,"Holt-Winters")/SUMIFS(BtActual,BtClass,$H9,BtMethod,"Holt-Winters"),"") -> 0.59039746 | N9: =IFERROR(SUMIFS(BtErr,BtClass,$H9,BtMethod,"Naive")/SUMIFS(BtActual,BtClass,$H9,BtMethod,"Naive"),"") -> -0.568 | O9: =IFERROR(SUMIFS(BtErr,BtClass,$H9,BtMethod,"Moving average")/SUMIFS(BtActual,BtClass,$H9,BtMethod,"Moving average"),"") -> -0.28150993 | P9: =IFERROR(SUMIFS(BtErr,BtClass,$H9,BtMethod,"SES")/SUMIFS(BtActual,BtClass,$H9,BtMethod,"SES"),"") -> -0.20274934 | Q9: =IFERROR(SUMIFS(BtErr,BtClass,$H9,BtMethod,"Holt-Winters")/SUMIFS(BtActual,BtClass,$H9,BtMethod,"Holt-Winters"),"") -> 0.071104209 | R9: =IFERROR(J9+ABS(N9),"") -> 1.2537748 | S9: =IFERROR(K9+ABS(O9),"") -> 0.88115232 | T9: =IFERROR(L9+ABS(P9),"") -> 0.74813153 | U9: =IFERROR(M9+ABS(Q9),"") -> 0.66150167 | V9: =IF(I9=0,"",SUBSTITUTE(INDEX($R$4:$U$4,MATCH(MIN(R9:U9),R9:U9,0)),"Score ","")) -> Holt-Winters | W9: =IF(I9=0,"",SUBSTITUTE(INDEX($R$4:$T$4,MATCH(MIN(R9:T9),R9:T9,0)),"Score ","")) -> SES
A10: 85123A | B10: Moving average | C10: 8260 | D10: 3682 | E10: -662.5 | F10: =_xlfn.XLOOKUP(A10,ClsCode,ClsClass) -> AY | H10: BZ | I10: =COUNTIFS(ClsClass,H10) -> 12 | J10: =IFERROR(SUMIFS(BtAbsErr,BtClass,$H10,BtMethod,"Naive")/SUMIFS(BtActual,BtClass,$H10,BtMethod,"Naive"),"") -> 1.1168692 | K10: =IFERROR(SUMIFS(BtAbsErr,BtClass,$H10,BtMethod,"Moving average")/SUMIFS(BtActual,BtClass,$H10,BtMethod,"Moving average"),"") -> 0.94767597 | L10: =IFERROR(SUMIFS(BtAbsErr,BtClass,$H10,BtMethod,"SES")/SUMIFS(BtActual,BtClass,$H10,BtMethod,"SES"),"") -> 0.93363083 | M10: =IFERROR(SUMIFS(BtAbsErr,BtClass,$H10,BtMethod,"Holt-Winters")/SUMIFS(BtActual,BtClass,$H10,BtMethod,"Holt-Winters"),"") -> 1.0760677 | N10: =IFERROR(SUMIFS(BtErr,BtClass,$H10,BtMethod,"Naive")/SUMIFS(BtActual,BtClass,$H10,BtMethod,"Naive"),"") -> -0.61773741 | O10: =IFERROR(SUMIFS(BtErr,BtClass,$H10,BtMethod,"Moving average")/SUMIFS(BtActual,BtClass,$H10,BtMethod,"Moving average"),"") -> -0.49833044 | P10: =IFERROR(SUMIFS(BtErr,BtClass,$H10,BtMethod,"SES")/SUMIFS(BtActual,BtClass,$H10,BtMethod,"SES"),"") -> -0.50268639 | Q10: =IFERROR(SUMIFS(BtErr,BtClass,$H10,BtMethod,"Holt-Winters")/SUMIFS(BtActual,BtClass,$H10,BtMethod,"Holt-Winters"),"") -> 0.00090534259 | R10: =IFERROR(J10+ABS(N10),"") -> 1.7346067 | S10: =IFERROR(K10+ABS(O10),"") -> 1.4460064 | T10: =IFERROR(L10+ABS(P10),"") -> 1.4363172 | U10: =IFERROR(M10+ABS(Q10),"") -> 1.076973 | V10: =IF(I10=0,"",SUBSTITUTE(INDEX($R$4:$U$4,MATCH(MIN(R10:U10),R10:U10,0)),"Score ","")) -> Holt-Winters | W10: =IF(I10=0,"",SUBSTITUTE(INDEX($R$4:$T$4,MATCH(MIN(R10:T10),R10:T10,0)),"Score ","")) -> SES
A11: 85123A | B11: SES | C11: 8260 | D11: 3887.1588 | E11: -2362.9528 | F11: =_xlfn.XLOOKUP(A11,ClsCode,ClsClass) -> AY | H11: CX | I11: =COUNTIFS(ClsClass,H11) -> 5 | J11: =IFERROR(SUMIFS(BtAbsErr,BtClass,$H11,BtMethod,"Naive")/SUMIFS(BtActual,BtClass,$H11,BtMethod,"Naive"),"") -> 0.56604185 | K11: =IFERROR(SUMIFS(BtAbsErr,BtClass,$H11,BtMethod,"Moving average")/SUMIFS(BtActual,BtClass,$H11,BtMethod,"Moving average"),"") -> 0.56097428 | L11: =IFERROR(SUMIFS(BtAbsErr,BtClass,$H11,BtMethod,"SES")/SUMIFS(BtActual,BtClass,$H11,BtMethod,"SES"),"") -> 0.54676216 | M11: =IFERROR(SUMIFS(BtAbsErr,BtClass,$H11,BtMethod,"Holt-Winters")/SUMIFS(BtActual,BtClass,$H11,BtMethod,"Holt-Winters"),"") -> 0.61682937 | N11: =IFERROR(SUMIFS(BtErr,BtClass,$H11,BtMethod,"Naive")/SUMIFS(BtActual,BtClass,$H11,BtMethod,"Naive"),"") -> -0.27942459 | O11: =IFERROR(SUMIFS(BtErr,BtClass,$H11,BtMethod,"Moving average")/SUMIFS(BtActual,BtClass,$H11,BtMethod,"Moving average"),"") -> 0.11748038 | P11: =IFERROR(SUMIFS(BtErr,BtClass,$H11,BtMethod,"SES")/SUMIFS(BtActual,BtClass,$H11,BtMethod,"SES"),"") -> 0.088597733 | Q11: =IFERROR(SUMIFS(BtErr,BtClass,$H11,BtMethod,"Holt-Winters")/SUMIFS(BtActual,BtClass,$H11,BtMethod,"Holt-Winters"),"") -> -0.44362194 | R11: =IFERROR(J11+ABS(N11),"") -> 0.84546643 | S11: =IFERROR(K11+ABS(O11),"") -> 0.67845466 | T11: =IFERROR(L11+ABS(P11),"") -> 0.6353599 | U11: =IFERROR(M11+ABS(Q11),"") -> 1.0604513 | V11: =IF(I11=0,"",SUBSTITUTE(INDEX($R$4:$U$4,MATCH(MIN(R11:U11),R11:U11,0)),"Score ","")) -> SES | W11: =IF(I11=0,"",SUBSTITUTE(INDEX($R$4:$T$4,MATCH(MIN(R11:T11),R11:T11,0)),"Score ","")) -> SES
A12: 85123A | B12: Holt-Winters | C12: 8260 | D12: 3529.8869 | E12: -1442.7521 | F12: =_xlfn.XLOOKUP(A12,ClsCode,ClsClass) -> AY | H12: CY | I12: =COUNTIFS(ClsClass,H12) -> 7 | J12: =IFERROR(SUMIFS(BtAbsErr,BtClass,$H12,BtMethod,"Naive")/SUMIFS(BtActual,BtClass,$H12,BtMethod,"Naive"),"") -> 0.70045234 | K12: =IFERROR(SUMIFS(BtAbsErr,BtClass,$H12,BtMethod,"Moving average")/SUMIFS(BtActual,BtClass,$H12,BtMethod,"Moving average"),"") -> 0.74401072 | L12: =IFERROR(SUMIFS(BtAbsErr,BtClass,$H12,BtMethod,"SES")/SUMIFS(BtActual,BtClass,$H12,BtMethod,"SES"),"") -> 0.70810035 | M12: =IFERROR(SUMIFS(BtAbsErr,BtClass,$H12,BtMethod,"Holt-Winters")/SUMIFS(BtActual,BtClass,$H12,BtMethod,"Holt-Winters"),"") -> 0.92831143 | N12: =IFERROR(SUMIFS(BtErr,BtClass,$H12,BtMethod,"Naive")/SUMIFS(BtActual,BtClass,$H12,BtMethod,"Naive"),"") -> -0.12950243 | O12: =IFERROR(SUMIFS(BtErr,BtClass,$H12,BtMethod,"Moving average")/SUMIFS(BtActual,BtClass,$H12,BtMethod,"Moving average"),"") -> -0.047830457 | P12: =IFERROR(SUMIFS(BtErr,BtClass,$H12,BtMethod,"SES")/SUMIFS(BtActual,BtClass,$H12,BtMethod,"SES"),"") -> -0.076494153 | Q12: =IFERROR(SUMIFS(BtErr,BtClass,$H12,BtMethod,"Holt-Winters")/SUMIFS(BtActual,BtClass,$H12,BtMethod,"Holt-Winters"),"") -> 0.46569461 | R12: =IFERROR(J12+ABS(N12),"") -> 0.82995477 | S12: =IFERROR(K12+ABS(O12),"") -> 0.79184118 | T12: =IFERROR(L12+ABS(P12),"") -> 0.7845945 | U12: =IFERROR(M12+ABS(Q12),"") -> 1.394006 | V12: =IF(I12=0,"",SUBSTITUTE(INDEX($R$4:$U$4,MATCH(MIN(R12:U12),R12:U12,0)),"Score ","")) -> SES | W12: =IF(I12=0,"",SUBSTITUTE(INDEX($R$4:$T$4,MATCH(MIN(R12:T12),R12:T12,0)),"Score ","")) -> SES
A13: 47566 | B13: Naive | C13: 2356 | D13: 1054 | E13: 116 | F13: =_xlfn.XLOOKUP(A13,ClsCode,ClsClass) -> AX | H13: CZ | I13: =COUNTIFS(ClsClass,H13) -> 4 | J13: =IFERROR(SUMIFS(BtAbsErr,BtClass,$H13,BtMethod,"Naive")/SUMIFS(BtActual,BtClass,$H13,BtMethod,"Naive"),"") -> 0.88807163 | K13: =IFERROR(SUMIFS(BtAbsErr,BtClass,$H13,BtMethod,"Moving average")/SUMIFS(BtActual,BtClass,$H13,BtMethod,"Moving average"),"") -> 0.74416374 | L13: =IFERROR(SUMIFS(BtAbsErr,BtClass,$H13,BtMethod,"SES")/SUMIFS(BtActual,BtClass,$H13,BtMethod,"SES"),"") -> 0.81386274 | M13: =IFERROR(SUMIFS(BtAbsErr,BtClass,$H13,BtMethod,"Holt-Winters")/SUMIFS(BtActual,BtClass,$H13,BtMethod,"Holt-Winters"),"") -> 1.1361949 | N13: =IFERROR(SUMIFS(BtErr,BtClass,$H13,BtMethod,"Naive")/SUMIFS(BtActual,BtClass,$H13,BtMethod,"Naive"),"") -> -0.67380876 | O13: =IFERROR(SUMIFS(BtErr,BtClass,$H13,BtMethod,"Moving average")/SUMIFS(BtActual,BtClass,$H13,BtMethod,"Moving average"),"") -> -0.38839143 | P13: =IFERROR(SUMIFS(BtErr,BtClass,$H13,BtMethod,"SES")/SUMIFS(BtActual,BtClass,$H13,BtMethod,"SES"),"") -> -0.30994589 | Q13: =IFERROR(SUMIFS(BtErr,BtClass,$H13,BtMethod,"Holt-Winters")/SUMIFS(BtActual,BtClass,$H13,BtMethod,"Holt-Winters"),"") -> 0.55824007 | R13: =IFERROR(J13+ABS(N13),"") -> 1.5618804 | S13: =IFERROR(K13+ABS(O13),"") -> 1.1325552 | T13: =IFERROR(L13+ABS(P13),"") -> 1.1238086 | U13: =IFERROR(M13+ABS(Q13),"") -> 1.694435 | V13: =IF(I13=0,"",SUBSTITUTE(INDEX($R$4:$U$4,MATCH(MIN(R13:U13),R13:U13,0)),"Score ","")) -> SES | W13: =IF(I13=0,"",SUBSTITUTE(INDEX($R$4:$T$4,MATCH(MIN(R13:T13),R13:T13,0)),"Score ","")) -> SES
A14: 47566 | B14: Moving average | C14: 2356 | D14: 3105.5 | E14: 3105.5 | F14: =_xlfn.XLOOKUP(A14,ClsCode,ClsClass) -> AX
A15: 47566 | B15: SES | C15: 2356 | D15: 2229.064 | E15: 2068.4768 | F15: =_xlfn.XLOOKUP(A15,ClsCode,ClsClass) -> AX | H15: All | I15: =SUM(I5:I13) -> 150 | J15: =SUMIFS(BtAbsErr,BtMethod,"Naive")/SUMIFS(BtActual,BtMethod,"Naive") -> 0.70415321 | K15: =SUMIFS(BtAbsErr,BtMethod,"Moving average")/SUMIFS(BtActual,BtMethod,"Moving average") -> 0.59950477 | L15: =SUMIFS(BtAbsErr,BtMethod,"SES")/SUMIFS(BtActual,BtMethod,"SES") -> 0.58890462 | M15: =SUMIFS(BtAbsErr,BtMethod,"Holt-Winters")/SUMIFS(BtActual,BtMethod,"Holt-Winters") -> 0.62435037 | N15: =SUMIFS(BtErr,BtMethod,"Naive")/SUMIFS(BtActual,BtMethod,"Naive") -> -0.34303476 | O15: =SUMIFS(BtErr,BtMethod,"Moving average")/SUMIFS(BtActual,BtMethod,"Moving average") -> -0.22563635 | P15: =SUMIFS(BtErr,BtMethod,"SES")/SUMIFS(BtActual,BtMethod,"SES") -> -0.2216346 | Q15: =SUMIFS(BtErr,BtMethod,"Holt-Winters")/SUMIFS(BtActual,BtMethod,"Holt-Winters") -> 0.08523496 | R15: =J15+ABS(N15) -> 1.047188 | S15: =K15+ABS(O15) -> 0.82514113 | T15: =L15+ABS(P15) -> 0.81053922 | U15: =M15+ABS(Q15) -> 0.70958533
A16: 47566 | B16: Holt-Winters | C16: 2356 | D16: 5195.5691 | E16: 5195.5691 | F16: =_xlfn.XLOOKUP(A16,ClsCode,ClsClass) -> AX
A17: 85099B | B17: Naive | C17: 13967 | D17: 6275 | E17: -5375 | F17: =_xlfn.XLOOKUP(A17,ClsCode,ClsClass) -> AX | H17: Why choose per class and not per SKU? 12 weeks is a short test, so one SKU's 'best' method is often luck. Pooling the SKUs of a class gives a more stable choice. Holt-Winters is only used for seasonal SKUs; a non-seasonal SKU in a Holt-Winters class gets the best non-seasonal method.
A18: 85099B | B18: Moving average | C18: 13967 | D18: 5967 | E18: -2694.5 | F18: =_xlfn.XLOOKUP(A18,ClsCode,ClsClass) -> AX
A19: 85099B | B19: SES | C19: 13967 | D19: 5967 | E19: -2247.2408 | F19: =_xlfn.XLOOKUP(A19,ClsCode,ClsClass) -> AX
A20: 85099B | B20: Holt-Winters | C20: 13967 | D20: 6718.8417 | E20: 623.8583 | F20: =_xlfn.XLOOKUP(A20,ClsCode,ClsClass) -> AX
A21: 84879 | B21: Naive | C21: 10500 | D21: 7908 | E21: -7908 | F21: =_xlfn.XLOOKUP(A21,ClsCode,ClsClass) -> AY
A22: 84879 | B22: Moving average | C22: 10500 | D22: 3724 | E22: 1644 | F22: =_xlfn.XLOOKUP(A22,ClsCode,ClsClass) -> AY
A23: 84879 | B23: SES | C23: 10500 | D23: 3072.563 | E23: -476.622 | F23: =_xlfn.XLOOKUP(A23,ClsCode,ClsClass) -> AY
A24: 84879 | B24: Holt-Winters | C24: 10500 | D24: 7177.6539 | E24: 7177.6539 | F24: =_xlfn.XLOOKUP(A24,ClsCode,ClsClass) -> AY
A25: 22086 | B25: Naive | C25: 12113 | D25: 9821 | E25: -9821 | F25: =_xlfn.XLOOKUP(A25,ClsCode,ClsClass) -> AZ
A26: 22086 | B26: Moving average | C26: 12113 | D26: 10965.5 | E26: -10965.5 | F26: =_xlfn.XLOOKUP(A26,ClsCode,ClsClass) -> AZ
A27: 22086 | B27: SES | C27: 12113 | D27: 9918.6272 | E27: -9918.6272 | F27: =_xlfn.XLOOKUP(A27,ClsCode,ClsClass) -> AZ
A28: 22086 | B28: Holt-Winters | C28: 12113 | D28: 4123.9499 | E28: -2293.8493 | F28: =_xlfn.XLOOKUP(A28,ClsCode,ClsClass) -> AZ
A29: 79321 | B29: Naive | C29: 3258 | D29: 2206 | E29: -738 | F29: =_xlfn.XLOOKUP(A29,ClsCode,ClsClass) -> AY
... A604: 21791 | B604: Holt-Winters | C604: 2599 | D604: 2002.0092 | E604: 1451.8472 | F604: =_xlfn.XLOOKUP(A604,ClsCode,ClsClass) -> CY

Sheet Policy
A1: Inventory policy per SKU (recalculates from Inputs)
A2: Safety stock = z × σ × √lead time · Reorder point = forecast lead-time demand + safety stock · EOQ = √(2DS / hC) · Max = ROP + EOQ
A4: Stock code | B4: Description | C4: Class | D4: Forecast method | E4: Avg weekly demand | F4: σ weekly | G4: Unit cost (£) | H4: Service level | I4: z | J4: Lead-time demand (forecast) | K4: Safety stock | L4: Reorder point = Min | M4: Annual demand | N4: EOQ | O4: Max | P4: Avg stock (recommended) | Q4: Weeks of cover (rec.) | R4: Current stock (assumed) | S4: Weeks of cover (now) | T4: Current stock value (£) | U4: Recommended stock value (£) | V4: Working capital freed (£) | W4: Status | X4: Stock-out risk if no order now | Y4: Suggested order qty | Z4: Holding cost / yr (£) | AA4: Ordering cost / yr (£) | AB4: Shortfall value (£) | AC4: Rank helper
A5: =ABC_XYZ!A5 -> 22423 | B5: =ABC_XYZ!B5 -> REGENCY CAKESTAND 3 TIER | C5: =ABC_XYZ!K5 -> AX | D5: =IF(AND(_xlfn.XLOOKUP(C5,BestClass,BestMethod)="Holt-Winters",ABC_XYZ!M5="No"),_xlfn.XLOOKUP(C5,BestClass,BestFlat),_xlfn.XLOOKUP(C5,BestClass,BestMethod)) -> Moving average | E5: =ABC_XYZ!G5 -> 244.40385 | F5: =ABC_XYZ!H5 -> 157.82943 | G5: =ABC_XYZ!N5*CostRatio -> 7.5188284 | H5: =_xlfn.XLOOKUP(LEFT(C5,1),ClassList,ClassSL) -> 0.95 | I5: =_xlfn.NORM.S.INV(H5) -> 1.6448536 | J5: =SUMIFS(FutUnits,FutCode,A5,FutMethod,D5,FutHorizon,"<="&LeadTime) -> 688.875 | K5: =ROUNDUP(I5*F5*SQRT(LeadTime),0) -> 450 | L5: =ROUNDUP(J5,0)+K5 -> 1139 | M5: =E5*WeeksPerYear -> 12709 | N5: =ROUNDUP(SQRT(2*M5*OrderCost/(HoldingRate*G5)),0) -> 823 | O5: =L5+N5 -> 1962 | P5: =K5+N5/2 -> 861.5 | Q5: =P5/E5 -> 3.5249036 | R5: =ROUND(CurrentCover*E5,0) -> 1955 | S5: =R5/E5 -> 7.9990558 | T5: =R5*G5 -> 14699.31 | U5: =P5*G5 -> 6477.4707 | V5: =T5-U5 -> 8221.8389 | W5: =IF(R5<=L5,"Reorder now",IF(R5>O5,"Overstock","OK")) -> OK | X5: =1-_xlfn.NORM.S.DIST((R5-J5)/(F5*SQRT(LeadTime)),TRUE) -> 1.81454e-06 | Y5: =IF(W5="Reorder now",O5-R5,0) -> 0 | Z5: =U5*HoldingRate -> 1619.3677 | AA5: =M5/N5*OrderCost -> 772.11422 | AB5: =MAX(0,L5-R5)*G5 -> 0 | AC5: =AB5+ROW()/1000000 -> 5e-06
A6: =ABC_XYZ!A6 -> 85123A | B6: =ABC_XYZ!B6 -> WHITE HANGING HEART T-LIGHT HOLDER | C6: =ABC_XYZ!K6 -> AY | D6: =IF(AND(_xlfn.XLOOKUP(C6,BestClass,BestMethod)="Holt-Winters",ABC_XYZ!M6="No"),_xlfn.XLOOKUP(C6,BestClass,BestFlat),_xlfn.XLOOKUP(C6,BestClass,BestMethod)) -> Holt-Winters | E6: =ABC_XYZ!G6 -> 665.01923 | F6: =ABC_XYZ!H6 -> 519.54797 | G6: =ABC_XYZ!N6*CostRatio -> 1.6849495 | H6: =_xlfn.XLOOKUP(LEFT(C6,1),ClassList,ClassSL) -> 0.95 | I6: =_xlfn.NORM.S.INV(H6) -> 1.6448536 | J6: =SUMIFS(FutUnits,FutCode,A6,FutMethod,D6,FutHorizon,"<="&LeadTime) -> 1906.554 | K6: =ROUNDUP(I6*F6*SQRT(LeadTime),0) -> 1481 | L6: =ROUNDUP(J6,0)+K6 -> 3388 | M6: =E6*WeeksPerYear -> 34581 | N6: =ROUNDUP(SQRT(2*M6*OrderCost/(HoldingRate*G6)),0) -> 2866 | O6: =L6+N6 -> 6254 | P6: =K6+N6/2 -> 2914 | Q6: =P6/E6 -> 4.3818282 | R6: =ROUND(CurrentCover*E6,0) -> 5320 | S6: =R6/E6 -> 7.9997687 | T6: =R6*G6 -> 8963.9311 | U6: =P6*G6 -> 4909.9427 | V6: =T6-U6 -> 4053.9884 | W6: =IF(R6<=L6,"Reorder now",IF(R6>O6,"Overstock","OK")) -> OK | X6: =1-_xlfn.NORM.S.DIST((R6-J6)/(F6*SQRT(LeadTime)),TRUE) -> 7.4356492e-05 | Y6: =IF(W6="Reorder now",O6-R6,0) -> 0 | Z6: =U6*HoldingRate -> 1227.4857 | AA6: =M6/N6*OrderCost -> 603.29728 | AB6: =MAX(0,L6-R6)*G6 -> 0 | AC6: =AB6+ROW()/1000000 -> 6e-06
A7: =ABC_XYZ!A7 -> 47566 | B7: =ABC_XYZ!B7 -> PARTY BUNTING | C7: =ABC_XYZ!K7 -> AX | D7: =IF(AND(_xlfn.XLOOKUP(C7,BestClass,BestMethod)="Holt-Winters",ABC_XYZ!M7="No"),_xlfn.XLOOKUP(C7,BestClass,BestFlat),_xlfn.XLOOKUP(C7,BestClass,BestMethod)) -> Moving average | E7: =ABC_XYZ!G7 -> 343.88462 | F7: =ABC_XYZ!H7 -> 253.99326 | G7: =ABC_XYZ!N7*CostRatio -> 3.2554644 | H7: =_xlfn.XLOOKUP(LEFT(C7,1),ClassList,ClassSL) -> 0.95 | I7: =_xlfn.NORM.S.INV(H7) -> 1.6448536 | J7: =SUMIFS(FutUnits,FutCode,A7,FutMethod,D7,FutHorizon,"<="&LeadTime) -> 532.875 | K7: =ROUNDUP(I7*F7*SQRT(LeadTime),0) -> 724 | L7: =ROUNDUP(J7,0)+K7 -> 1257 | M7: =E7*WeeksPerYear -> 17882 | N7: =ROUNDUP(SQRT(2*M7*OrderCost/(HoldingRate*G7)),0) -> 1483 | O7: =L7+N7 -> 2740 | P7: =K7+N7/2 -> 1465.5 | Q7: =P7/E7 -> 4.2616038 | R7: =ROUND(CurrentCover*E7,0) -> 2751 | S7: =R7/E7 -> 7.9997763 | T7: =R7*G7 -> 8955.7826 | U7: =P7*G7 -> 4770.8831 | V7: =T7-U7 -> 4184.8995 | W7: =IF(R7<=L7,"Reorder now",IF(R7>O7,"Overstock","OK")) -> Overstock | X7: =1-_xlfn.NORM.S.DIST((R7-J7)/(F7*SQRT(LeadTime)),TRUE) -> 2.303406e-07 | Y7: =IF(W7="Reorder now",O7-R7,0) -> 0 | Z7: =U7*HoldingRate -> 1192.7208 | AA7: =M7/N7*OrderCost -> 602.89953 | AB7: =MAX(0,L7-R7)*G7 -> 0 | AC7: =AB7+ROW()/1000000 -> 7e-06
A8: =ABC_XYZ!A8 -> 85099B | B8: =ABC_XYZ!B8 -> JUMBO BAG RED RETROSPOT | C8: =ABC_XYZ!K8 -> AX | D8: =IF(AND(_xlfn.XLOOKUP(C8,BestClass,BestMethod)="Holt-Winters",ABC_XYZ!M8="No"),_xlfn.XLOOKUP(C8,BestClass,BestFlat),_xlfn.XLOOKUP(C8,BestClass,BestMethod)) -> Moving average | E8: =ABC_XYZ!G8 -> 900.42308 | F8: =ABC_XYZ!H8 -> 493.56249 | G8: =ABC_XYZ!N8*CostRatio -> 1.1621706 | H8: =_xlfn.XLOOKUP(LEFT(C8,1),ClassList,ClassSL) -> 0.95 | I8: =_xlfn.NORM.S.INV(H8) -> 1.6448536 | J8: =SUMIFS(FutUnits,FutCode,A8,FutMethod,D8,FutHorizon,"<="&LeadTime) -> 3827.625 | K8: =ROUNDUP(I8*F8*SQRT(LeadTime),0) -> 1407 | L8: =ROUNDUP(J8,0)+K8 -> 5235 | M8: =E8*WeeksPerYear -> 46822 | N8: =ROUNDUP(SQRT(2*M8*OrderCost/(HoldingRate*G8)),0) -> 4015 | O8: =L8+N8 -> 9250 | P8: =K8+N8/2 -> 3414.5 | Q8: =P8/E8 -> 3.7921063 | R8: =ROUND(CurrentCover*E8,0) -> 7203 | S8: =R8/E8 -> 7.9995729 | T8: =R8*G8 -> 8371.1151 | U8: =P8*G8 -> 3968.2317 | V8: =T8-U8 -> 4402.8835 | W8: =IF(R8<=L8,"Reorder now",IF(R8>O8,"Overstock","OK")) -> OK | X8: =1-_xlfn.NORM.S.DIST((R8-J8)/(F8*SQRT(LeadTime)),TRUE) -> 3.9340458e-05 | Y8: =IF(W8="Reorder now",O8-R8,0) -> 0 | Z8: =U8*HoldingRate -> 992.05791 | AA8: =M8/N8*OrderCost -> 583.08842 | AB8: =MAX(0,L8-R8)*G8 -> 0 | AC8: =AB8+ROW()/1000000 -> 8e-06
A9: =ABC_XYZ!A9 -> 84879 | B9: =ABC_XYZ!B9 -> ASSORTED COLOUR BIRD ORNAMENT | C9: =ABC_XYZ!K9 -> AY | D9: =IF(AND(_xlfn.XLOOKUP(C9,BestClass,BestMethod)="Holt-Winters",ABC_XYZ!M9="No"),_xlfn.XLOOKUP(C9,BestClass,BestFlat),_xlfn.XLOOKUP(C9,BestClass,BestMethod)) -> Holt-Winters | E9: =ABC_XYZ!G9 -> 667.76923 | F9: =ABC_XYZ!H9 -> 560.66958 | G9: =ABC_XYZ!N9*CostRatio -> 0.97202861 | H9: =_xlfn.XLOOKUP(LEFT(C9,1),ClassList,ClassSL) -> 0.95 | I9: =_xlfn.NORM.S.INV(H9) -> 1.6448536 | J9: =SUMIFS(FutUnits,FutCode,A9,FutMethod,D9,FutHorizon,"<="&LeadTime) -> 1665.5237 | K9: =ROUNDUP(I9*F9*SQRT(LeadTime),0) -> 1598 | L9: =ROUNDUP(J9,0)+K9 -> 3264 | M9: =E9*WeeksPerYear -> 34724 | N9: =ROUNDUP(SQRT(2*M9*OrderCost/(HoldingRate*G9)),0) -> 3781 | O9: =L9+N9 -> 7045 | P9: =K9+N9/2 -> 3488.5 | Q9: =P9/E9 -> 5.2241101 | R9: =ROUND(CurrentCover*E9,0) -> 5342 | S9: =R9/E9 -> 7.9997696 | T9: =R9*G9 -> 5192.5769 | U9: =P9*G9 -> 3390.9218 | V9: =T9-U9 -> 1801.655 | W9: =IF(R9<=L9,"Reorder now",IF(R9>O9,"Overstock","OK")) -> OK | X9: =1-_xlfn.NORM.S.DIST((R9-J9)/(F9*SQRT(LeadTime)),TRUE) -> 7.6590022e-05 | Y9: =IF(W9="Reorder now",O9-R9,0) -> 0 | Z9: =U9*HoldingRate -> 847.73046 | AA9: =M9/N9*OrderCost -> 459.19069 | AB9: =MAX(0,L9-R9)*G9 -> 0 | AC9: =AB9+ROW()/1000000 -> 9e-06
A10: =ABC_XYZ!A10 -> 22086 | B10: =ABC_XYZ!B10 -> PAPER CHAIN KIT 50'S CHRISTMAS | C10: =ABC_XYZ!K10 -> AZ | D10: =IF(AND(_xlfn.XLOOKUP(C10,BestClass,BestMethod)="Holt-Winters",ABC_XYZ!M10="No"),_xlfn.XLOOKUP(C10,BestClass,BestFlat),_xlfn.XLOOKUP(C10,BestClass,BestMethod)) -> Holt-Winters | E10: =ABC_XYZ!G10 -> 313.82692 | F10: =ABC_XYZ!H10 -> 522.61637 | G10: =ABC_XYZ!N10*CostRatio -> 2.0390072 | H10: =_xlfn.XLOOKUP(LEFT(C10,1),ClassList,ClassSL) -> 0.95 | I10: =_xlfn.NORM.S.INV(H10) -> 1.6448536 | J10: =SUMIFS(FutUnits,FutCode,A10,FutMethod,D10,FutHorizon,"<="&LeadTime) -> 1885.2431 | K10: =ROUNDUP(I10*F10*SQRT(LeadTime),0) -> 1489 | L10: =ROUNDUP(J10,0)+K10 -> 3375 | M10: =E10*WeeksPerYear -> 16319 | N10: =ROUNDUP(SQRT(2*M10*OrderCost/(HoldingRate*G10)),0) -> 1790 | O10: =L10+N10 -> 5165 | P10: =K10+N10/2 -> 2384 | Q10: =P10/E10 -> 7.5965439 | R10: =ROUND(CurrentCover*E10,0) -> 2511 | S10: =R10/E10 -> 8.0012256 | T10: =R10*G10 -> 5119.947 | U10: =P10*G10 -> 4860.9931 | V10: =T10-U10 -> 258.95391 | W10: =IF(R10<=L10,"Reorder now",IF(R10>O10,"Overstock","OK")) -> Reorder now | X10: =1-_xlfn.NORM.S.DIST((R10-J10)/(F10*SQRT(LeadTime)),TRUE) -> 0.24469079 | Y10: =IF(W10="Reorder now",O10-R10,0) -> 2654 | Z10: =U10*HoldingRate -> 1215.2483 | AA10: =M10/N10*OrderCost -> 455.83799 | AB10: =MAX(0,L10-R10)*G10 -> 1761.7022 | AC10: =AB10+ROW()/1000000 -> 1761.7022
A11: =ABC_XYZ!A11 -> 79321 | B11: =ABC_XYZ!B11 -> CHILLI LIGHTS | C11: =ABC_XYZ!K11 -> AY | D11: =IF(AND(_xlfn.XLOOKUP(C11,BestClass,BestMethod)="Holt-Winters",ABC_XYZ!M11="No"),_xlfn.XLOOKUP(C11,BestClass,BestFlat),_xlfn.XLOOKUP(C11,BestClass,BestMethod)) -> Holt-Winters | E11: =ABC_XYZ!G11 -> 189.92308 | F11: =ABC_XYZ!H11 -> 226.97049 | G11: =ABC_XYZ!N11*CostRatio -> 3.1261995 | H11: =_xlfn.XLOOKUP(LEFT(C11,1),ClassList,ClassSL) -> 0.95 | I11: =_xlfn.NORM.S.INV(H11) -> 1.6448536 | J11: =SUMIFS(FutUnits,FutCode,A11,FutMethod,D11,FutHorizon,"<="&LeadTime) -> 820.8764 | K11: =ROUNDUP(I11*F11*SQRT(LeadTime),0) -> 647 | L11: =ROUNDUP(J11,0)+K11 -> 1468 | M11: =E11*WeeksPerYear -> 9876 | N11: =ROUNDUP(SQRT(2*M11*OrderCost/(HoldingRate*G11)),0) -> 1125 | O11: =L11+N11 -> 2593 | P11: =K11+N11/2 -> 1209.5 | Q11: =P11/E11 -> 6.3683678 | R11: =ROUND(CurrentCover*E11,0) -> 1519 | S11: =R11/E11 -> 7.9979749 | T11: =R11*G11 -> 4748.697 | U11: =P11*G11 -> 3781.1383 | V11: =T11-U11 -> 967.55874 | W11: =IF(R11<=L11,"Reorder now",IF(R11>O11,"Overstock","OK")) -> OK | X11: =1-_xlfn.NORM.S.DIST((R11-J11)/(F11*SQRT(LeadTime)),TRUE) -> 0.037880162 | Y11: =IF(W11="Reorder now",O11-R11,0) -> 0 | Z11: =U11*HoldingRate -> 945.28457 | AA11: =M11/N11*OrderCost -> 438.93333 | AB11: =MAX(0,L11-R11)*G11 -> 0 | AC11: =AB11+ROW()/1000000 -> 1.1e-05
A12: =ABC_XYZ!A12 -> 22502 | B12: =ABC_XYZ!B12 -> PICNIC BASKET WICKER SMALL | C12: =ABC_XYZ!K12 -> AZ | D12: =IF(AND(_xlfn.XLOOKUP(C12,BestClass,BestMethod)="Holt-Winters",ABC_XYZ!M12="No"),_xlfn.XLOOKUP(C12,BestClass,BestFlat),_xlfn.XLOOKUP(C12,BestClass,BestMethod)) -> Holt-Winters | E12: =ABC_XYZ!G12 -> 36.673077 | F12: =ABC_XYZ!H12 -> 48.335316 | G12: =ABC_XYZ!N12*CostRatio -> 15.651112 | H12: =_xlfn.XLOOKUP(LEFT(C12,1),ClassList,ClassSL) -> 0.95 | I12: =_xlfn.NORM.S.INV(H12) -> 1.6448536 | J12: =SUMIFS(FutUnits,FutCode,A12,FutMethod,D12,FutHorizon,"<="&LeadTime) -> 0 | K12: =ROUNDUP(I12*F12*SQRT(LeadTime),0) -> 138 | L12: =ROUNDUP(J12,0)+K12 -> 138 | M12: =E12*WeeksPerYear -> 1907 | N12: =ROUNDUP(SQRT(2*M12*OrderCost/(HoldingRate*G12)),0) -> 221 | O12: =L12+N12 -> 359 | P12: =K12+N12/2 -> 248.5 | Q12: =P12/E12 -> 6.7760881 | R12: =ROUND(CurrentCover*E12,0) -> 293 | S12: =R12/E12 -> 7.9895123 | T12: =R12*G12 -> 4585.7758 | U12: =P12*G12 -> 3889.3013 | V12: =T12-U12 -> 696.47448 | W12: =IF(R12<=L12,"Reorder now",IF(R12>O12,"Overstock","OK")) -> OK | X12: =1-_xlfn.NORM.S.DIST((R12-J12)/(F12*SQRT(LeadTime)),TRUE) -> 0.00023280929 | Y12: =IF(W12="Reorder now",O12-R12,0) -> 0 | Z12: =U12*HoldingRate -> 972.32533 | AA12: =M12/N12*OrderCost -> 431.44796 | AB12: =MAX(0,L12-R12)*G12 -> 0 | AC12: =AB12+ROW()/1000000 -> 1.2e-05
A13: =ABC_XYZ!A13 -> 22197 | B13: =ABC_XYZ!B13 -> SMALL POPCORN HOLDER | C13: =ABC_XYZ!K13 -> AY | D13: =IF(AND(_xlfn.XLOOKUP(C13,BestClass,BestMethod)="Holt-Winters",ABC_XYZ!M13="No"),_xlfn.XLOOKUP(C13,BestClass,BestFlat),_xlfn.XLOOKUP(C13,BestClass,BestMethod)) -> Holt-Winters | E13: =ABC_XYZ!G13 -> 940.19231 | F13: =ABC_XYZ!H13 -> 942.673 | G13: =ABC_XYZ!N13*CostRatio -> 0.54449663 | H13: =_xlfn.XLOOKUP(LEFT(C13,1),ClassList,ClassSL) -> 0.95 | I13: =_xlfn.NORM.S.INV(H13) -> 1.6448536 | J13: =SUMIFS(FutUnits,FutCode,A13,FutMethod,D13,FutHorizon,"<="&LeadTime) -> 3294.6563 | K13: =ROUNDUP(I13*F13*SQRT(LeadTime),0) -> 2686 | L13: =ROUNDUP(J13,0)+K13 -> 5981 | M13: =E13*WeeksPerYear -> 48890 | N13: =ROUNDUP(SQRT(2*M13*OrderCost/(HoldingRate*G13)),0) -> 5993 | O13: =L13+N13 -> 11974 | P13: =K13+N13/2 -> 5682.5 | Q13: =P13/E13 -> 6.0439763 | R13: =ROUND(CurrentCover*E13,0) -> 7522 | S13: =R13/E13 -> 8.0004909 | T13: =R13*G13 -> 4095.7036 | U13: =P13*G13 -> 3094.1021 | V13: =T13-U13 -> 1001.6015 | W13: =IF(R13<=L13,"Reorder now",IF(R13>O13,"Overstock","OK")) -> OK | X13: =1-_xlfn.NORM.S.DIST((R13-J13)/(F13*SQRT(LeadTime)),TRUE) -> 0.0048116041 | Y13: =IF(W13="Reorder now",O13-R13,0) -> 0 | Z13: =U13*HoldingRate -> 773.52552 | AA13: =M13/N13*OrderCost -> 407.89254 | AB13: =MAX(0,L13-R13)*G13 -> 0 | AC13: =AB13+ROW()/1000000 -> 1.3e-05
A14: =ABC_XYZ!A14 -> 22386 | B14: =ABC_XYZ!B14 -> JUMBO BAG PINK POLKADOT | C14: =ABC_XYZ!K14 -> AX | D14: =IF(AND(_xlfn.XLOOKUP(C14,BestClass,BestMethod)="Holt-Winters",ABC_XYZ!M14="No"),_xlfn.XLOOKUP(C14,BestClass,BestFlat),_xlfn.XLOOKUP(C14,BestClass,BestMethod)) -> Moving average | E14: =ABC_XYZ!G14 -> 396.30769 | F14: =ABC_XYZ!H14 -> 278.83515 | G14: =ABC_XYZ!N14*CostRatio -> 1.1842563 | H14: =_xlfn.XLOOKUP(LEFT(C14,1),ClassList,ClassSL) -> 0.95 | I14: =_xlfn.NORM.S.INV(H14) -> 1.6448536 | J14: =SUMIFS(FutUnits,FutCode,A14,FutMethod,D14,FutHorizon,"<="&LeadTime) -> 1632 | K14: =ROUNDUP(I14*F14*SQRT(LeadTime),0) -> 795 | L14: =ROUNDUP(J14,0)+K14 -> 2427 | M14: =E14*WeeksPerYear -> 20608 | N14: =ROUNDUP(SQRT(2*M14*OrderCost/(HoldingRate*G14)),0) -> 2639 | O14: =L14+N14 -> 5066 | P14: =K14+N14/2 -> 2114.5 | Q14: =P14/E14 -> 5.3355008 | R14: =ROUND(CurrentCover*E14,0) -> 3170 | S14: =R14/E14 -> 7.9988354 | T14: =R14*G14 -> 3754.0924 | U14: =P14*G14 -> 2504.1099 | V14: =T14-U14 -> 1249.9825 | W14: =IF(R14<=L14,"Reorder now",IF(R14>O14,"Overstock","OK")) -> OK | X14: =1-_xlfn.NORM.S.DIST((R14-J14)/(F14*SQRT(LeadTime)),TRUE) -> 0.00072489418 | Y14: =IF(W14="Reorder now",O14-R14,0) -> 0 | Z14: =U14*HoldingRate -> 626.02747 | AA14: =M14/N14*OrderCost -> 390.45093 | AB14: =MAX(0,L14-R14)*G14 -> 0 | AC14: =AB14+ROW()/1000000 -> 1.4e-05
A15: =ABC_XYZ!A15 -> 21137 | B15: =ABC_XYZ!B15 -> BLACK RECORD COVER FRAME | C15: =ABC_XYZ!K15 -> AY | D15: =IF(AND(_xlfn.XLOOKUP(C15,BestClass,BestMethod)="Holt-Winters",ABC_XYZ!M15="No"),_xlfn.XLOOKUP(C15,BestClass,BestFlat),_xlfn.XLOOKUP(C15,BestClass,BestMethod)) -> Holt-Winters | E15: =ABC_XYZ!G15 -> 191.69231 | F15: =ABC_XYZ!H15 -> 227.12004 | G15: =ABC_XYZ!N15*CostRatio -> 2.0814805 | H15: =_xlfn.XLOOKUP(LEFT(C15,1),ClassList,ClassSL) -> 0.95 | I15: =_xlfn.NORM.S.INV(H15) -> 1.6448536 | J15: =SUMIFS(FutUnits,FutCode,A15,FutMethod,D15,FutHorizon,"<="&LeadTime) -> 656.0198 | K15: =ROUNDUP(I15*F15*SQRT(LeadTime),0) -> 648 | L15: =ROUNDUP(J15,0)+K15 -> 1305 | M15: =E15*WeeksPerYear -> 9968 | N15: =ROUNDUP(SQRT(2*M15*OrderCost/(HoldingRate*G15)),0) -> 1385 | O15: =L15+N15 -> 2690 | P15: =K15+N15/2 -> 1340.5 | Q15: =P15/E15 -> 6.9929775 | R15: =ROUND(CurrentCover*E15,0) -> 1534 | S15: =R15/E15 -> 8.0024077 | T15: =R15*G15 -> 3192.9911 | U15: =P15*G15 -> 2790.2246 | V15: =T15-U15 -> 402.76647 | W15: =IF(R15<=L15,"Reorder now",IF(R15>O15,"Overstock","OK")) -> OK | X15: =1-_xlfn.NORM.S.DIST((R15-J15)/(F15*SQRT(LeadTime)),TRUE) -> 0.012811821 | Y15: =IF(W15="Reorder now",O15-R15,0) -> 0 | Z15: =U15*HoldingRate -> 697.55615 | AA15: =M15/N15*OrderCost -> 359.8556 | AB15: =MAX(0,L15-R15)*G15 -> 0 | AC15: =AB15+ROW()/1000000 -> 1.5e-05
A16: =ABC_XYZ!A16 -> 20725 | B16: =ABC_XYZ!B16 -> LUNCH BAG RED RETROSPOT | C16: =ABC_XYZ!K16 -> AX | D16: =IF(AND(_xlfn.XLOOKUP(C16,BestClass,BestMethod)="Holt-Winters",ABC_XYZ!M16="No"),_xlfn.XLOOKUP(C16,BestClass,BestFlat),_xlfn.XLOOKUP(C16,BestClass,BestMethod)) -> Moving average | E16: =ABC_XYZ!G16 -> 352.61538 | F16: =ABC_XYZ!H16 -> 174.64969 | G16: =ABC_XYZ!N16*CostRatio -> 1.1026018 | H16: =_xlfn.XLOOKUP(LEFT(C16,1),ClassList,ClassSL) -> 0.95 | I16: =_xlfn.NORM.S.INV(H16) -> 1.6448536 | J16: =SUMIFS(FutUnits,FutCode,A16,FutMethod,D16,FutHorizon,"<="&LeadTime) -> 1128 | K16: =ROUNDUP(I16*F16*SQRT(LeadTime),0) -> 498 | L16: =ROUNDUP(J16,0)+K16 -> 1626 | M16: =E16*WeeksPerYear -> 18336 | N16: =ROUNDUP(SQRT(2*M16*OrderCost/(HoldingRate*G16)),0) -> 2580 | O16: =L16+N16 -> 4206 | P16: =K16+N16/2 -> 1788 | Q16: =P16/E16 -> 5.0706806 | R16: =ROUND(CurrentCover*E16,0) -> 2821 | S16: =R16/E16 -> 8.0002182 | T16: =R16*G16 -> 3110.4398 | U16: =P16*G16 -> 1971.4521 | V16: =T16-U16 -> 1138.9877 | W16: =IF(R16<=L16,"Reorder now",IF(R16>O16,"Overstock","OK")) -> OK | X16: =1-_xlfn.NORM.S.DIST((R16-J16)/(F16*SQRT(LeadTime)),TRUE) -> 1.0926377e-08 | Y16: =IF(W16="Reorder now",O16-R16,0) -> 0 | Z16: =U16*HoldingRate -> 492.86302 | AA16: =M16/N16*OrderCost -> 355.34884 | AB16: =MAX(0,L16-R16)*G16 -> 0 | AC16: =AB16+ROW()/1000000 -> 1.6e-05
... A154: =ABC_XYZ!A154 -> 21791 | B154: =ABC_XYZ!B154 -> VINTAGE HEADS AND TAILS CARD GAME | C154: =ABC_XYZ!K154 -> CY | D154: =IF(AND(_xlfn.XLOOKUP(C154,BestClass,BestMethod)="Holt-Winters",ABC_XYZ!M154="No"),_xlfn.XLOOKUP(C154,BestClass,BestFlat),_xlfn.XLOOKUP(C154,BestClass,BestMethod)) -> SES | E154: =ABC_XYZ!G154 -> 143.75 | F154: =ABC_XYZ!H154 -> 160.7869 | G154: =ABC_XYZ!N154*CostRatio -> 0.80122407 | H154: =_xlfn.XLOOKUP(LEFT(C154,1),ClassList,ClassSL) -> 0.95 | I154: =_xlfn.NORM.S.INV(H154) -> 1.6448536 | J154: =SUMIFS(FutUnits,FutCode,A154,FutMethod,D154,FutHorizon,"<="&LeadTime) -> 959.2674 | K154: =ROUNDUP(I154*F154*SQRT(LeadTime),0) -> 459 | L154: =ROUNDUP(J154,0)+K154 -> 1419 | M154: =E154*WeeksPerYear -> 7475 | N154: =ROUNDUP(SQRT(2*M154*OrderCost/(HoldingRate*G154)),0) -> 1932 | O154: =L154+N154 -> 3351 | P154: =K154+N154/2 -> 1425 | Q154: =P154/E154 -> 9.9130435 | R154: =ROUND(CurrentCover*E154,0) -> 1150 | S154: =R154/E154 -> 8 | T154: =R154*G154 -> 921.40768 | U154: =P154*G154 -> 1141.7443 | V154: =T154-U154 -> -220.33662 | W154: =IF(R154<=L154,"Reorder now",IF(R154>O154,"Overstock","OK")) -> Reorder now | X154: =1-_xlfn.NORM.S.DIST((R154-J154)/(F154*SQRT(LeadTime)),TRUE) -> 0.24671024 | Y154: =IF(W154="Reorder now",O154-R154,0) -> 2201 | Z154: =U154*HoldingRate -> 285.43608 | AA154: =M154/N154*OrderCost -> 193.45238 | AB154: =MAX(0,L154-R154)*G154 -> 215.52928 | AC154: =AB154+ROW()/1000000 -> 215.52943

Sheet Demand
A1: Weekly demand per SKU (units, net of returns) · DATA
A2: From notebook 01. Row 3 = week number, row 4 = week starting (Monday). Train = weeks 1-91, Test = 92-103, last 52 weeks = 52-103.
A3: Stock code | B3: Description | C3: 1 | D3: 2 | E3: 3 | F3: 4 | G3: 5 | H3: 6 | I3: 7 | J3: 8 | K3: 9 | L3: 10 | M3: 11 | N3: 12 | O3: 13 | P3: 14 | Q3: 15 | R3: 16 | S3: 17 | T3: 18 | U3: 19 | V3: 20 | W3: 21 | X3: 22 | Y3: 23 | Z3: 24 | AA3: 25 | AB3: 26 | AC3: 27 | AD3: 28 | AE3: 29 | AF3: 30 | AG3: 31 | AH3: 32 | AI3: 33 | AJ3: 34 | AK3: 35 | AL3: 36 | AM3: 37 | AN3: 38 | AO3: 39 | AP3: 40 | AQ3: 41 | AR3: 42 | AS3: 43 | AT3: 44 | AU3: 45 | AV3: 46 | AW3: 47 | AX3: 48 | AY3: 49 | AZ3: 50 | BA3: 51 | BB3: 52 | BC3: 53 | BD3: 54 | BE3: 55 | BF3: 56 | BG3: 57 | BH3: 58 | BI3: 59 | BJ3: 60 | BK3: 61 | BL3: 62 | BM3: 63 | BN3: 64 | BO3: 65 | BP3: 66 | BQ3: 67 | BR3: 68 | BS3: 69 | BT3: 70 | BU3: 71 | BV3: 72 | BW3: 73 | BX3: 74 | BY3: 75 | BZ3: 76 | CA3: 77 | CB3: 78 | CC3: 79 | CD3: 80 | CE3: 81 | CF3: 82 | CG3: 83 | CH3: 84 | CI3: 85 | CJ3: 86 | CK3: 87 | CL3: 88 | CM3: 89 | CN3: 90 | CO3: 91 | CP3: 92 | CQ3: 93 | CR3: 94 | CS3: 95 | CT3: 96 | CU3: 97 | CV3: 98 | CW3: 99 | CX3: 100 | CY3: 101 | CZ3: 102 | DA3: 103
A4: week starting → | C4: 40154 | D4: 40161 | E4: 40168 | F4: 40175 | G4: 40182 | H4: 40189 | I4: 40196 | J4: 40203 | K4: 40210 | L4: 40217 | M4: 40224 | N4: 40231 | O4: 40238 | P4: 40245 | Q4: 40252 | R4: 40259 | S4: 40266 | T4: 40273 | U4: 40280 | V4: 40287 | W4: 40294 | X4: 40301 | Y4: 40308 | Z4: 40315 | AA4: 40322 | AB4: 40329 | AC4: 40336 | AD4: 40343 | AE4: 40350 | AF4: 40357 | AG4: 40364 | AH4: 40371 | AI4: 40378 | AJ4: 40385 | AK4: 40392 | AL4: 40399 | AM4: 40406 | AN4: 40413 | AO4: 40420 | AP4: 40427 | AQ4: 40434 | AR4: 40441 | AS4: 40448 | AT4: 40455 | AU4: 40462 | AV4: 40469 | AW4: 40476 | AX4: 40483 | AY4: 40490 | AZ4: 40497 | BA4: 40504 | BB4: 40511 | BC4: 40518 | BD4: 40525 | BE4: 40532 | BF4: 40539 | BG4: 40546 | BH4: 40553 | BI4: 40560 | BJ4: 40567 | BK4: 40574 | BL4: 40581 | BM4: 40588 | BN4: 40595 | BO4: 40602 | BP4: 40609 | BQ4: 40616 | BR4: 40623 | BS4: 40630 | BT4: 40637 | BU4: 40644 | BV4: 40651 | BW4: 40658 | BX4: 40665 | BY4: 40672 | BZ4: 40679 | CA4: 40686 | CB4: 40693 | CC4: 40700 | CD4: 40707 | CE4: 40714 | CF4: 40721 | CG4: 40728 | CH4: 40735 | CI4: 40742 | CJ4: 40749 | CK4: 40756 | CL4: 40763 | CM4: 40770 | CN4: 40777 | CO4: 40784 | CP4: 40791 | CQ4: 40798 | CR4: 40805 | CS4: 40812 | CT4: 40819 | CU4: 40826 | CV4: 40833 | CW4: 40840 | CX4: 40847 | CY4: 40854 | CZ4: 40861 | DA4: 40868
A5: 22423 | B5: REGENCY CAKESTAND 3 TIER | C5: 0 | D5: 0 | E5: 0 | F5: 0 | G5: 0 | H5: 0 | I5: 0 | J5: 0 | K5: 0 | L5: 0 | M5: 0 | N5: 0 | O5: 0 | P5: 0 | Q5: 198 | R5: 423 | S5: 185 | T5: 231 | U5: 290 | V5: 349 | W5: 278 | X5: 298 | Y5: 107 | Z5: 16 | AA5: 15 | AB5: 92 | AC5: 456 | AD5: 447 | AE5: 178 | AF5: 390 | AG5: 122 | AH5: 101 | AI5: 453 | AJ5: 566 | AK5: 287 | AL5: 223 | AM5: 194 | AN5: 259 | AO5: 438 | AP5: 284 | AQ5: 367 | AR5: 607 | AS5: 372 | AT5: 486 | AU5: 304 | AV5: 356 | AW5: 639 | AX5: 240 | AY5: 546 | AZ5: 548 | BA5: 384 | BB5: 925 | BC5: 835 | BD5: 387 | BE5: 145 | BF5: 0 | BG5: 241 | BH5: 369 | BI5: 130 | BJ5: 199 | BK5: 140 | BL5: 117 | BM5: 391 | BN5: 195 | BO5: 329 | BP5: 165 | BQ5: 294 | BR5: 304 | BS5: 281 | BT5: 271 | BU5: 340 | BV5: 182 | BW5: 323 | BX5: 157 | BY5: 364 | BZ5: 302 | CA5: 152 | CB5: 259 | CC5: 208 | CD5: 169 | CE5: 129 | CF5: 82 | CG5: 129 | CH5: 284 | CI5: 340 | CJ5: 333 | CK5: 144 | CL5: 176 | CM5: 209 | CN5: 90 | CO5: 138 | CP5: 145 | CQ5: 217 | CR5: 136 | CS5: 146 | CT5: 407 | CU5: 204 | CV5: 235 | CW5: 123 | CX5: 228 | CY5: 162 | CZ5: 231 | DA5: 247
A6: 85123A | B6: WHITE HANGING HEART T-LIGHT HOLDER | C6: 3138 | D6: 1286 | E6: 125 | F6: 0 | G6: 1767 | H6: 917 | I6: 1405 | J6: 1373 | K6: 726 | L6: 576 | M6: 667 | N6: 922 | O6: 837 | P6: 833 | Q6: 1481 | R6: 1178 | S6: 895 | T6: 905 | U6: 842 | V6: 688 | W6: 1107 | X6: 1047 | Y6: 1105 | Z6: 1248 | AA6: 953 | AB6: 545 | AC6: 1590 | AD6: 581 | AE6: 784 | AF6: 1204 | AG6: 711 | AH6: 1261 | AI6: 1124 | AJ6: 587 | AK6: 542 | AL6: 1223 | AM6: 1685 | AN6: 793 | AO6: 877 | AP6: 912 | AQ6: 1038 | AR6: 1088 | AS6: 911 | AT6: 994 | AU6: 998 | AV6: 798 | AW6: 1144 | AX6: 1362 | AY6: 1624 | AZ6: 886 | BA6: 2002 | BB6: 1648 | BC6: 1120 | BD6: 1028 | BE6: 173 | BF6: 0 | BG6: 971 | BH6: 3327 | BI6: 655 | BJ6: 540 | BK6: 586 | BL6: 516 | BM6: 365 | BN6: 401 | BO6: 380 | BP6: 446 | BQ6: 463 | BR6: 365 | BS6: 574 | BT6: 368 | BU6: 474 | BV6: 492 | BW6: 375 | BX6: 1144 | BY6: 880 | BZ6: 794 | CA6: 1023 | CB6: 629 | CC6: 372 | CD6: 390 | CE6: 236 | CF6: 258 | CG6: 263 | CH6: 1198 | CI6: 720 | CJ6: 780 | CK6: 438 | CL6: 470 | CM6: 296 | CN6: 775 | CO6: 388 | CP6: 449 | CQ6: 662 | CR6: 697 | CS6: 404 | CT6: 162 | CU6: 683 | CV6: 233 | CW6: 447 | CX6: 1705 | CY6: 594 | CZ6: 1321 | DA6: 903
A7: 47566 | B7: PARTY BUNTING | C7: 18 | D7: 52 | E7: 1 | F7: 0 | G7: 47 | H7: 64 | I7: 49 | J7: 186 | K7: 52 | L7: 51 | M7: 159 | N7: 79 | O7: 78 | P7: 262 | Q7: 223 | R7: 212 | S7: 149 | T7: 179 | U7: 386 | V7: 525 | W7: 418 | X7: 565 | Y7: 435 | Z7: 450 | AA7: 671 | AB7: 301 | AC7: 716 | AD7: 141 | AE7: 52 | AF7: 51 | AG7: 52 | AH7: 44 | AI7: 52 | AJ7: 34 | AK7: 57 | AL7: 188 | AM7: 351 | AN7: 9 | AO7: 8 | AP7: 6 | AQ7: 0 | AR7: 99 | AS7: 915 | AT7: 262 | AU7: 333 | AV7: 167 | AW7: 155 | AX7: 58 | AY7: 98 | AZ7: 286 | BA7: 67 | BB7: 69 | BC7: 165 | BD7: 29 | BE7: 24 | BF7: 0 | BG7: 145 | BH7: 85 | BI7: 69 | BJ7: 170 | BK7: 232 | BL7: 292 | BM7: 189 | BN7: 157 | BO7: 254 | BP7: 205 | BQ7: 606 | BR7: 321 | BS7: 376 | BT7: 452 | BU7: 542 | BV7: 648 | BW7: 176 | BX7: 980 | BY7: 754 | BZ7: 753 | CA7: 835 | CB7: 434 | CC7: 658 | CD7: 507 | CE7: 581 | CF7: 276 | CG7: 901 | CH7: 354 | CI7: 935 | CJ7: 520 | CK7: 423 | CL7: 330 | CM7: 402 | CN7: 471 | CO7: 206 | CP7: 299 | CQ7: 322 | CR7: 158 | CS7: 156 | CT7: 122 | CU7: 106 | CV7: 211 | CW7: 78 | CX7: 102 | CY7: 135 | CZ7: 218 | DA7: 449
A8: 85099B | B8: JUMBO BAG RED RETROSPOT | C8: 1233 | D8: 1303 | E8: 36 | F8: 0 | G8: 1152 | H8: 929 | I8: 627 | J8: 864 | K8: 478 | L8: 546 | M8: 1014 | N8: 613 | O8: 754 | P8: 799 | Q8: 553 | R8: 929 | S8: 587 | T8: 415 | U8: 1004 | V8: 644 | W8: 1538 | X8: 1207 | Y8: 981 | Z8: 618 | AA8: 759 | AB8: 724 | AC8: 966 | AD8: 696 | AE8: 761 | AF8: 1405 | AG8: 688 | AH8: 865 | AI8: 1266 | AJ8: 617 | AK8: 724 | AL8: 924 | AM8: 188 | AN8: 1 | AO8: 1885 | AP8: 1313 | AQ8: 1118 | AR8: 1514 | AS8: 1716 | AT8: 1015 | AU8: 1859 | AV8: 782 | AW8: 515 | AX8: 792 | AY8: 2104 | AZ8: 1213 | BA8: 1223 | BB8: 1744 | BC8: 836 | BD8: 427 | BE8: 170 | BF8: 0 | BG8: 1274 | BH8: 225 | BI8: 588 | BJ8: 500 | BK8: 964 | BL8: 288 | BM8: 984 | BN8: 810 | BO8: 624 | BP8: 738 | BQ8: 1546 | BR8: 1378 | BS8: 1103 | BT8: 975 | BU8: 616 | BV8: 545 | BW8: 385 | BX8: 380 | BY8: 1206 | BZ8: 977 | CA8: 930 | CB8: 273 | CC8: 883 | CD8: 954 | CE8: 841 | CF8: 814 | CG8: 1362 | CH8: 431 | CI8: 732 | CJ8: 540 | CK8: 949 | CL8: 1373 | CM8: 1356 | CN8: 1418 | CO8: 716 | CP8: 552 | CQ8: 720 | CR8: 1659 | CS8: 829 | CT8: 2501 | CU8: 647 | CV8: 1045 | CW8: 499 | CX8: 1061 | CY8: 2099 | CZ8: 1602 | DA8: 753
A9: 84879 | B9: ASSORTED COLOUR BIRD ORNAMENT | C9: 1205 | D9: 1324 | E9: 82 | F9: 0 | G9: 168 | H9: 233 | I9: 897 | J9: 211 | K9: 274 | L9: 504 | M9: 587 | N9: 294 | O9: 735 | P9: 917 | Q9: 550 | R9: 808 | S9: 331 | T9: 736 | U9: 653 | V9: 504 | W9: 919 | X9: 342 | Y9: 899 | Z9: 275 | AA9: 560 | AB9: 309 | AC9: 256 | AD9: 569 | AE9: 252 | AF9: 692 | AG9: 858 | AH9: 400 | AI9: 1043 | AJ9: 621 | AK9: 640 | AL9: 750 | AM9: 664 | AN9: 1000 | AO9: 963 | AP9: 387 | AQ9: 619 | AR9: 1784 | AS9: 773 | AT9: 753 | AU9: 2277 | AV9: 1736 | AW9: 1031 | AX9: 992 | AY9: 5584 | AZ9: 1459 | BA9: 779 | BB9: 971 | BC9: 781 | BD9: 638 | BE9: 40 | BF9: 0 | BG9: 472 | BH9: 434 | BI9: 139 | BJ9: 336 | BK9: 937 | BL9: 160 | BM9: 588 | BN9: 328 | BO9: 213 | BP9: 642 | BQ9: 963 | BR9: 383 | BS9: 585 | BT9: 753 | BU9: 815 | BV9: 612 | BW9: 264 | BX9: 594 | BY9: 1201 | BZ9: 594 | CA9: 565 | CB9: 384 | CC9: 292 | CD9: 446 | CE9: 246 | CF9: 292 | CG9: 460 | CH9: 371 | CI9: 519 | CJ9: 470 | CK9: 3800 | CL9: 1322 | CM9: 548 | CN9: 850 | CO9: 216 | CP9: 488 | CQ9: 907 | CR9: 686 | CS9: 791 | CT9: 573 | CU9: 413 | CV9: 821 | CW9: 777 | CX9: 968 | CY9: 1740 | CZ9: 1310 | DA9: 1026
A10: 22086 | B10: PAPER CHAIN KIT 50'S CHRISTMAS | C10: 661 | D10: 571 | E10: 69 | F10: 0 | G10: 0 | H10: 20 | I10: 3 | J10: 0 | K10: 0 | L10: 0 | M10: 0 | N10: 0 | O10: 3 | P10: 0 | Q10: 12 | R10: 0 | S10: 2 | T10: 0 | U10: 0 | V10: 1 | W10: 18 | X10: 46 | Y10: 6 | Z10: 6 | AA10: 0 | AB10: 4 | AC10: 3 | AD10: 28 | AE10: 305 | AF10: 44 | AG10: 14 | AH10: 2 | AI10: 50 | AJ10: 128 | AK10: 142 | AL10: 74 | AM10: 19 | AN10: 27 | AO10: 3 | AP10: 12 | AQ10: 224 | AR10: 431 | AS10: 494 | AT10: 1516 | AU10: 523 | AV10: 406 | AW10: 466 | AX10: 1543 | AY10: 1674 | AZ10: 1791 | BA10: 1755 | BB10: 1144 | BC10: 1046 | BD10: 597 | BE10: 125 | BF10: 0 | BG10: 16 | BH10: 6 | BI10: 2 | BJ10: 0 | BK10: 0 | BL10: 0 | BM10: 2 | BN10: 2 | BO10: 45 | BP10: 1 | BQ10: 0 | BR10: 42 | BS10: 3 | BT10: 0 | BU10: 0 | BV10: 1 | BW10: 0 | BX10: 4 | BY10: 13 | BZ10: 0 | CA10: 0 | CB10: 0 | CC10: 2 | CD10: 1 | CE10: 6 | CF10: 365 | CG10: 18 | CH10: 10 | CI10: 32 | CJ10: 287 | CK10: 161 | CL10: 22 | CM10: 34 | CN10: 28 | CO10: 191 | CP10: 495 | CQ10: 599 | CR10: 602 | CS10: 359 | CT10: 937 | CU10: 736 | CV10: 756 | CW10: 644 | CX10: 1745 | CY10: 1396 | CZ10: 2153 | DA10: 1691
A11: 79321 | B11: CHILLI LIGHTS | C11: 177 | D11: 171 | E11: 0 | F11: 0 | G11: 15 | H11: 23 | I11: 0 | J11: 0 | K11: 24 | L11: 0 | M11: 0 | N11: 0 | O11: 2 | P11: 0 | Q11: 0 | R11: 0 | S11: 450 | T11: 216 | U11: 91 | V11: 116 | W11: 54 | X11: 62 | Y11: 16 | Z11: 87 | AA11: 69 | AB11: 29 | AC11: 220 | AD11: 25 | AE11: 35 | AF11: 22 | AG11: 88 | AH11: 6 | AI11: 8 | AJ11: 5 | AK11: 16 | AL11: 45 | AM11: 37 | AN11: 70 | AO11: 110 | AP11: 68 | AQ11: 38 | AR11: 107 | AS11: 239 | AT11: 542 | AU11: 152 | AV11: 226 | AW11: 175 | AX11: 123 | AY11: 517 | AZ11: 303 | BA11: 343 | BB11: 848 | BC11: 337 | BD11: 589 | BE11: 60 | BF11: 0 | BG11: 860 | BH11: 175 | BI11: 163 | BJ11: 105 | BK11: 99 | BL11: 192 | BM11: 305 | BN11: 75 | BO11: 39 | BP11: 270 | BQ11: 107 | BR11: 22 | BS11: 85 | BT11: 14 | BU11: 5 | BV11: 4 | BW11: 5 | BX11: 109 | BY11: 187 | BZ11: 44 | CA11: 72 | CB11: 27 | CC11: 91 | CD11: 113 | CE11: 60 | CF11: 113 | CG11: 23 | CH11: 33 | CI11: 133 | CJ11: 650 | CK11: 87 | CL11: 135 | CM11: 62 | CN11: 110 | CO11: 210 | CP11: 71 | CQ11: 262 | CR11: 28 | CS11: 162 | CT11: 51 | CU11: 150 | CV11: 109 | CW11: 431 | CX11: 165 | CY11: 481 | CZ11: 389 | DA11: 959
A12: 22502 | B12: PICNIC BASKET WICKER SMALL | C12: 0 | D12: 0 | E12: 0 | F12: 0 | G12: 0 | H12: 0 | I12: 0 | J12: 0 | K12: 0 | L12: 0 | M12: 0 | N12: 0 | O12: 0 | P12: 0 | Q12: 0 | R12: 0 | S12: 0 | T12: 0 | U12: 0 | V12: 0 | W12: 0 | X12: 0 | Y12: 0 | Z12: 54 | AA12: 95 | AB12: 46 | AC12: 122 | AD12: 63 | AE12: 52 | AF12: 139 | AG12: 81 | AH12: 88 | AI12: 80 | AJ12: 63 | AK12: 41 | AL12: 36 | AM12: 55 | AN12: 24 | AO12: 56 | AP12: 33 | AQ12: 17 | AR12: 103 | AS12: 49 | AT12: 104 | AU12: 31 | AV12: 31 | AW12: 26 | AX12: 32 | AY12: 77 | AZ12: 117 | BA12: 58 | BB12: 112 | BC12: 40 | BD12: 57 | BE12: 10 | BF12: 0 | BG12: 12 | BH12: 27 | BI12: 28 | BJ12: 153 | BK12: 46 | BL12: 24 | BM12: 48 | BN12: 72 | BO12: 45 | BP12: 138 | BQ12: 25 | BR12: 59 | BS12: 48 | BT12: 60 | BU12: 96 | BV12: 54 | BW12: 47 | BX12: 160 | BY12: 213 | BZ12: 93 | CA12: 27 | CB12: 25 | CC12: 95 | CD12: 4 | CE12: 10 | CF12: 1 | CG12: 17 | CH12: 4 | CI12: 14 | CJ12: 7 | CK12: 10 | CL12: 9 | CM12: 7 | CN12: 2 | CO12: 5 | CP12: 0 | CQ12: 2 | CR12: 1 | CS12: 0 | CT12: 0 | CU12: 0 | CV12: 0 | CW12: 0 | CX12: 0 | CY12: 0 | CZ12: 0 | DA12: 0
A13: 22197 | B13: SMALL POPCORN HOLDER | C13: 153 | D13: 643 | E13: 2 | F13: 0 | G13: 21 | H13: 70 | I13: 23 | J13: 619 | K13: 81 | L13: 66 | M13: 12 | N13: 1407 | O13: 133 | P13: 45 | Q13: 810 | R13: 97 | S13: 423 | T13: 716 | U13: 24 | V13: 378 | W13: 500 | X13: 203 | Y13: 178 | Z13: 190 | AA13: 218 | AB13: 139 | AC13: 617 | AD13: 624 | AE13: 167 | AF13: 356 | AG13: 278 | AH13: 764 | AI13: 691 | AJ13: 265 | AK13: 93 | AL13: 549 | AM13: 1025 | AN13: 880 | AO13: 133 | AP13: 262 | AQ13: 532 | AR13: 1709 | AS13: 284 | AT13: 907 | AU13: 344 | AV13: 1237 | AW13: 2581 | AX13: 924 | AY13: 4113 | AZ13: 1745 | BA13: 2190 | BB13: 661 | BC13: 1009 | BD13: 980 | BE13: 250 | BF13: 0 | BG13: 794 | BH13: 342 | BI13: 261 | BJ13: 351 | BK13: 105 | BL13: 239 | BM13: 1037 | BN13: 1312 | BO13: 365 | BP13: 779 | BQ13: 583 | BR13: 237 | BS13: 1042 | BT13: 552 | BU13: 784 | BV13: 231 | BW13: 310 | BX13: 372 | BY13: 375 | BZ13: 1298 | CA13: 4561 | CB13: 533 | CC13: 410 | CD13: 437 | CE13: 342 | CF13: 430 | CG13: 634 | CH13: 157 | CI13: 609 | CJ13: 436 | CK13: 2177 | CL13: 1732 | CM13: 517 | CN13: 826 | CO13: 954 | CP13: 516 | CQ13: 552 | CR13: 673 | CS13: 1661 | CT13: 828 | CU13: 881 | CV13: 1164 | CW13: 2739 | CX13: 1144 | CY13: 3825 | CZ13: 3129 | DA13: 2754
A14: 22386 | B14: JUMBO BAG PINK POLKADOT | C14: 0 | D14: 0 | E14: 0 | F14: 0 | G14: 0 | H14: 0 | I14: 0 | J14: 114 | K14: 336 | L14: 311 | M14: 720 | N14: 551 | O14: 306 | P14: 402 | Q14: 179 | R14: 467 | S14: 331 | T14: 164 | U14: 217 | V14: 248 | W14: 384 | X14: 751 | Y14: 289 | Z14: 511 | AA14: 277 | AB14: 236 | AC14: 427 | AD14: 361 | AE14: 460 | AF14: 595 | AG14: 331 | AH14: 240 | AI14: 728 | AJ14: 171 | AK14: 354 | AL14: 460 | AM14: 677 | AN14: 338 | AO14: 652 | AP14: 617 | AQ14: 305 | AR14: 354 | AS14: 518 | AT14: 258 | AU14: 917 | AV14: 144 | AW14: 135 | AX14: 345 | AY14: 657 | AZ14: 699 | BA14: 272 | BB14: 261 | BC14: 270 | BD14: 105 | BE14: 9 | BF14: 0 | BG14: 523 | BH14: 323 | BI14: 73 | BJ14: 199 | BK14: 225 | BL14: 95 | BM14: 409 | BN14: 260 | BO14: 174 | BP14: 374 | BQ14: 1083 | BR14: 586 | BS14: 675 | BT14: 115 | BU14: 119 | BV14: 155 | BW14: 282 | BX14: 154 | BY14: 401 | BZ14: 179 | CA14: 556 | CB14: 400 | CC14: 468 | CD14: 243 | CE14: 611 | CF14: 455 | CG14: 454 | CH14: 315 | CI14: 307 | CJ14: 403 | CK14: 382 | CL14: 551 | CM14: 586 | CN14: 619 | CO14: 248 | CP14: 657 | CQ14: 478 | CR14: 809 | CS14: 665 | CT14: 1647 | CU14: 237 | CV14: 334 | CW14: 639 | CX14: 307 | CY14: 416 | CZ14: 519 | DA14: 253
A15: 21137 | B15: BLACK RECORD COVER FRAME | C15: 319 | D15: 232 | E15: 4 | F15: 0 | G15: 18 | H15: 61 | I15: 64 | J15: 59 | K15: 231 | L15: 24 | M15: 73 | N15: 175 | O15: 100 | P15: 33 | Q15: 56 | R15: 75 | S15: 104 | T15: 100 | U15: 0 | V15: 8 | W15: 346 | X15: 132 | Y15: 29 | Z15: 80 | AA15: 35 | AB15: 55 | AC15: 210 | AD15: 160 | AE15: 56 | AF15: 49 | AG15: 144 | AH15: 76 | AI15: 32 | AJ15: 388 | AK15: 35 | AL15: 25 | AM15: 72 | AN15: 48 | AO15: 15 | AP15: 128 | AQ15: 28 | AR15: 173 | AS15: 40 | AT15: 638 | AU15: 401 | AV15: 310 | AW15: 182 | AX15: 13 | AY15: 928 | AZ15: 191 | BA15: 190 | BB15: 658 | BC15: 577 | BD15: 575 | BE15: 55 | BF15: 0 | BG15: 177 | BH15: 20 | BI15: 24 | BJ15: 1 | BK15: 592 | BL15: 0 | BM15: 40 | BN15: 69 | BO15: 0 | BP15: 6 | BQ15: 120 | BR15: 117 | BS15: 50 | BT15: 11 | BU15: 84 | BV15: 110 | BW15: 38 | BX15: 395 | BY15: 81 | BZ15: 36 | CA15: 0 | CB15: 504 | CC15: 18 | CD15: 865 | CE15: 131 | CF15: 236 | CG15: 90 | CH15: 100 | CI15: 254 | CJ15: 116 | CK15: 0 | CL15: 73 | CM15: 270 | CN15: 19 | CO15: 176 | CP15: 104 | CQ15: 210 | CR15: 34 | CS15: 202 | CT15: 305 | CU15: 21 | CV15: 184 | CW15: 95 | CX15: 433 | CY15: 857 | CZ15: 255 | DA15: 580
A16: 20725 | B16: LUNCH BAG RED RETROSPOT | C16: 324 | D16: 236 | E16: 111 | F16: 0 | G16: 314 | H16: 190 | I16: 481 | J16: 504 | K16: 324 | L16: 211 | M16: 442 | N16: 263 | O16: 404 | P16: 337 | Q16: 375 | R16: 176 | S16: 415 | T16: 296 | U16: 475 | V16: 294 | W16: 313 | X16: 711 | Y16: 516 | Z16: 251 | AA16: 662 | AB16: 297 | AC16: 309 | AD16: 459 | AE16: 511 | AF16: 536 | AG16: 211 | AH16: 570 | AI16: 486 | AJ16: 394 | AK16: 694 | AL16: 604 | AM16: 934 | AN16: 448 | AO16: 373 | AP16: 479 | AQ16: 304 | AR16: 615 | AS16: 347 | AT16: 249 | AU16: 521 | AV16: 139 | AW16: 275 | AX16: 514 | AY16: 262 | AZ16: 666 | BA16: 327 | BB16: 291 | BC16: 279 | BD16: 187 | BE16: 44 | BF16: 0 | BG16: 361 | BH16: 642 | BI16: 127 | BJ16: 166 | BK16: 417 | BL16: 254 | BM16: 291 | BN16: 369 | BO16: 173 | BP16: 148 | BQ16: 277 | BR16: 379 | BS16: 584 | BT16: 247 | BU16: 304 | BV16: 368 | BW16: 164 | BX16: 289 | BY16: 884 | BZ16: 444 | CA16: 684 | CB16: 183 | CC16: 584 | CD16: 447 | CE16: 225 | CF16: 302 | CG16: 430 | CH16: 230 | CI16: 491 | CJ16: 385 | CK16: 600 | CL16: 719 | CM16: 432 | CN16: 341 | CO16: 198 | CP16: 323 | CQ16: 319 | CR16: 480 | CS16: 266 | CT16: 292 | CU16: 422 | CV16: 276 | CW16: 314 | CX16: 323 | CY16: 456 | CZ16: 649 | DA16: 276
... A154: 21791 | B154: VINTAGE HEADS AND TAILS CARD GAME | C154: 205 | D154: 241 | E154: 20 | F154: 0 | G154: 234 | H154: 38 | I154: 185 | J154: 64 | K154: 92 | L154: 80 | M154: 99 | N154: 191 | O154: 107 | P154: 64 | Q154: 53 | R154: 239 | S154: 117 | T154: 86 | U154: 64 | V154: 358 | W154: 56 | X154: 32 | Y154: 156 | Z154: 101 | AA154: 47 | AB154: 58 | AC154: 247 | AD154: 127 | AE154: 131 | AF154: 43 | AG154: 118 | AH154: 52 | AI154: 65 | AJ154: 40 | AK154: 69 | AL154: 74 | AM154: 53 | AN154: 289 | AO154: 43 | AP154: 144 | AQ154: 111 | AR154: 152 | AS154: 623 | AT154: 270 | AU154: 591 | AV154: 310 | AW154: 243 | AX154: 233 | AY154: 467 | AZ154: 569 | BA154: 204 | BB154: 517 | BC154: 608 | BD154: 123 | BE154: 4 | BF154: 0 | BG154: 88 | BH154: 66 | BI154: 35 | BJ154: 169 | BK154: 38 | BL154: 51 | BM154: 66 | BN154: 114 | BO154: 45 | BP154: 3 | BQ154: 203 | BR154: 54 | BS154: 206 | BT154: 50 | BU154: 113 | BV154: 39 | BW154: 31 | BX154: 13 | BY154: 82 | BZ154: 266 | CA154: 3 | CB154: 39 | CC154: 93 | CD154: 129 | CE154: 55 | CF154: 77 | CG154: 55 | CH154: 10 | CI154: 59 | CJ154: 59 | CK154: 695 | CL154: 179 | CM154: 127 | CN154: 85 | CO154: 227 | CP154: 148 | CQ154: 53 | CR154: 190 | CS154: 79 | CT154: 224 | CU154: 127 | CV154: 211 | CW154: 81 | CX154: 161 | CY154: 494 | CZ154: 586 | DA154: 245

Sheet SKU_Data
A1: SKU facts · DATA
A2: From notebook 01 (last 52 weeks). abc_xyz_python is only used to check that the Excel formulas give the same classes.
A4: Stock code | B4: Description | C4: Sales value 52w (£) | D4: Units sold 52w | E4: Net sales value 52w (£) | F4: abc_xyz_python
A5: 22423 | B5: REGENCY CAKESTAND 3 TIER | C5: 169725.02 | D5: 13544 | E5: 160270.37 | F5: AX
A6: 85123A | B6: WHITE HANGING HEART T-LIGHT HOLDER | C6: 104348.92 | D6: 37158 | E6: 97727.17 | F6: AY
A7: 47566 | B7: PARTY BUNTING | C7: 98526.63 | D7: 18159 | E7: 97325.28 | F7: AX
A8: 85099B | B8: JUMBO BAG RED RETROSPOT | C8: 92828.38 | D8: 47925 | E8: 90869.71 | F8: AX
A9: 84879 | B9: ASSORTED COLOUR BIRD ORNAMENT | C9: 56729.21 | D9: 35017 | E9: 56285.16 | F9: AY
A10: 22086 | B10: PAPER CHAIN KIT 50'S CHRISTMAS | C10: 56888.3 | D10: 16740 | E10: 55727.95 | F10: AZ
A11: 79321 | B11: CHILLI LIGHTS | C11: 51868.86 | D11: 9955 | E11: 51524.91 | F11: AY
A12: 22502 | B12: PICNIC BASKET WICKER SMALL | C12: 51700.84 | D12: 1982 | E12: 51315.59 | F12: AZ
A13: 22197 | B13: SMALL POPCORN HOLDER | C13: 44794.83 | D13: 49361 | E13: 44426.46 | F13: AY
A14: 22386 | B14: JUMBO BAG PINK POLKADOT | C14: 41575.29 | D14: 21064 | E14: 40758.71 | F14: AX
A15: 21137 | B15: BLACK RECORD COVER FRAME | C15: 34656.65 | D15: 9990 | E15: 34577.75 | F15: AY
A16: 20725 | B16: LUNCH BAG RED RETROSPOT | C16: 34754.01 | D16: 18912 | E16: 33896.01 | F16: AX
... A154: 21791 | B154: VINTAGE HEADS AND TAILS CARD GAME | C154: 10029.99 | D154: 7511 | E154: 9984.99 | F154: CY

Sheet Model_Params
A1: Fitted smoothing parameters · DATA
A2: From notebook 02: for each SKU the α (SES) and α, β, γ (Holt-Winters) with the lowest one-step error on the training weeks 1-91.
A4: Stock code | B4: SES α | C4: HW α (level) | D4: HW β (trend) | E4: HW γ (season)
A5: 22423 | B5: 0.35 | C5: 0.3 | D5: 0 | E5: 0
A6: 85123A | B6: 0.5 | C6: 0.05 | D6: 0.05 | E6: 0
A7: 47566 | B7: 0.35 | C7: 0.1 | D7: 0.05 | E7: 0
A8: 85099B | B8: 0.15 | C8: 0.05 | D8: 0 | E8: 0
A9: 84879 | B9: 0.25 | C9: 0.05 | D9: 0 | E9: 0
A10: 22086 | B10: 0.95 | C10: 0.05 | D10: 0 | E10: 0
A11: 79321 | B11: 0.25 | C11: 0.2 | D11: 0 | E11: 0
A12: 22502 | B12: 0.35 | C12: 0.3 | D12: 0 | E12: 0
A13: 22197 | B13: 0.15 | C13: 0.05 | D13: 0.05 | E13: 0
A14: 22386 | B14: 0.25 | C14: 0.05 | D14: 0 | E14: 0
A15: 21137 | B15: 0.2 | C15: 0.05 | D15: 0 | E15: 0
A16: 20725 | B16: 0.15 | C16: 0.05 | D16: 0.05 | E16: 0
... A154: 21791 | B154: 0.3 | C154: 0.05 | D154: 0 | E154: 0

Sheet Forecast_Future
A1: Future forecasts, weeks 104-115 (28-Nov-2011 to 13-Feb-2012) · DATA
A2: From notebook 02: all four methods for every SKU, fitted on all 103 weeks. The Policy sheet adds up the first 'lead time' weeks with SUMIFS.
A4: Stock code | B4: Method | C4: Weeks ahead | D4: Week no | E4: Forecast units
A5: 15036 | B5: Holt-Winters | C5: 1 | D5: 104 | E5: 166.4519
A6: 15036 | B6: Holt-Winters | C6: 2 | D6: 105 | E6: 58.3186
A7: 15036 | B7: Holt-Winters | C7: 3 | D7: 106 | E7: 47.9519
A8: 15036 | B8: Holt-Winters | C8: 4 | D8: 107 | E8: 53.1186
A9: 15036 | B9: Holt-Winters | C9: 5 | D9: 108 | E9: 49.6186
A10: 15036 | B10: Holt-Winters | C10: 6 | D10: 109 | E10: 44.3408
A11: 15036 | B11: Holt-Winters | C11: 7 | D11: 110 | E11: 43.7853
A12: 15036 | B12: Holt-Winters | C12: 8 | D12: 111 | E12: 60.563
A13: 15036 | B13: Holt-Winters | C13: 9 | D13: 112 | E13: 60.563
A14: 15036 | B14: Holt-Winters | C14: 10 | D14: 113 | E14: 82.1186
A15: 15036 | B15: Holt-Winters | C15: 11 | D15: 114 | E15: 72.3408
A16: 15036 | B16: Holt-Winters | C16: 12 | D16: 115 | E16: 152.0075
... A7204: 85152 | B7204: SES | C7204: 12 | D7204: 115 | E7204: 149.1897
